Workbook
Name Slicer_Candidate_Status: #N/A
Name Slicer_Year_of_Profile_Submission: #N/A

Sheet Summary
B3: Count of Account | C3: Candidate Status | D3: Mandatory Skill
Y4: Total | Z4: Active | AC4: Active Total | AD4: C#.NET,.NET Core,MVC,REST API/Web APIs,JavaScript | AE4: C#.NET,.NET Core,MVC,REST API/Web APIs,JavaScript Total | AF4: Client IP | BA4: Client IP Total | BB4: Client Reject | CP4: Client Reject Total | CQ4: Dropped | FW4: Dropped Total | FX4: Duplicate | FY4: Duplicate Total | FZ4: Feedback pending from client | GC4: Feedback pending from client Total | GD4: Final Select | GE4: Final Select Total | GF4: Hold | GH4: Hold Total | GI4: Joined | GO4: Joined Total | GP4: L2 reject | GQ4: L2 reject Total | GR4: Level 1 interview Done | GS4: Level 1 interview Done Total | GT4: No show | GW4: No show Total | GX4: Not my requirement | GY4: Not my requirement Total | GZ4: Not responding the calls | HA4: Not responding the calls Total | HB4: Offered | HD4: Offered Total | HE4: On Hold | HJ4: On Hold Total | HK4: Position closed | HN4: Position closed Total | HO4: Position Hold | HP4: Position Hold Total | HQ4: Position hold | HR4: Position hold Total | HS4: Rec Screen IP | HY4: Rec Screen IP Total | HZ4: Rec Screen Reject | IF4: Rec Screen Reject Total | IG4: Req closed | II4: Req closed Total | IJ4: Sceening IP | IK4: Sceening IP Total | IL4: Schduled | IN4: Schduled Total | IO4: Screen IP | IT4: Screen IP Total | IU4: Screen Reject | LI4: Screen Reject Total | LJ4: Screen reject | LM4: Screen reject Total | LN4: Screen reject from client | LO4: Screen reject from client Total | LP4: Screening IP | OF4: Screening IP Total | OG4: Screening IP | OH4: Screening IP Total | OI4: Sourced | OM4: Sourced Total | ON4: Submitted | OY4: Submitted Total | OZ4: TBO | PE4: TBO Total | PF4: Tech 1 Reject | PH4: Tech 1 Reject Total | PI4: Tech1 IP | QR4: Tech1 IP Total | QS4: Tech1 Reject | RY4: Tech1 Reject Total | RZ4: Tech2 IP | SH4: Tech2 IP Total | SI4: Tech2 Reject | SN4: Tech2 Reject Total | SO4: Uploaded | SP4: Uploaded Total | SQ4: (blank) | TB4: (blank) Total | TC4: Grand Total
B5: Recruiter Name | C5: . Net Developer | D5: .net core | E5: 5-8y Oracle DBA with MongoDB | F5: DevOps | G5: Dot Net | H5: DOTNET | I5: DW/EBI | J5: Hadoop developer | K5: J2EE,SpringBoot, ,Angular, | L5: Java | M5: Java | N5: Java Developer | O5: Java,Spring,JSP,Apache,Tomcat,SOAP/REST | P5: JAVA/J2EE | Q5: Java/J2EE,Core Java,Spring Boot | R5: Mobility | S5: Oracle | T5: PL SQL | U5: PM | V5: Product Manager | W5: RPA | X5: SDET | Z5: .Netcore | AA5: .NetCore,Angular | AB5: It Security | AD5: Digizura Technologies | AF5: .net core | AG5: 2-5 yrs C# Selenium | AH5: 4y+ Andriod Developer with Flutter | AI5: 8-12y NodeJS,Angular,Typescript,REST API,Automation Web Services,Cloud,Kafka,RabbitMQ,NGNIX | AJ5: Android Developer | AK5: Asp.Net MVC, Entity Framework,Web api | AL5: C#.NET, Desktop app | AM5: Cyber Security | AN5: Dell Boomi | AO5: Dell Boomi | AP5: Dot Net | AQ5: DOTNET | AR5: Dotnet Core | AS5: Java,Selenium,API | AT5: Mobility | AU5: NodeJS Developer,JavaScript,Postgres,MySQL,Redis(No SQL)- | AV5: Product Manager with Mobile, Web | AW5: Product Manager with Mobile, Web | AX5: SDET | AY5: SW Automation Testing | AZ5: UI UX Designer | BB5: .NET,SQL,WEB API | BC5: Andriod Developer with Flutter | BD5: Android Developer | BE5: Asp.Net MVC, Entity Framework,Web api | BF5: Automation Testing | BG5: Azure/AWS DevOps,Infrastructure ,Terraform,Scripting | BH5: BRM | BI5: C# SELENIUM | BJ5: C#,.NET core | BK5: C#.NET, Desktop app | BL5: C#.Net,.NET Core, Angular | BM5: c,c++,linux | BN5: Cyber Recovery | BO5: DBA | BP5: Dot Net | BQ5: DOT NET DEVELOPER | BR5: DOTNET | BS5: DW/EBI | BT5: Install shield | BU5: iOS | BV5: Java | BW5: JAVA , Strong exp in spring boot | BX5: Java, Spring, Springboot, Hibernate | BY5: Java,Selenium,API | BZ5: Java/J2EE,Spring Boot, Microservices | CA5: Manual Tesing, QA | CB5: Mobile Automation | CC5: Mobility | CD5: MSSQL,SQL | CE5: Oracle BRM Testing | CF5: PM | CG5: Power BI | CH5: Product Manager | CI5: Project Manager | CJ5: Project Manager ,SDLC,AGILE | CK5: Project manager with release mngt ITIL | CL5: RPA | CM5: SDET | CN5: Technical PM | CO5: TPM(Technical Project Manager) | CQ5: - 8+ yrs java springboot microservices | CR5: .Net Core,Angular | CS5: .NET Core,Spring Boot,Microservices,Kafka | CT5: .NET, microservices | CU5: .NET,.NET Core,Spring Boot,Microservices,Kafka | CV5: .NET,SQL,WEB API | CW5: 2-5y C/C++ on Linux/Windows,Unit Testing,Automation | CX5: 4y+ Andriod Developer with Flutter | CY5: 4y+ Java/J2EE,Microserices,SpringBoot,Node JS | CZ5: 5-8y Java/J2EE,Spring boot and Nodejs | DA5: 5-8y Java/J2EE,Spring Boot,Hibernate,Restful Services,Junit - | DB5: 8-.NET Core,Spring Boot,Microservices,Kafka | DC5: 8-12y Full Stack Testing,Automation Testing,UX/API Layer,SQL | DD5: Ansible,GitLab,Jenkins | DE5: Azure/AWS DevOps,Infrastructure ,Terraform,Scripting | DF5: BRM | DG5: C# .Net, .NET Core, Web Api, Angular | DH5: C#.NET,.NET Core, Web API, MVC,Angular,Jquery | DI5: C#.NET,.NET Core, Web API, MVC,Angular,Jquery role | DJ5: C#.NET,.NET Core, Web API, MVC,Angular,Jquery role . | DK5: C,C++ Programming with Linux | DL5: c,c++,linux | DM5: C/C++ | DN5: Cyber Security | DO5: DevOps | DP5: Dot Net | DQ5: DOTNET | DR5: Dotnet Core | DS5: Install shield | DT5: iOS | DU5: IOS Developer | DV5: IOS Flutter | DW5: Java | DX5: JAVA , Strong exp in spring boot | DY5: JAVA ,Spring boot | DZ5: Java Developer | EA5: Java Selenium | EB5: Java, Springboot, Microservices | EC5: Java, springboot, Microservices, MongoDB, Node.Js | ED5: Java,Selenium,API | EE5: Java,Selenium,API | EF5: java,selenium,API testing | EG5: Java,Spring,Oracle | EH5: Java,Springboot | EI5: Java/J2EE,Microserices,SpringBoot,Node JS, | EJ5: Java/J2EE,Spring Boot | EK5: Java/J2EE,Spring Boot, Microservices | EL5: Mobile Automation | EM5: Mobile automation testing | EN5: Mobility | EO5: MS Power BI Developer | EP5: MSSQL,SQL | EQ5: Mysql | ER5: NET Core,Spring Boot,Microservices | ES5: Networking | ET5: Node JS | EU5: Oracle BRM Testing | EV5: PL SQL Developer | EW5: PL/SQL | EX5: PLSQL Develop, Informatica and Control – M | EY5: PLSQL Developer, Informatica and Control – M | EZ5: PM | FA5: Power BI | FB5: Product designer | FC5: Product Manager | FD5: Project Manager | FE5: Project Manager with Java/Android | FF5: Python,Linux | FG5: Python,Selenium, Robot Framework | FH5: Python,Selenium,API | FI5: Python/C#, Selenium | FJ5: QA , Manual tester role | FK5: RPA Developer | FL5: SDET | FM5: Selenium,Appium | FN5: Senior Java Developer | FO5: SQL,Stored procedures,t-sql | FP5: Testing | FQ5: UI Developer | FR5: UI Developer ,Angular | FS5: UI/UX | FT5: UI/UX role | FU5: Vulnerability | FV5: Windows Install Shield Developer | FX5: Dotnet Core | FZ5: Java | GA5: Java Developer | GB5: JAVA FULL STACK DEVELOPER | GD5: Plsql developer | GF5: DW/EBI | GG5: Power BI | GI5: .Dot Net,Mvc,Sql | GJ5: .Net Core,Angular | GK5: Dotnet Developer | GL5: Mobility | GM5: PM | GN5: UI/UX Designer | GP5: DOTNET | GR5: Dotnet Core | GT5: Dotnet Core | GU5: Plsql developer | GV5: Selenium SDET | GX5: Cyber Security | GZ5: Java | HB5: DOTNET | HC5: SDET | HE5: C,C++ | HF5: Devops Engineer | HG5: Java,Springboot, kafka | HH5: Product Manager | HI5: Python,Selenium,Robot Framework | HK5: PL/SQL | HL5: PLSQL Dev | HM5: Plsql developer | HO5: PT | HQ5: Java | HS5: .Net Core,Angular | HT5: C#.NET,.NET Core,Web API,,Web Services | HU5: Data Scientist Python | HV5: Dell Boomi,API Gateway,B2B/EDI | HW5: Product Manager Jira | HX5: SDETAutomation & Manual Testing, | HZ5: Java,Selenium,API | IA5: Product Manager with Mobile, Web | IB5: Project Manager | IC5: python | ID5: SDET | IE5: SDET | IG5: Cyber Security | IH5: UI/UX | IJ5: SDET | IL5: Dotnet Core | IM5: Java | IO5: 2-5y C#, Selenium with API Testing | IP5: 4y+ Mobile and Web application Automation | IQ5: 4y+ Mobile and Web application Automation testing | IR5: 5y Project Manager with Release Management and ITIL | IS5: 8-12y5-8y Developer | IU5: .net core | IV5: .Net Core,Angular | IW5: 2-5y Windows Install Shield Developer | IX5: 4y+ Andriod Developer with Flutter | IY5: 4y+ iOS Developer | IZ5: 4y+ Java/J2EE,Microserices,SpringBoot,Node JS | JA5: 5-8y Java/.NET,Selenium,eCommerce Domain | JB5: 5-8y Java/J2EE,Spring Boot,Hibernate,Restful Services,JUnit | JC5: 5-8y Java/J2EE,Spring Boot,Hibernate,Restful Services,Junit - | JD5: 8-10y Project Manager with Cloud-Native Apps and Devops Experience | JE5: Andriod Developer with Flutter | JF5: Android Developer | JG5: Asp.Net MVC, Entity Framework,Web api | JH5: BRM | JI5: C#.NET,.NET Core, Web API, MVC,Angular,Jquery role . | JJ5: C,C++ | JK5: C/C++ | JL5: Cyber Security | JM5: Cybersecurity | JN5: Dell Boomi | JO5: Dot Net | JP5: DOTNET | JQ5: iOS | JR5: Java | JS5: Java Developer | JT5: Java,Nodejs | JU5: Java,Springboot | JV5: Kafka | JW5: Linux | JX5: Manual and Automation Testing ,Server Hardware Testing | JY5: Mobile Automation | JZ5: Mobile automation testing | KA5: MongoDB | KB5: NET Core,Spring Boot,Microservices | KC5: Node JS | KD5: PL SQL Dev | KE5: PL/SQL | KF5: Plsql developer | KG5: PM | KH5: Power BI | KI5: Product Manager | KJ5: Product Manager with Mobile, Web | KK5: Project Manager | KL5: Project Manager | KM5: Project Manager ,SDLC,AGILE | KN5: Project Manager with Java/Android | KO5: Project manager with release mngt ITIL | KP5: python | KQ5: QA , Manual tester role | KR5: QA , Manual tester role:- | KS5: RPA Developer | KT5: RPA, Automation Anywhere,UiPath | KU5: SDET | KV5: SDET - Automation Testing,Selenium,Appium,Java | KW5: Selenium SDET | KX5: Selenium,Appium | KY5: Server | KZ5: SQL,Stored procedures,t-sql | LA5: Technical Project Manager | LB5: UI | LC5: UI Developer | LD5: UI Developer ,Angular | LE5: UI/UX | LF5: UI/UX Designer | LG5: Vulnerability | LH5: Windows Install Shield Developer | LJ5: .net core | LK5: Java | LL5: SDET | LN5: Java,Selenium | LP5: .net | LQ5: .net core | LR5: .Net Core; Angular | LS5: .NET Developer | LT5: 3y SW Automation Testing,Python-Robot Framework or C#-Selenium | LU5: 8-12y Full Stack Testing,Automation Testing,UX/API Layer,SQL | LV5: 8y+ Java,IBM MDM Tool - IBM Infosphere,PLSQL | LW5: Adobe Experience Manager | LX5: ANGULAR, NODE JS,TYPE SCRIPT | LY5: Boomi | LZ5: Boomi,Javascript | MA5: C#, Dot Net (5-8 Yrs) | MB5: C#, Selenium with API testing | MC5: C#, Selenium with API Testing | MD5: C#, Selenium, API Testing | ME5: C#.NET Core, Angular | MF5: C#.NET,.NET Core,MVC,REST API/Web APIs,JavaScript/JQuery/AJAX/Bootstrap,SQL Server,CI-CD pipeline | MG5: Data Science | MH5: Data Scientist | MI5: Devops,Docker,Kubernete,Linux | MJ5: Dot Net | MK5: DOTNET | ML5: Dotnet Core | MM5: DW/EBI | MN5: Governance,Risk Management,Compliance | MO5: GPU Driver Engineer | MP5: Hadoop developer | MQ5: iMobile Developer with iOS Developer | MR5: Informatica power center | MS5: Infrastructure Engineer | MT5: IT Secruity | MU5: It Security | MV5: Java | MW5: Java Backend developer | MX5: Java Developer | MY5: Java Selenium | MZ5: JAVA/J2EE | NA5: Java/J2EE | NB5: Java/J2EE,Microserices,SpringBoot,Node JS | NC5: Junior DW/EBI | ND5: Mobile Automation | NE5: MongoDB | NF5: Node JS | NG5: Oracle PLSQL with ORACLE EBS | NH5: Oracle SOA | NI5: PLSQL Dev | NJ5: PM | NK5: Power BI | NL5: Power shell | NM5: Powershell | NN5: Product Manager | NO5: Project Manager | NP5: python | NQ5: Python,Selenium,API | NR5: RPA | NS5: RPA Developer | NT5: SDET | NU5: Selenium SDET | NV5: Senior DW/EBI | NW5: Tableau | NX5: UAT Automation | NY5: UI | NZ5: UI +AngularJS Developer | OA5: UI Developer | OB5: UI/UX(Node.js,typescript,Angular) | OC5: Unit Testing | OD5: UX Designer | OE5: Windows Installer | OG5: C#, DotNet (8 -12 Yrs) | OI5: DW/EBI | OJ5: ELK | OK5: I Mobile& IOS Developer | OL5: iOS | ON5: DevOps | OO5: DW/EBI | OP5: Java Developer | OQ5: Mobility | OR5: Node + Angular developer | OS5: PM | OT5: Product Manager | OU5: SDET | OV5: Selenium,Appium,Java | OW5: Tandem | OX5: UI/UX | OZ5: IOS Developer | PA5: Java | PB5: Java Fullstack Developer | PC5: Oracle BRM Testing | PD5: SDET | PF5: DevOps | PG5: Java/J2EE,Spring Boot | PI5: Java/J2EE,Spring Boot, Elastic search- | PJ5: .net core | PK5: .Net Core Full Stack | PL5: .Net Core,Angular | PM5: .Net Fullstack | PN5: .NET,SQL,WEB API | PO5: .Netcore | PP5: Ansible,GitLab,Jenkins | PQ5: Automation Engineer - SDET | PR5: C# .Net, .NET Core, Web Api, Angular | PS5: C#.NET, Windows internals, Desktop application | PT5: C#/Java,Selenium | PU5: Cyber Security | PV5: Data Scientist | PW5: DevOps | PX5: Dot Net | PY5: DOTNET | PZ5: Hadoop developer | QA5: IOS Developer | QB5: iOS Develper | QC5: Java | QD5: Java Developer | QE5: Java,Selenium | QF5: Java,Selenium,API | QG5: Java,Selenium,Automation | QH5: Plsql developer | QI5: PM | QJ5: Powershell | QK5: Product Manager | QL5: Project Manager | QM5: RPA | QN5: SDET | QO5: Selenium SDET | QP5: SW Automation Testing | QQ5: Vulnerability | QS5: Java/J2EE,Spring Boot,Hibernate,Restful Services,JUnit | QT5: .net | QU5: .Net Core,Angular | QV5: .Net Developer | QW5: .NET,SQL,WEB API | QX5: 5-8y Java/.NET,Selenium,eCommerce Domain | QY5: 5-8y Java/J2EE,Spring Boot,Hibernate,Restful Services,JUnit | QZ5: C#,Selenium | RA5: Dot Net | RB5: DOTNET | RC5: iOS | RD5: IOS Developer | RE5: Java | RF5: JAVA , Strong exp in spring boot | RG5: Java Developer | RH5: Java Selenium | RI5: Java, Spring, Springboot | RJ5: Java, Springboot, Microservices, Kafka MongoDB | RK5: Java,Selenium | RL5: Java,Selenium,API | RM5: Java,Selenium,API | RN5: java,selenium,API testing | RO5: Java,Springboot | RP5: Java/J2EE,Core Java | RQ5: Java/J2EE,Spring Boot, React | RR5: java/J2EE,Spring Boot,Hibernate,Restful Services,JUnit | RS5: Python,Selenium,API | RT5: SDET | RU5: UI Developer | RV5: UI Developer ,Angular | RW5: UI/UX | RX5: Windows Install Shield Developer | RZ5: .Net Core,Angular | SA5: .NET,SQL,WEB API | SB5: Java | SC5: Java,Selenium,API | SD5: UI Developer | SE5: UI Developer ,Angular | SF5: UI Developer with Typescript,Angular,Angular JS,React JS | SG5: UI/UX | SI5: .Net Core,Angular | SJ5: .NET Core,Spring Boot,Microservices,Kafka | SK5: 5-8y Java/J2EE,Spring Boot,Hibernate,Restful Services,Junit - | SL5: DOTNET | SM5: Java | SO5: C#, DotNet | SQ5: .NET Developer | SR5: .NET Full Stack Developer | SS5: C#, .NET,.NET Core,MVC,REST API OR Web APIs, JavaScript | ST5: C#, DotNet (5-8 Yrs) | SU5: C#, Selenium, API Testing | SV5: Dot Net | SW5: DOTNET | SX5: Informatica Power center , writing SQL queries | SY5: Java Selenium | SZ5: SDET | TA5: (blank)
B6: Febha John | AH6: 1 | AJ6: 1 | AM6: 2 | AP6: 1 | AQ6: 2 | AR6: 2 | AU6: 2 | AY6: 1 | BA6: 12 | BB6: 3 | BC6: 2 | BD6: 1 | BF6: 2 | BH6: 2 | BN6: 2 | BR6: 1 | BT6: 1 | BU6: 1 | BV6: 5 | BW6: 1 | BY6: 1 | CB6: 3 | CC6: 4 | CD6: 3 | CE6: 2 | CF6: 2 | CG6: 1 | CH6: 1 | CJ6: 2 | CK6: 1 | CL6: 2 | CP6: 43 | CQ6: 2 | CR6: 8 | CS6: 1 | CT6: 2 | CU6: 1 | CV6: 3 | CW6: 3 | CX6: 1 | CY6: 1 | CZ6: 1 | DA6: 5 | DB6: 1 | DC6: 2 | DD6: 3 | DE6: 4 | DF6: 1 | DG6: 1 | DN6: 2 | DO6: 5 | DP6: 1 | DQ6: 13 | DR6: 6 | DS6: 3 | DT6: 3 | DU6: 4 | DV6: 1 | DW6: 21 | DX6: 4 | DY6: 4 | DZ6: 4 | EB6: 1 | EC6: 1 | ED6: 8 | EE6: 5 | EF6: 5 | EG6: 3 | EH6: 4 | EI6: 1 | EJ6: 1 | EK6: 1 | EL6: 4 | EM6: 1 | EN6: 5 | EO6: 4 | EP6: 3 | EQ6: 2 | ER6: 3 | ES6: 4 | ET6: 1 | EU6: 1 | EZ6: 3 | FA6: 1 | FB6: 4 | FC6: 3 | FD6: 2 | FE6: 1 | FF6: 3 | FG6: 2 | FI6: 2 | FK6: 1 | FL6: 9 | FM6: 1 | FP6: 7 | FQ6: 6 | FR6: 9 | FS6: 1 | FU6: 2 | FV6: 4 | FW6: 230 | GI6: 1 | GJ6: 1 | GK6: 1 | GL6: 1 | GM6: 1 | GN6: 1 | GO6: 6 | HE6: 2 | HG6: 1 | HH6: 3 | HI6: 3 | HJ6: 9 | IP6: 3 | IQ6: 4 | IR6: 2 | IS6: 2 | IT6: 11 | IV6: 2 | IW6: 2 | IX6: 2 | IY6: 2 | IZ6: 1 | JA6: 1 | JB6: 1 | JC6: 2 | JD6: 5 | JE6: 1 | JF6: 1 | JH6: 5 | JJ6: 1 | JO6: 1 | JQ6: 1 | JR6: 8 | JS6: 3 | JT6: 1 | JU6: 2 | JW6: 1 | JX6: 2 | JY6: 4 | JZ6: 2 | KB6: 1 | KC6: 1 | KG6: 8 | KH6: 1 | KI6: 3 | KK6: 2 | KL6: 2 | KM6: 5 | KN6: 2 | KO6: 3 | KS6: 3 | KT6: 2 | KU6: 1 | KV6: 1 | KX6: 1 | LA6: 4 | LC6: 1 | LD6: 1 | LE6: 2 | LF6: 1 | LH6: 1 | LI6: 97 | LT6: 4 | NB6: 2 | ND6: 3 | NF6: 2 | OE6: 2 | OF6: 13 | OO6: 3 | OP6: 1 | OQ6: 3 | OU6: 4 | OV6: 4 | OY6: 15 | PB6: 1 | PC6: 1 | PE6: 2 | PF6: 2 | PG6: 1 | PH6: 3 | PI6: 2 | PP6: 2 | PR6: 1 | PW6: 2 | PX6: 1 | PY6: 1 | QA6: 1 | QB6: 2 | QC6: 1 | QD6: 1 | QN6: 2 | QP6: 2 | QR6: 18 | QS6: 1 | QT6: 1 | QU6: 5 | QV6: 1 | QW6: 2 | QX6: 1 | QY6: 1 | RB6: 5 | RC6: 4 | RD6: 3 | RE6: 10 | RF6: 1 | RG6: 4 | RI6: 1 | RJ6: 1 | RK6: 8 | RL6: 25 | RM6: 3 | RN6: 1 | RO6: 2 | RQ6: 1 | RR6: 1 | RS6: 2 | RT6: 8 | RU6: 2 | RV6: 5 | RW6: 1 | RX6: 8 | RY6: 108 | RZ6: 1 | SB6: 1 | SC6: 1 | SD6: 1 | SE6: 1 | SF6: 1 | SG6: 1 | SH6: 7 | SI6: 1 | SJ6: 1 | SK6: 1 | SL6: 1 | SM6: 1 | SN6: 5 | SR6: 1 | SX6: 2 | SY6: 1 | TB6: 4 | TC6: 583
B7: Pratik Yamawar | AD7: 2 | AE7: 2 | AF7: 1 | AG7: 1 | AI7: 1 | AK7: 1 | AL7: 1 | AN7: 1 | AO7: 2 | AQ7: 1 | AS7: 4 | AT7: 2 | AV7: 4 | AW7: 1 | AX7: 4 | AZ7: 1 | BA7: 25 | BB7: 6 | BE7: 1 | BG7: 2 | BI7: 1 | BJ7: 2 | BK7: 2 | BL7: 3 | BM7: 1 | BO7: 5 | BP7: 3 | BQ7: 2 | BR7: 1 | BS7: 2 | BV7: 2 | BX7: 1 | BZ7: 1 | CA7: 1 | CC7: 11 | CI7: 2 | CM7: 20 | CN7: 4 | CO7: 1 | CP7: 74 | CR7: 1 | DH7: 3 | DI7: 1 | DJ7: 1 | DK7: 2 | DL7: 4 | DM7: 1 | DQ7: 1 | EA7: 1 | EE7: 1 | EV7: 3 | EW7: 3 | EX7: 3 | EY7: 2 | FC7: 2 | FD7: 1 | FH7: 5 | FJ7: 1 | FL7: 1 | FO7: 6 | FT7: 2 | FW7: 45 | GP7: 2 | GQ7: 2 | HB7: 1 | HC7: 1 | HD7: 2 | HS7: 1 | HY7: 1 | HZ7: 7 | IA7: 1 | IB7: 1 | IC7: 2 | ID7: 2 | IE7: 1 | IF7: 14 | IO7: 4 | IT7: 4 | IV7: 1 | JG7: 2 | JI7: 1 | JK7: 1 | JN7: 2 | JO7: 9 | JP7: 1 | JR7: 1 | KI7: 1 | KJ7: 1 | KQ7: 1 | KR7: 1 | KZ7: 3 | LI7: 25 | LP7: 1 | LQ7: 8 | LR7: 4 | LX7: 1 | LY7: 2 | LZ7: 3 | MA7: 4 | MB7: 6 | MC7: 6 | MD7: 12 | ME7: 4 | MF7: 1 | MG7: 2 | MH7: 2 | MI7: 3 | MJ7: 3 | MK7: 9 | ML7: 1 | MM7: 2 | MO7: 6 | MY7: 1 | NM7: 4 | NN7: 3 | NO7: 2 | NQ7: 2 | NT7: 19 | OB7: 1 | OD7: 2 | OF7: 114 | OG7: 2 | OH7: 2 | ON7: 1 | OR7: 1 | OW7: 2 | OX7: 1 | OY7: 5 | PD7: 1 | PE7: 1 | PJ7: 4 | PK7: 2 | PL7: 6 | PN7: 4 | PS7: 1 | PX7: 1 | PY7: 1 | QF7: 1 | QN7: 3 | QR7: 23 | QT7: 1 | QU7: 1 | QW7: 2 | QZ7: 2 | RA7: 2 | RB7: 2 | RH7: 1 | RM7: 4 | RP7: 1 | RS7: 4 | RT7: 1 | RY7: 21 | SA7: 1 | SH7: 1 | SO7: 1 | SP7: 1 | SS7: 5 | ST7: 11 | SU7: 5 | SV7: 4 | SW7: 2 | SZ7: 4 | TA7: 5 | TB7: 36 | TC7: 398
B8: Vinay Nambiar | C8: 2 | D8: 4 | E8: 2 | F8: 1 | G8: 2 | H8: 12 | I8: 1 | J8: 1 | K8: 3 | L8: 9 | M8: 3 | N8: 21 | O8: 2 | P8: 11 | Q8: 3 | R8: 7 | S8: 3 | T8: 3 | U8: 2 | V8: 1 | W8: 3 | X8: 6 | Y8: 102 | Z8: 1 | AA8: 2 | AB8: 2 | AC8: 5 | DO8: 4 | DW8: 5 | DZ8: 1 | FN8: 1 | FW8: 11 | FX8: 1 | FY8: 1 | FZ8: 1 | GA8: 2 | GB8: 3 | GC8: 6 | GD8: 1 | GE8: 1 | GF8: 5 | GG8: 7 | GH8: 12 | GR8: 1 | GS8: 1 | GT8: 1 | GU8: 2 | GV8: 1 | GW8: 4 | GX8: 1 | GY8: 1 | GZ8: 4 | HA8: 4 | HF8: 2 | HJ8: 2 | HK8: 4 | HL8: 3 | HM8: 8 | HN8: 15 | HO8: 5 | HP8: 5 | HQ8: 1 | HR8: 1 | HT8: 1 | HU8: 1 | HV8: 1 | HW8: 1 | HX8: 1 | HY8: 5 | IG8: 1 | IH8: 2 | II8: 3 | IJ8: 2 | IK8: 2 | IL8: 8 | IM8: 6 | IN8: 14 | IU8: 2 | JL8: 2 | JM8: 2 | JP8: 2 | JR8: 11 | JS8: 3 | JV8: 2 | KD8: 2 | KE8: 2 | KF8: 3 | KG8: 2 | KI8: 3 | KK8: 6 | KP8: 1 | KU8: 4 | KW8: 3 | KY8: 1 | LB8: 2 | LE8: 9 | LI8: 62 | LJ8: 2 | LK8: 1 | LL8: 2 | LM8: 5 | LN8: 2 | LO8: 2 | LP8: 4 | LQ8: 6 | LS8: 6 | LU8: 3 | LV8: 1 | MH8: 7 | MJ8: 2 | MK8: 11 | MM8: 3 | MP8: 2 | MR8: 3 | MS8: 2 | MT8: 4 | MU8: 5 | MV8: 7 | MW8: 4 | MX8: 3 | NC8: 4 | NG8: 2 | NI8: 4 | NJ8: 2 | NK8: 3 | NL8: 3 | NM8: 4 | NN8: 3 | NP8: 2 | NR8: 4 | NS8: 4 | NT8: 14 | NU8: 1 | NV8: 1 | NW8: 3 | NX8: 2 | NY8: 1 | OA8: 2 | OF8: 132 | PA8: 1 | PE8: 1 | PJ8: 11 | PM8: 2 | PO8: 6 | PQ8: 7 | PT8: 2 | PU8: 1 | PX8: 2 | PZ8: 4 | QC8: 2 | QE8: 2 | QG8: 1 | QH8: 2 | QI8: 2 | QL8: 3 | QM8: 5 | QN8: 6 | QO8: 1 | QR8: 59 | SQ8: 1 | TB8: 1 | TC8: 457
B9: (blank)
B10: Divakara Rangaswamy | KA10: 1 | LG10: 1 | LI10: 2 | MN10: 1 | NE10: 2 | NH10: 5 | OC10: 3 | OF10: 11 | OI10: 4 | OJ10: 1 | OK10: 2 | OL10: 1 | OM10: 8 | OS10: 5 | OT10: 1 | OY10: 6 | PV10: 2 | PY10: 1 | QD10: 3 | QJ10: 2 | QK10: 1 | QQ10: 1 | QR10: 10 | TC10: 37
B11: Dinesh Shiranpel | LW11: 8 | MQ11: 33 | MZ11: 8 | NA11: 1 | NN11: 4 | NZ11: 5 | OF11: 59 | OZ11: 1 | PE11: 1 | TC11: 60
B12: Grand Total | C12: 2 | D12: 4 | E12: 2 | F12: 1 | G12: 2 | H12: 12 | I12: 1 | J12: 1 | K12: 3 | L12: 9 | M12: 3 | N12: 21 | O12: 2 | P12: 11 | Q12: 3 | R12: 7 | S12: 3 | T12: 3 | U12: 2 | V12: 1 | W12: 3 | X12: 6 | Y12: 102 | Z12: 1 | AA12: 2 | AB12: 2 | AC12: 5 | AD12: 2 | AE12: 2 | AF12: 1 | AG12: 1 | AH12: 1 | AI12: 1 | AJ12: 1 | AK12: 1 | AL12: 1 | AM12: 2 | AN12: 1 | AO12: 2 | AP12: 1 | AQ12: 3 | AR12: 2 | AS12: 4 | AT12: 2 | AU12: 2 | AV12: 4 | AW12: 1 | AX12: 4 | AY12: 1 | AZ12: 1 | BA12: 37 | BB12: 9 | BC12: 2 | BD12: 1 | BE12: 1 | BF12: 2 | BG12: 2 | BH12: 2 | BI12: 1 | BJ12: 2 | BK12: 2 | BL12: 3 | BM12: 1 | BN12: 2 | BO12: 5 | BP12: 3 | BQ12: 2 | BR12: 2 | BS12: 2 | BT12: 1 | BU12: 1 | BV12: 7 | BW12: 1 | BX12: 1 | BY12: 1 | BZ12: 1 | CA12: 1 | CB12: 3 | CC12: 15 | CD12: 3 | CE12: 2 | CF12: 2 | CG12: 1 | CH12: 1 | CI12: 2 | CJ12: 2 | CK12: 1 | CL12: 2 | CM12: 20 | CN12: 4 | CO12: 1 | CP12: 117 | CQ12: 2 | CR12: 9 | CS12: 1 | CT12: 2 | CU12: 1 | CV12: 3 | CW12: 3 | CX12: 1 | CY12: 1 | CZ12: 1 | DA12: 5 | DB12: 1 | DC12: 2 | DD12: 3 | DE12: 4 | DF12: 1 | DG12: 1 | DH12: 3 | DI12: 1 | DJ12: 1 | DK12: 2 | DL12: 4 | DM12: 1 | DN12: 2 | DO12: 9 | DP12: 1 | DQ12: 14 | DR12: 6 | DS12: 3 | DT12: 3 | DU12: 4 | DV12: 1 | DW12: 26 | DX12: 4 | DY12: 4 | DZ12: 5 | EA12: 1 | EB12: 1 | EC12: 1 | ED12: 8 | EE12: 6 | EF12: 5 | EG12: 3 | EH12: 4 | EI12: 1 | EJ12: 1 | EK12: 1 | EL12: 4 | EM12: 1 | EN12: 5 | EO12: 4 | EP12: 3 | EQ12: 2 | ER12: 3 | ES12: 4 | ET12: 1 | EU12: 1 | EV12: 3 | EW12: 3 | EX12: 3 | EY12: 2 | EZ12: 3 | FA12: 1 | FB12: 4 | FC12: 5 | FD12: 3 | FE12: 1 | FF12: 3 | FG12: 2 | FH12: 5 | FI12: 2 | FJ12: 1 | FK12: 1 | FL12: 10 | FM12: 1 | FN12: 1 | FO12: 6 | FP12: 7 | FQ12: 6 | FR12: 9 | FS12: 1 | FT12: 2 | FU12: 2 | FV12: 4 | FW12: 286 | FX12: 1 | FY12: 1 | FZ12: 1 | GA12: 2 | GB12: 3 | GC12: 6 | GD12: 1 | GE12: 1 | GF12: 5 | GG12: 7 | GH12: 12 | GI12: 1 | GJ12: 1 | GK12: 1 | GL12: 1 | GM12: 1 | GN12: 1 | GO12: 6 | GP12: 2 | GQ12: 2 | GR12: 1 | GS12: 1 | GT12: 1 | GU12: 2 | GV12: 1 | GW12: 4 | GX12: 1 | GY12: 1 | GZ12: 4 | HA12: 4 | HB12: 1 | HC12: 1 | HD12: 2 | HE12: 2 | HF12: 2 | HG12: 1 | HH12: 3 | HI12: 3 | HJ12: 11 | HK12: 4 | HL12: 3 | HM12: 8 | HN12: 15 | HO12: 5 | HP12: 5 | HQ12: 1 | HR12: 1 | HS12: 1 | HT12: 1 | HU12: 1 | HV12: 1 | HW12: 1 | HX12: 1 | HY12: 6 | HZ12: 7 | IA12: 1 | IB12: 1 | IC12: 2 | ID12: 2 | IE12: 1 | IF12: 14 | IG12: 1 | IH12: 2 | II12: 3 | IJ12: 2 | IK12: 2 | IL12: 8 | IM12: 6 | IN12: 14 | IO12: 4 | IP12: 3 | IQ12: 4 | IR12: 2 | IS12: 2 | IT12: 15 | IU12: 2 | IV12: 3 | IW12: 2 | IX12: 2 | IY12: 2 | IZ12: 1 | JA12: 1 | JB12: 1 | JC12: 2 | JD12: 5 | JE12: 1 | JF12: 1 | JG12: 2 | JH12: 5 | JI12: 1 | JJ12: 1 | JK12: 1 | JL12: 2 | JM12: 2 | JN12: 2 | JO12: 10 | JP12: 3 | JQ12: 1 | JR12: 20 | JS12: 6 | JT12: 1 | JU12: 2 | JV12: 2 | JW12: 1 | JX12: 2 | JY12: 4 | JZ12: 2 | KA12: 1 | KB12: 1 | KC12: 1 | KD12: 2 | KE12: 2 | KF12: 3 | KG12: 10 | KH12: 1 | KI12: 7 | KJ12: 1 | KK12: 8 | KL12: 2 | KM12: 5 | KN12: 2 | KO12: 3 | KP12: 1 | KQ12: 1 | KR12: 1 | KS12: 3 | KT12: 2 | KU12: 5 | KV12: 1 | KW12: 3 | KX12: 1 | KY12: 1 | KZ12: 3 | LA12: 4 | LB12: 2 | LC12: 1 | LD12: 1 | LE12: 11 | LF12: 1 | LG12: 1 | LH12: 1 | LI12: 186 | LJ12: 2 | LK12: 1 | LL12: 2 | LM12: 5 | LN12: 2 | LO12: 2 | LP12: 5 | LQ12: 14 | LR12: 4 | LS12: 6 | LT12: 4 | LU12: 3 | LV12: 1 | LW12: 8 | LX12: 1 | LY12: 2 | LZ12: 3 | MA12: 4 | MB12: 6 | MC12: 6 | MD12: 12 | ME12: 4 | MF12: 1 | MG12: 2 | MH12: 9 | MI12: 3 | MJ12: 5 | MK12: 20 | ML12: 1 | MM12: 5 | MN12: 1 | MO12: 6 | MP12: 2 | MQ12: 33 | MR12: 3 | MS12: 2 | MT12: 4 | MU12: 5 | MV12: 7 | MW12: 4 | MX12: 3 | MY12: 1 | MZ12: 8 | NA12: 1 | NB12: 2 | NC12: 4 | ND12: 3 | NE12: 2 | NF12: 2 | NG12: 2 | NH12: 5 | NI12: 4 | NJ12: 2 | NK12: 3 | NL12: 3 | NM12: 8 | NN12: 10 | NO12: 2 | NP12: 2 | NQ12: 2 | NR12: 4 | NS12: 4 | NT12: 33 | NU12: 1 | NV12: 1 | NW12: 3 | NX12: 2 | NY12: 1 | NZ12: 5 | OA12: 2 | OB12: 1 | OC12: 3 | OD12: 2 | OE12: 2 | OF12: 329 | OG12: 2 | OH12: 2 | OI12: 4 | OJ12: 1 | OK12: 2 | OL12: 1 | OM12: 8 | ON12: 1 | OO12: 3 | OP12: 1 | OQ12: 3 | OR12: 1 | OS12: 5 | OT12: 1 | OU12: 4 | OV12: 4 | OW12: 2 | OX12: 1 | OY12: 26 | OZ12: 1 | PA12: 1 | PB12: 1 | PC12: 1 | PD12: 1 | PE12: 5 | PF12: 2 | PG12: 1 | PH12: 3 | PI12: 2 | PJ12: 15 | PK12: 2 | PL12: 6 | PM12: 2 | PN12: 4 | PO12: 6 | PP12: 2 | PQ12: 7 | PR12: 1 | PS12: 1 | PT12: 2 | PU12: 1 | PV12: 2 | PW12: 2 | PX12: 4 | PY12: 3 | PZ12: 4 | QA12: 1 | QB12: 2 | QC12: 3 | QD12: 4 | QE12: 2 | QF12: 1 | QG12: 1 | QH12: 2 | QI12: 2 | QJ12: 2 | QK12: 1 | QL12: 3 | QM12: 5 | QN12: 11 | QO12: 1 | QP12: 2 | QQ12: 1 | QR12: 110 | QS12: 1 | QT12: 2 | QU12: 6 | QV12: 1 | QW12: 4 | QX12: 1 | QY12: 1 | QZ12: 2 | RA12: 2 | RB12: 7 | RC12: 4 | RD12: 3 | RE12: 10 | RF12: 1 | RG12: 4 | RH12: 1 | RI12: 1 | RJ12: 1 | RK12: 8 | RL12: 25 | RM12: 7 | RN12: 1 | RO12: 2 | RP12: 1 | RQ12: 1 | RR12: 1 | RS12: 6 | RT12: 9 | RU12: 2 | RV12: 5 | RW12: 1 | RX12: 8 | RY12: 129 | RZ12: 1 | SA12: 1 | SB12: 1 | SC12: 1 | SD12: 1 | SE12: 1 | SF12: 1 | SG12: 1 | SH12: 8 | SI12: 1 | SJ12: 1 | SK12: 1 | SL12: 1 | SM12: 1 | SN12: 5 | SO12: 1 | SP12: 1 | SQ12: 1 | SR12: 1 | SS12: 5 | ST12: 11 | SU12: 5 | SV12: 4 | SW12: 2 | SX12: 2 | SY12: 1 | SZ12: 4 | TA12: 5 | TB12: 41 | TC12: 1535

Sheet Candidate Basedata
A1: Sl No | B1: Account | C1: Profile Submission Date | D1: SO Number | E1: Recruiter Name | G1: Source | H1: Sub Source | I1: Mandatory Skill | J1: Skill combinations | K1: Candidate Status | L1: Detailed Status | M1: Hire Type | N1: Candidate ID | O1: Candidate Name | P1: Contact Number | Q1: Email id | R1: Total Yrs of Exp | S1: Relevant Exp | T1: Current Company | U1: Current CTC | V1: Expected CTC | W1: Notice period | X1: Buyout(Y/N) | Y1: Ex-Employee(Y/N) | Z1: If Rehire Ex- Employee ID | AA1: Current Location | AB1: Preferred Location | AC1: Remarks
A2: 1 | B2: Dell FG | C2: 44546 | D2: 38024355 | E2: Rahul Kapoor | F2: U82721 | G2: Vendor Partner | H2: Mindsoft | I2: Java Selenium | J2: JAVA SELENIUM | K2: Dropped | M2: Regular | N2: 484611 | O2: Jacob | P2: 9553801682 | Q2: jacobkoheer@gmail.com | R2: 3yrs | S2: 2yrs | T2: Sun icon | U2: 600000 | V2: 950000 | W2: LWD-Dec 22nd-Immediate | X2: N | Y2: N | Z2: N | AA2: Hyderabad | AB2: Banglore/Hyderabad
A3: 2 | B3: Dell FG | C3: 44550 | D3: 38024355 | E3: Rahul Kapoor | F3: U82721 | G3: Vendor Partner | H3: Mindsoft | I3: SDET | J3: JAVA SELENIUM | K3: Tech1 Reject | L3: Screening IP | M3: Regular | N3: 351671 | O3: T M NANDINI | P3: 9739829708 | Q3: nandini.m.t78@gmail.com | R3: 3.4yrs | S3: 3.4yrs | T3: Mindtree | U3: 550000 | V3: 1150000 | W3: LWD-JAN 25TH | X3: N | Y3: N | Z3: N | AA3: Bangalore | AB3: Bangalore
A4: 3 | B4: Dell FG | C4: 44550 | D4: 94967553 | E4: Rahul Kapoor | F4: U82721 | G4: UST Global | H4: Mindsoft | I4: QA , Manual tester role | J4: SDET | K4: Joined | L4: Rejected | M4: Regular | N4: 354205 | O4: Vaishali Dixit | P4: 9691520066 | Q4: dixit.vaishali08@gmail.com | R4: 3.5yrs | S4: 3yrs | T4: Capgemini | U4: 450000 | V4: 1300000 | W4: 30 days(LWD: 26th Jan) | X4: N | Y4: N | Z4: NA | AA4: Bangalore | AB4: Bangalore
A5: 4 | B5: Dell FG | C5: 44550 | D5: 31972088 | E5: Vinay Nambiar | F5: 181547 | G5: Vendor Partner | H5: SRS | I5: Java | J5: Java/J2EE,Spring Boot,Spring Core,Spring MVC, Spring Web Services, Spring boot, Spring Data, Spring Cloud,HTML/CSS/JS | K5: Joined | L5: Interview No show | M5: Regular | N5: 419101 | O5: Hema Latha | P5: 9948358570 | Q5: hemalatha.friends@gmail.com | R5: 14 yr | S5: 14 yr | T5: Infosys | U5: 1450000 | V5: 3000000 | W5: LWD : 4/1/2021 | X5: No | Y5: No | Z5: N | AA5: Hyderabad | AB5: Hyderabad
A6: 5 | B6: Dell FG | C6: 44551 | D6: 94967553 | E6: Rahul Kapoor | F6: U82721 | G6: UST Global | H6: Mindsoft | I6: QA , Manual tester role:- | J6: SDET | K6: Joined | L6: Rejected | M6: Regular | N6: 379458 | O6: Alekya | P6: 9441095144 | Q6: alekya.d1988@gmail.com | R6: 4.8yrs | S6: 4.8yrs | T6: Nuance Transcription | U6: 500000 | V6: 850000 | W6: Immediate | X6: N | Y6: N | Z6: NA | AA6: Bangalore | AB6: Bangalore
A7: 6 | B7: Dell FG | C7: 44551 | D7: 82866188 | E7: Rahul Kapoor | F7: U82721 | G7: UST Global | H7: Mindsoft | I7: UI/UX role | J7: UI | K7: Dropped | L7: Drop out | M7: Regular | N7: 355575 | O7: Rajesh Sah | P7: 9739607439 | Q7: codeuix@gmail.com | R7: 6 years | S7: 5Years | T7: Nubewell Networks Pvt Ltd | U7: 1500000 | V7: 2200000 | W7: 11-Jan LWD | X7: N | Y7: N | Z7: NA | AA7: Bangalore | AB7: Bangalore
A8: 7 | B8: Dell FG | C8: 44551 | D8: 82866188 | E8: Rahul Kapoor | F8: U82721 | G8: UST Global | H8: Mindsoft | I8: UI/UX role | J8: UI | K8: Dropped | L8: Drop out | M8: Regular | N8: H8271088 | O8: Ankita Awasthi | P8: 9717348292 | Q8: ankitaawasthi05@gmail.com | R8: 7.6years | S8: 3+years | T8: Genpact | U8: 1000000 | V8: 2400000 | W8: 29-Dec LWD | X8: N | Y8: N | Z8: NA | AA8: Bangalore | AB8: Bangalore
A9: 8 | B9: Dell FG | C9: 44551 | D9: 51907700 | E9: Vinay Nambiar | F9: 181547 | G9: Vendor Partner | H9: SRS | I9: Java | J9: Java/J2EE,Spring Boot,Spring Core,Spring MVC, Spring Web Services, Spring boot, Spring Data, Spring Cloud,HTML/CSS/JS | K9: Joined | L9: Not responding | M9: Regular | N9: H14387 | O9: Sreedhar Vinjamuri | P9: 7337067133 | Q9: sreedhar.vin12@gmail.com | R9: 13 yr | S9: 13 yr | T9: Virinchi Technologies | U9: 1500000 | V9: 2500000 | W9: IMMEDATE JOINNER | X9: No | Y9: No | AA9: Hyderabad | AB9: Hyderabad
A10: 9 | B10: Dell FG | C10: 44551 | D10: 57335575 | E10: Vinay Nambiar | F10: 181547 | G10: Vendor Partner | H10: SRS | I10: Java | J10: Java/J2EE,Spring Boot,Spring Core,Spring MVC, Spring Web Services, Spring boot, Spring Data, Spring Cloud,HTML/CSS/JS | K10: Joined | L10: Interview No show | M10: Regular | N10: 419812 | O10: Pokuri Ramanjaneyulu | P10: 8106332319 | Q10: ram1980.p@gmail.com | R10: 14 yr | S10: 14 yr | T10: HCL Technologies, | U10: 1450000 | V10: 2400000 | W10: LWD: 28/1/2021 | X10: No | Y10: No | AA10: Hyderabad | AB10: Hyderabad
A11: 10 | B11: Dell FG | C11: 44551 | D11: 94990037 | E11: Vinay Nambiar | F11: 181547 | G11: Vendor Partner | H11: SRS | I11: Java | J11: Java/J2EE,Spring Boot,Spring Core,Spring MVC, Spring Web Services, Spring boot, Spring Data, Spring Cloud,HTML/CSS/JS | K11: Joined | L11: Interview No show | M11: Regular | N11: 418251 | O11: Sailaja Malyala | P11: 9848623920 | Q11: sailajamalyal@gmail.com | R11: 14 yr | S11: 14 yr | T11: IBM | U11: 1200000 | V11: 3000000 | W11: ELWD : 26/01/22 | X11: No | Y11: No | AA11: Hyderabad | AB11: Hyderabad
A12: 11 | B12: Dell FG | C12: 44552 | D12: 44173531 | E12: Vinay Nambiar | F12: 181547 | G12: Vendor Partner | H12: SRS | I12: Java | J12: Java/J2EE, Angularjs | K12: Dropped | L12: Not interested | M12: Regular | N12: 421816 | O12: G.Ramana Reddy | P12: 9390911344 | Q12: grreddy1729@gmail.com | R12: 5 Years | S12: 5 Years | T12: L&T Infotech | U12: 900000 | V12: 1500000 | W12: LWD 30-01-2022 | X12: Yes | Y12: No | AA12: Hyderabad | AB12: Hyderabad
A13: 12 | B13: Dell FG | C13: 44552 | D13: 44173531 | E13: Vinay Nambiar | F13: 181547 | G13: Vendor Partner | H13: SRS | I13: Java | J13: Java/J2EE, Angularjs | K13: Screen Reject | L13: Not responding | M13: Regular | N13: 421822 | O13: Prem Kumar Jannu | P13: 7893092220 | Q13: prem.jannu182829@gamil.com | R13: 9 Years | S13: 5 Years | T13: Infosys LTD | U13: 1200000 | V13: 2000000 | W13: LWD 31-01-2022 | X13: Yes | Y13: No | AA13: Hyderabad | AB13: Hyderabad
A14: 13 | B14: Dell FG | C14: 44552 | D14: 67489866 | E14: Vinay Nambiar | F14: 181547 | G14: Vendor Partner | H14: SRS | I14: DevOps | J14: 5-8y Devops with GIT,CICD (Gitlab),Powershell/Bash | K14: Dropped | L14: Requirement closed | M14: Regular | N14: 421830 | O14: Srinivas. Y | P14: 8247858588 | Q14: srinivasyara1257@gmail.com | R14: 5.3years | S14: 3.5years | T14: Sciens Software Technologies | U14: 650000 | V14: 1000000 | W14: 25days | X14: Yes | Y14: No | AA14: Hyderabad | AB14: Hyderabad | AC14: Req closed
A15: 14 | B15: Dell FG | C15: 44553 | D15: 94967553 | E15: Rahul Kapoor | F15: U82721 | G15: UST Global | H15: Mindsoft | I15: QA , Manual tester role | J15: SDET | K15: Dropped | L15: Pending | M15: Regular | N15: 389073 | O15: Vishnu kumar | P15: 9390839924 | Q15: m.vishnu225@gmail.com | R15: 3 yrs | S15: 3 yrs | T15: Brillquest technologies Pvt Ltd | U15: 300000 | V15: 500000 | W15: LWD-3rd Jan 22 | X15: N | Y15: N | Z15: NA | AA15: Bangalore | AB15: Bangalore
A16: 15 | B16: Dell FG | C16: 44553 | D16: 67489866 | E16: Vinay Nambiar | F16: 181547 | G16: Vendor Partner | H16: SRS | I16: DevOps | J16: 5-8y Devops with GIT,CICD (Gitlab),Powershell/Bash | K16: Dropped | L16: Requirement closed | M16: Regular | N16: 421842 | O16: Tejaswi Jonnalagadda | P16: 6302517658 | Q16: tejaswi.jonnalagadda91@gmail.com | R16: 7.2years | S16: 7years | T16: Cognizant | U16: 510000 | V16: 800000 | W16: 30days | X16: Yes | Y16: No | AA16: Hyderabad | AB16: Hyderabad | AC16: Req closed
A17: 16 | B17: Dell FG | C17: 44553 | D17: 98936697 | E17: Vinay Nambiar | F17: 181547 | G17: Vendor Partner | H17: SRS | I17: Java | J17: Java/J2EE,Full Stack Developer,Spring Boot,Angular,Cloud Technologies | K17: Screen Reject | L17: Not responding | M17: Regular | N17: 422936 | O17: Raja Mohan Munjeti | P17: 9492543488 | Q17: mohan123.java@gmail.com | R17: 14 yr | S17: 14 yr | T17: Birlasoft | U17: 1300000 | V17: 2400000 | W17: LWD 20/1/2022 | X17: No | Y17: No | AA17: Hyderabad | AB17: Hyderabad
A18: 17 | B18: Dell FG | C18: 44554 | D18: 34147670 | E18: Rahul Kapoor | F18: U82721 | G18: UST Global | H18: Mindsoft | I18: C#.NET,.NET Core, Web API, MVC,Angular,Jquery role . | J18: C#.NET | K18: Dropped | L18: High ctc expectation | M18: Regular | N18: H7835795 | O18: Venna Bhagyalakshmi | P18: 7022114311 | Q18: Bhagyalaxmi.venna@gmail.com | R18: 5.1 years | S18: 5.1 years | T18: Infosys, | U18: 730000 | V18: 2000000 | W18: 10-Jan LWD | X18: N | Y18: N | Z18: NA | AA18: Bangalore | AB18: Bangalore
A19: 18 | B19: Dell FG | C19: 44554 | D19: 34147670 | E19: Rahul Kapoor | F19: U82721 | G19: UST Global | H19: Mindsoft | I19: C#.NET,.NET Core, Web API, MVC,Angular,Jquery role . | J19: C#.NET | K19: Joined | L19: Rejected | M19: Regular | N19: H6549840 | O19: Swagat Das Pattanaik | P19: 9090016506 | Q19: sdpswagat@gmail.com | R19: 8 years | S19: 8 years | T19: Infosys | U19: 1600000 | V19: 2100000 | W19: 30 Days (in provision period till dec end) | X19: N | Y19: N | Z19: NA | AA19: Bhubaneswar | AB19: Bangalore
A20: 19 | B20: Dell FG | C20: 44554 | D20: 92843512 | E20: Rahul Kapoor | F20: U82721 | G20: UST Global | H20: Mindsoft | I20: C#.NET,.NET Core, Web API, MVC,Angular,Jquery | J20: C#.NET | K20: Dropped | L20: Drop out | M20: Regular | N20: 402046 | O20: Rajat Patel | P20: 8970264977 | Q20: rpatel062021@gmail.com | R20: 7.3yrs | S20: 4yrs | T20: Wipro Limited | U20: 1300000 | V20: 1800000 | W20: 30 days(LWD:27th Jan) | X20: N | Y20: N | Z20: NA | AA20: Bangalore | AB20: Bangalore
A21: 20 | B21: Dell FG | C21: 44554 | D21: 68506880 | E21: Rahul Kapoor | F21: U82721 | G21: UST Global | H21: Mindsoft | I21: C#.NET,.NET Core, Web API, MVC,Angular,Jquery | J21: C#.NET | K21: Dropped | L21: High ctc rejected | M21: Regular | N21: 401907 | O21: Pramod K | P21: 9538686070 | Q21: Pramodk41@gmail.com | R21: 11yrs | S21: 5yrs | T21: Wells Fargo EGS India Pvt. Ltd | U21: 1600000 | V21: 2600000 | W21: 20 days(LWD:14th Jan) | X21: N | Y21: Y | AA21: Bangalore | AB21: Bangalore
A22: 21 | B22: Dell FG | C22: 44554 | D22: 68506880 | E22: Rahul Kapoor | F22: U82721 | G22: UST Global | H22: Mindsoft | I22: C#.NET,.NET Core, Web API, MVC,Angular,Jquery | J22: C#.NET | K22: Dropped | L22: Duplicate | M22: Regular | N22: 402000 | O22: Ramachandra Reddy E | P22: 9739527778 | Q22: ercreddy4@gmail.com | R22: 14.5yrs | S22: 4.5yrs | T22: Not working | U22: 1900000 | V22: 2700000 | W22: Immediate | X22: N | Y22: N | Z22: NA | AA22: Bangalore | AB22: Bangalore
A23: 22 | B23: Dell FG | C23: 44554 | D23: 98936697 | E23: Vinay Nambiar | F23: 181547 | G23: Vendor Partner | H23: SRS | I23: Java | J23: Java/J2EE,Full Stack Developer,Spring Boot,Angular,Cloud Technologies | K23: Screen Reject | L23: Not responding | M23: Regular | N23: H8110634 | O23: Jinka Mohan | P23: 9963120609 | Q23: jinkamohan@yahoo.com | R23: 15 YR | S23: 15 YR | T23: Hyderabad | U23: 1500000 | V23: 1800000 | W23: IMMEDAITE JOINNER | X23: No | Y23: No | AA23: Hyderabad | AB23: Hyderabad
A24: 23 | B24: Dell FG | C24: 44554 | D24: 77765032 | E24: Vinay Nambiar | F24: 181547 | G24: Vendor Partner | H24: SRS | I24: Java | J24: Java/J2EE,Spring,PostgreSQL,ReactJS,PCF,Cloud Microservices,TFS,GitLab,Dev Ops CICD | K24: Screen Reject | L24: Not responding | M24: Regular | N24: 422946 | O24: C. Phani Kishore | P24: 9502329926 | Q24: phanikishorechavvakula@gmail.com | R24: 4.10 years | S24: 4.2 years | T24: Zenith Technology Services | U24: 1000000 | V24: 1400000 | W24: LWD: 17/01/2022 | X24: Yes | Y24: No | AA24: Hyderabad | AB24: Hyderabad
A25: 24 | B25: Dell FG | C25: 44554 | D25: 58270892 | E25: Rahul Kapoor | F25: U82721 | G25: Vendor Partner | H25: Nityo InfoTech | I25: PLSQL Developer, Informatica and Control – M | J25: PLSQL Developer | K25: Dropped | M25: Regular | N25: 431922 | O25: Tanguturi Jayapal | P25: 8217012668/7899098018 | Q25: jayapalinfo232@gmail.com | R25: 3.8 Years | S25: 3.8 Years | T25: Tata Consultancy Services Ltd. | U25: 520000 | V25: 850000 | W25: LWD:30/12/21 | X25: N | Y25: N | Z25: NA | AA25: Bangalore | AB25: Bangalore
A26: 25 | B26: Dell FG | C26: 44557 | D26: 58270892 | E26: Rahul Kapoor | F26: U82721 | G26: Vendor Partner | H26: Nityo InfoTech | I26: PLSQL Developer, Informatica and Control – M | J26: PLSQL Developer | K26: Dropped | M26: Regular | N26: 430273 | O26: Ashok Kumar Nahak | P26: 7550154965 | Q26: ashoktech1008@gmail.com | R26: 3.5 Years | S26: 3.5 Years | T26: PLEXUS SOFTWARE SECURITY SYSTEMS PRIVATE LIMITED | U26: 850000 | V26: 1050000 | W26: Immediate | X26: N | Y26: N | Z26: NA | AA26: Chennai | AB26: Bangalore
A27: 26 | B27: Dell FG | C27: 44557 | D27: 58270892 | E27: Rahul Kapoor | F27: U82721 | G27: Vendor Partner | H27: Nityo InfoTech | I27: PLSQL Develop, Informatica and Control – M | J27: PLSQL Developer | K27: Dropped | M27: Regular | N27: 430286 | O27: M Murali krishna | P27: 8217455947/7008255417 | Q27: medmuralikrishna@gmail.com | R27: 3.6 Years | S27: 3.6 Years | T27: Cognizant Technologies | U27: 850000 | V27: 1050000 | W27: 30days(15days) | X27: N | Y27: N | Z27: NA | AA27: Bangalore | AB27: Bangalore
A28: 27 | B28: Dell FG | C28: 44557 | D28: 58270892 | E28: Rahul Kapoor | F28: U82721 | G28: Vendor Partner | H28: Nityo InfoTech | I28: PLSQL Develop, Informatica and Control – M | J28: PLSQL Developer | K28: Dropped | M28: Regular | N28: 430617 | O28: Eswar Sai S | P28: 7675099160 | Q28: eswarsai.etldb@gmail.com | R28: 3.5 Years | S28: 3 Years | T28: Deltra Soft Technologies Pvt Ltd | U28: 360000 | V28: 650000 | W28: 30days(15days) | X28: Y | Y28: N | Z28: NA | AA28: Hyderabad | AB28: Bangalore
A29: 28 | B29: Dell FG | C29: 44557 | D29: 34147670 | E29: Rahul Kapoor | F29: U82721 | G29: UST Global | H29: Mindsoft | I29: C#.NET,.NET Core, Web API, MVC,Angular,Jquery role | J29: C#.NET | K29: Dropped | L29: Drop out | M29: Regular | N29: L376418 | O29: Manikandan K | P29: 7829098574 | Q29: maniksfwr@gmail.com | R29: 7.2 yrs | S29: 4yrs | T29: Not working | U29: 950000 | V29: 1700000 | W29: Immediate | X29: N | Y29: N | Z29: NA | AA29: Bangalore | AB29: Bangalore
A30: 29 | B30: Dell FG | C30: 44557 | D30: 58270892 | E30: Rahul Kapoor | F30: U82721 | G30: Vendor Partner | H30: Nityo InfoTech | I30: PLSQL Develop, Informatica and Control – M | J30: PLSQL Developer | K30: Dropped | M30: Regular | N30: 431752 | O30: Naga Malleswara Rao Mannem | P30: 7659935955 | Q30: nagamallesh519@gmail.com | R30: 4.6 Years | S30: 4.6 Years | T30: Tata Consultancy Services Ltd. | U30: 600000 | V30: 1050000 | W30: 30days(15days) | X30: N | Y30: N | Z30: NA | AA30: Bangalore | AB30: Bangalore
A31: 30 | B31: Dell FG | C31: 44558 | D31: 67489866 | E31: Vinay Nambiar | F31: 181547 | G31: Vendor Partner | H31: SRS | I31: DevOps | J31: 5-8y Devops with GIT,CICD (Gitlab),Powershell/Bash | K31: Dropped | L31: Requirement closed | M31: Regular | N31: H7890084 | O31: Prashanth Reddy | P31: 7816087160 | Q31: prashanth.anakapally@gmail.com | R31: 5years | S31: 3years | T31: Future Nine Information Technologies Pvt. Ltd | U31: 700000 | V31: 1300000 | W31: 25days | X31: No | Y31: No | AA31: Hyderabad | AB31: Hyderabad
A32: 31 | B32: Dell FG | C32: 44558 | D32: 67489866 | E32: Vinay Nambiar | F32: 181547 | G32: Vendor Partner | H32: SRS | I32: DevOps | J32: 5-8y Devops with GIT,CICD (Gitlab),Powershell/Bash | K32: Dropped | L32: Requirement closed | M32: Regular | N32: 431002 | O32: Vamsi reddy Peddinti | P32: 9381863414 | Q32: vamsipeddinti28@gmail.com | R32: 5.5years | S32: 3years | T32: Nivass IT Solutions Pvt Ltd | U32: 550000 | V32: 850000 | W32: 30days | X32: No | Y32: No | AA32: Hyderabad | AB32: Hyderabad
A33: 32 | B33: Dell FG | C33: 44558 | D33: ​98936697 | E33: Vinay Nambiar | F33: 181547 | G33: Vendor Partner | H33: SRS | I33: Java | J33: Java/J2EE,Full Stack Developer,Spring Boot,Angular,Cloud Technologies | K33: Joined | L33: Joined because of high CTC | M33: Regular | N33: 351658 | O33: Yashwanth Vyamasani | P33: 9949073900 | Q33: yashwanth.vyam@gmail.com | R33: 13 yr | S33: 13 yr | T33: IBM | U33: 1230000 | V33: 3000000 | W33: ELWD : 21/01/22 | X33: No | Y33: No | AA33: HYDERABAD | AB33: HYDERABAD
A34: 33 | B34: Dell FG | C34: 44558 | D34: ​98936697 | E34: Vinay Nambiar | F34: 181547 | G34: Vendor Partner | H34: SRS | I34: Java | J34: Java/J2EE,Full Stack Developer,Spring Boot,Angular,Cloud Technologies | K34: Feedback pending from client | L34: Processed yet to get feedback from client | M34: Regular | N34: 432232 | O34: Chiranjeevi Madasu | P34: 9848869290 | Q34: chiranjeevi.madasu@gmail.com | R34: 15 yr | S34: 15 yr | T34: Infosys | U34: 1600000 | V34: 3000000 | W34: Immediate joiner | X34: No | Y34: No | AA34: HYDERABAD | AB34: HYDERABAD
A35: 34 | B35: Dell FG | C35: 44558 | D35: 95801483 | E35: Vinay Nambiar | F35: 181547 | G35: Vendor Partner | H35: SRS | I35: Java | J35: JAVA/J2EE SPRING, ANGULAR | K35: Joined | L35: Not responding | M35: Regular | N35: H7777151 | O35: M Anil Kumar | P35: 9538824541 | Q35: anelkumar.m159@gmail.com | R35: 6 yr | S35: 6 yr | T35: Tech Mahindra | U35: 750000 | V35: 1500000 | W35: ELWD : 29/01/22 | X35: No | Y35: No | AA35: Bangalore/ | AB35: Bangalore
A36: 35 | B36: Dell FG | C36: 44558 | D36: 95801483 | E36: Vinay Nambiar | F36: 181547 | G36: Vendor Partner | H36: SRS | I36: Java | J36: JAVA/J2EE SPRING ANGULAR | K36: Joined | L36: Not responding | M36: Regular | N36: 328950 | O36: Ravikanth Sharma | P36: 8639575493 | Q36: vrksharma1981@gmail.com | R36: 8yr | S36: 8yr | T36: DXC Technology | U36: 1000000 | V36: 1900000 | W36: ELWD : 21/01/22 | X36: No | Y36: No | AA36: Bangalore/ | AB36: Bangalore
A37: 36 | B37: Dell FG | C37: 44558 | D37: 95801483 | E37: Vinay Nambiar | F37: 181547 | G37: Vendor Partner | H37: SRS | I37: Java | J37: JAVA/J2EE SPRING ANGULAR | K37: Joined | L37: Not responding | M37: Regular | N37: L757477 | O37: Tarun Barik | P37: 7828724103 | Q37: tarunbarik.csit@gmail.com | R37: 6 yr | S37: 6 yr | T37: Slk Software Services | U37: 790000 | V37: 1900000 | W37: ELWD : 25/01/22 | X37: No | Y37: No | AA37: Bangalore/ | AB37: Bangalore
A38: 37 | B38: Dell FG | C38: 44558 | D38: 95801483 | E38: Vinay Nambiar | F38: 181547 | G38: Vendor Partner | H38: SRS | I38: Java | J38: Java/J2EE, Angularjs,Spring Boot | K38: Joined | L38: Not responding | M38: Regular | N38: 432194 | O38: Selva Kumar G | P38: 9500552392 | Q38: selva.kak@gmail.com | R38: 5.5 Years | S38: 5.5 Years | T38: Smartpoint Technologies | U38: 890000 | V38: 1500000 | W38: LWD 04-02-2022 | X38: Yes | Y38: No | AA38: Chennai | AB38: Banglore
A39: 38 | B39: Dell FG | C39: 44558 | D39: 98927307 | E39: Vinay Nambiar | F39: 181547 | G39: Vendor Partner | H39: SRS | I39: Java | J39: 3-6y Java/J2EE,Springboot,Cloud Native Concepts,RESTful,web services,Microservice Architecture,Spring Framework | K39: Joined | L39: No show | M39: Regular | N39: 433908 | O39: Manoj kumar | P39: 8143524153 | Q39: manojkumar.yerukondu@gmail.com | R39: 3.2 years | S39: 2 yrs | T39: Infosys | U39: 660000 | V39: 1000000 | W39: LWD: 31/12/2021 | X39: No | Y39: No | AA39: Hyderabad | AB39: Bangalore
A40: 39 | B40: Dell FG | C40: 44558 | D40: 98927307 | E40: Vinay Nambiar | F40: 181547 | G40: Vendor Partner | H40: SRS | I40: Java | J40: 3-6y Java/J2EE,Springboot,Cloud Native Concepts,RESTful,web services,Microservice Architecture,Spring Framework | K40: Dropped | L40: Candidate has other offer not processed | M40: Regular | N40: 433941 | O40: G. Ganesh | P40: 7893030070 | Q40: gampalaganesh05@gmail.com | R40: 2.4 years | S40: 2 yrs | T40: Sun Icon systems Pvt. Ltd | U40: 480000 | V40: 1000000 | W40: 30 days | X40: No | Y40: No | AA40: Hyderabad | AB40: Hyderabad
A41: 40 | B41: Dell FG | C41: 44558 | D41: 31972088 | E41: Vinay Nambiar | F41: 181547 | G41: Vendor Partner | H41: Mindsoft | I41: Java | J41: Java/J2EE,Spring Boot,Spring Core,Spring MVC, Spring Web Services, Spring boot, Spring Data, Spring Cloud,HTML/CSS/JS | K41: Joined | L41: Other offer | M41: Regular | N41: 430788 | O41: K.V.S Chandra Sekhar | P41: 9347977897 | Q41: chandu.process@gmail.com | R41: 14.5 years | S41: 13.5 years | T41: Not working( Last worked with Ivy Comptech till August '21 | U41: 2300000 | V41: 2500000 | W41: Immediate | X41: No | Y41: No | AA41: Hyderabad | AB41: Hyderabad
A42: 41 | B42: Dell FG | C42: 44558 | D42: 31972088 | E42: Vinay Nambiar | F42: 181547 | G42: Vendor Partner | H42: Mindsoft | I42: Java | J42: Java/J2EE,Spring Boot,Spring Core,Spring MVC, Spring Web Services, Spring boot, Spring Data, Spring Cloud,HTML/CSS/JS | K42: Dropped | L42: Candidate not responding the calls | M42: Regular | N42: 436834 | O42: Sreelekha Jakka | P42: 9000950687 | Q42: jsreelekhareddy@gmail.com | R42: 12 years | S42: 6 years | T42: Not working( Last worked with Vsoft Technologies till December '21 ) | U42: 1100000 | V42: 1600000 | W42: Immediate | X42: No | Y42: No | AA42: Hyderabad | AB42: Hyderabad
A43: 42 | B43: Dell FG | C43: 44558 | D43: 36862234 | E43: Rahul Kapoor | F43: U82721 | G43: Vendor Partner | H43: Nityo InfoTech | I43: Mobility | J43: 4G/5G RAN L2 | K43: Client Reject | M43: Regular | N43: 429695 | O43: AMITKUMAR P SHIROL | P43: 9535291492 | Q43: amitshirolbgm@gmail.com | R43: 6.5YRS | S43: 5yrs | T43: coforge | U43: 1000000 | V43: 1600000 | W43: Immediate-LWD/30TH NOV | X43: N | Y43: N | Z43: N | AA43: banglore | AB43: banglore
A44: 43 | B44: Dell FG | C44: 44558 | D44: 73030060 | E44: Rahul Kapoor | F44: U82721 | G44: Vendor Partner | H44: Nityo InfoTech | I44: Mobility | J44: 4G/5G RAN L2 | K44: Client Reject | M44: Regular | N44: 429683 | O44: Prathap kumar | P44: 9618484841 | Q44: prathapambothula@outlook.com | R44: 8yrs | S44: 7yrs | T44: Radisys | U44: 2100000 | V44: 2700000 | W44: Immediate-LWD/31ST DEC | X44: N | Y44: N | Z44: N | AA44: Hyderabad | AB44: banglore
A45: 44 | B45: Dell FG | C45: 44558 | D45: 75600044 | E45: Rahul Kapoor | F45: U82721 | G45: Vendor Partner | H45: Nityo InfoTech | I45: Mobility | J45: 4G/5G RAN L2 | K45: Client Reject | M45: Regular | N45: 431908 | O45: Vikrant Namdev | P45: 8817724704 | Q45: vikrant.namdev@gmail.com | R45: 10yrs | S45: 2yrs | T45: ultimateinfo soft | U45: 980000 | V45: 1400000 | W45: 30days(nego 15days) | X45: N | Y45: N | Z45: N | AA45: Indore | AB45: banglore
A46: 45 | B46: Dell FG | C46: 44558 | D46: 50201569 | E46: Rahul Kapoor | F46: U82721 | G46: Vendor Partner | H46: Nityo InfoTech | I46: Mobility | J46: 4G/5G RAN L2 | K46: Client Reject | M46: Regular | N46: 429246 | O46: Pinki Singh | P46: 7987723612 | Q46: singhpinkirajput@gmail.com | R46: 6yrs | S46: 2yrs | T46: Mastec Quadgen Wireless | U46: 813000 | V46: 1600000 | W46: Lwd Jan 17th | X46: N | Y46: N | Z46: N | AA46: Bangalore | AB46: Bangalore
A47: 46 | B47: Dell FG | C47: 44558 | D47: 50201569 | E47: Rahul Kapoor | F47: U82721 | G47: Vendor Partner | H47: Nityo InfoTech | I47: Mobility | J47: 4G/5G RAN L2 | K47: Client Reject | M47: Regular | N47: 429324 | O47: Erfan Muhammed | P47: 9539025426 | Q47: mohderfan0991@gmail.com | R47: 6yrs | S47: 2yrs | T47: Ericsson Global | U47: 700000 | V47: 1400000 | W47: 30 days official(Neg) | X47: N | Y47: N | Z47: N | AA47: Bangalore | AB47: Bangalore
A48: 47 | B48: Dell FG | C48: 44558 | D48: 73030060 | E48: Rahul Kapoor | F48: U82721 | G48: Vendor Partner | H48: Nityo InfoTech | I48: Mobility | J48: 4G/5G RAN L2 | K48: Client Reject | M48: Regular | N48: 428259 | O48: Md Zafar | P48: 7717761848 | Q48: mdzafar008@gmail.com | R48: 7.6yrs | S48: 2.6yrs | T48: Telemania Services | U48: 560000 | V48: 900000 | W48: 30 days official(Neg) | X48: N | Y48: N | Z48: N | AA48: Hyderabad | AB48: Bangalore
A49: 48 | B49: Dell FG | C49: 44559 | D49: 44879198 | E49: Rahul Kapoor | F49: U82721 | G49: Vendor Partner | H49: Nityo InfoTech | I49: .NET,SQL,WEB API | J49: DOTNET | K49: Offered | M49: Regular | N49: 436862 | O49: AMIT JANGIR | P49: 8058860500/8078679705 | Q49: amit5010jangir@gmail.com | R49: 2.5 Years | S49: 2.5 Years | T49: Anuin Techlogix | U49: 315000 | V49: 850000 | W49: LWD:20/01/22 | X49: N | Y49: N | Z49: NA | AA49: Pune | AB49: Bangalore
A50: 49 | B50: Dell FG | C50: 44559 | D50: 44879198 | E50: Rahul Kapoor | F50: U82721 | G50: Vendor Partner | H50: Nityo InfoTech | I50: .NET,SQL,WEB API | J50: DOTNET | K50: Offered | M50: Regular | N50: 436855 | O50: Praveen kumar.R | P50: 7659022717/7411026147 | Q50: praveenreddi.in@gmail.com | R50: 2.2 Years | S50: 2 Years | T50: Temenos | U50: 510000 | V50: 950000 | W50: LWD:2/01/22 | X50: N | Y50: N | Z50: NA | AA50: Bangalore | AB50: Bangalore
A51: 50 | B51: Dell FG | C51: 44559 | D51: 44879198 | E51: Rahul Kapoor | F51: U82721 | G51: Vendor Partner | H51: Nityo InfoTech | I51: .NET,SQL,WEB API | J51: DOTNET | K51: Offered | M51: Regular | N51: 437985 | O51: SATISH UDA | P51: 9515500554/8639576943 | Q51: satishgoud313@gmail.com | R51: 2 Years | S51: 2 Years | T51: Ecofil Technologies India Pvt Ltd | U51: 420000 | V51: 850000 | W51: Immediate | X51: N | Y51: N | Z51: NA | AA51: Chennai | AB51: Bangalore
A52: 51 | B52: Dell FG | C52: 44559 | D52: 44879198 | E52: Rahul Kapoor | F52: U82721 | G52: Vendor Partner | H52: Nityo InfoTech | I52: .NET,SQL,WEB API | J52: DOTNET | K52: Offered | M52: Regular | N52: 436649 | O52: Srinivas T | P52: 9398575490/9642633714 | Q52: tsrinivas714@gmail.com | R52: 2.7 Years | S52: 2.7 Years | T52: Resilience Info Tech | U52: 350000 | V52: 950000 | W52: Immediate | X52: N | Y52: N | Z52: NA | AA52: Bangalore | AB52: Bangalore
A53: 52 | B53: Dell FG | C53: 44559 | D53: 73030060 | E53: Rahul Kapoor | F53: U82721 | G53: Vendor Partner | H53: Nityo InfoTech | I53: Mobility | J53: 4G/5G RAN L2 | K53: Client Reject | M53: Regular | N53: 436426 | O53: Sachin Kakkadath | P53: 9947099962 | Q53: snk.360@gmail.com | R53: 12yrs | S53: 4yrs | T53: Vodafone Idea Ltd | U53: 710000 | V53: 1500000 | W53: 30 days | X53: N | Y53: N | Z53: N | AA53: Cochin | AB53: Bangalore
A54: 53 | B54: Dell FG | C54: 44559 | D54: 73030060 | E54: Rahul Kapoor | F54: U82721 | G54: Vendor Partner | H54: Nityo InfoTech | I54: Mobility | J54: 4G/5G RAN L2 | K54: Client Reject | M54: Regular | N54: 429479 | O54: Midhun P K | P54: 9446861022 | Q54: pk.midhun01@gmail.com | R54: 8yrs | S54: 3yrs | T54: IKYA Human Capital | U54: 1200000 | V54: 1600000 | W54: Immediate | X54: N | Y54: N | Z54: N | AA54: Bangalore | AB54: Bangalore
A55: 54 | B55: Dell FG | C55: 44559 | D55: 73030060 | E55: Rahul Kapoor | F55: U82721 | G55: Vendor Partner | H55: Mindsoft | I55: Mobility | J55: Mobility | K55: Client Reject | L55: Waiting for client feedback | M55: Regular | N55: 431520 | O55: Ajit Singh | P55: 7462826329 | Q55: ajitsinghcsmt@gmail.com | R55: 10yrs | S55: RAN Dev - 2yrs | T55: Tata Communication | U55: 720000 | V55: 1200000 | W55: Immediate | X55: N | Y55: N | Z55: N | AA55: Bangalore | AB55: Bangalore
A56: 55 | B56: Dell FG | C56: 44559 | D56: 12527642 | E56: Vinay Nambiar | F56: 181547 | G56: Vendor Partner | H56: Growelsoftech pvt ltd | I56: Project Manager | J56: 5-8y Project Manager with Agile,SCRUM | K56: Joined | L56: Back up candidates | M56: Regular | N56: 2903254 | O56: Sunil S Shettigar | P56: 8105956342/7892257756 | Q56: sunil.shettigar615@gmail.com | R56: 6years | S56: 5YEARS | T56: IXAR Pvt ltd | U56: 600000 | V56: 900000 | W56: 15 days 30 days officially ( negotiablr) | X56: N | Y56: N | Z56: N | AA56: MUMBAI | AB56: BANGALORE
A57: 56 | B57: Dell FG | C57: 44559 | D57: 12527642 | E57: Vinay Nambiar | F57: 181547 | G57: Vendor Partner | H57: Growelsoftech pvt ltd | I57: Project Manager | J57: 5-8y Project Manager with Agile,SCRUM | K57: Joined | L57: Back up candidates | M57: Regular | N57: 297406 | O57: PRERNA RANI | P57: 9911941521 | Q57: prernarani18@gmail.com | R57: 7+YEARS | S57: 7+YEARS | T57: Pragmatic Play India Pvt Ltd | U57: 550000 | V57: 800000 | W57: LWD-15 SEP ( IMMEDIATE JOINER) | X57: N | Y57: N | Z57: N | AA57: BANGALORE | AB57: BANGALORE
A58: 57 | B58: Dell FG | C58: 44559 | D58: 12527642 | E58: Vinay Nambiar | F58: 181547 | G58: Vendor Partner | H58: Growelsoftech pvt ltd | I58: Project Manager | J58: 5-8y Project Manager with Agile,SCRUM | K58: Joined | L58: Back up candidates | M58: Regular | N58: 429859 | O58: Jyoti Khetal | P58: 9871494074 | Q58: khetaljyoti@gmail.com | R58: 7years | S58: 7years | T58: Brute Corp | U58: 750000 | V58: 1350000 | W58: LWD-Dec-31 | X58: N | Y58: N | Z58: N | AA58: Gaziabad | AB58: Bangalore
A59: 58 | B59: Dell FG | C59: 44559 | D59: 12527642 | E59: Vinay Nambiar | F59: 181547 | G59: Vendor Partner | H59: Growelsoftech pvt ltd | I59: Project Manager | J59: 5-8y Project Manager with Agile,SCRUM | K59: Joined | L59: Back up candidates | M59: Regular | N59: 431485 | O59: Sathiya K | P59: 6380481442 | Q59: sathiyakannadasann@gmail.com | R59: 5yrs | S59: 4yrs | T59: Maximos Global Solutions | U59: 300000 | V59: 500000 | W59: lwd-30 Dec | X59: N | Y59: N | Z59: N | AA59: Chennai | AB59: Bangalore
A60: 59 | B60: Dell FG | C60: 44559 | D60: 12527642 | E60: Vinay Nambiar | F60: 181547 | G60: Vendor Partner | H60: Growelsoftech pvt ltd | I60: Project Manager | J60: 5-8y Project Manager with Agile,SCRUM | K60: Joined | L60: Back up candidates | M60: Regular | N60: 430746 | O60: Madhukar Ch | P60: 9949387693 | Q60: madhukarch90@gmail.com | R60: 5years | S60: 5years | T60: Optum - UHG | U60: 850000 | V60: 1100000 | W60: immediate | X60: N | Y60: N | Z60: N | AA60: Hyderabad | AB60: Bangalore
A61: 60 | B61: Dell FG | C61: 44559 | D61: 12527642 | E61: Vinay Nambiar | F61: 181547 | G61: Vendor Partner | H61: Growelsoftech pvt ltd | I61: Project Manager | J61: 5-8y Project Manager with Agile,SCRUM | K61: Joined | L61: Back up candidates | M61: Regular | N61: 430767 | O61: Muna Hannan | P61: 9449150744 | Q61: munahannan@gmail.com | R61: 8.5 Years | S61: 4.10 Years | T61: Shreeon Computers Pvt Ltd | U61: 900000 | V61: 1300000 | W61: Immediate joiner LWD:24.12.2021 | X61: N | Y61: N | Z61: N | AA61: Bangalore | AB61: Bangalore
A62: 61 | B62: Dell FG | C62: 44559 | D62: 14885881 | E62: Vinay Nambiar | F62: 181547 | G62: Vendor Partner | H62: Growelsoftech pvt ltd | I62: UI/UX | J62: 5-8 yrs UX/UI Developer with HTML5,CSS3,Bootstrap,Javascript,Typescript | K62: Joined | L62: No Angular 6 exp | M62: Regular | N62: 430071 | O62: Shashi Prakash Singh | P62: 8800470750 | Q62: shashi.s22@yahoo.com | R62: 8years | S62: 8years | T62: American Express | U62: 770000 | V62: 1300000 | W62: LWD-Dec-31 | X62: N | Y62: N | Z62: N | AA62: Gurgaon | AB62: Bangalore
A63: 62 | B63: Dell FG | C63: 44559 | D63: 14885881 | E63: Vinay Nambiar | F63: 181547 | G63: Vendor Partner | H63: Growelsoftech pvt ltd | I63: UI/UX | J63: 5-8 yrs UX/UI Developer with HTML5,CSS3,Bootstrap,Javascript,Typescript | K63: Joined | L63: No Angular 6 exp | M63: Regular | N63: 355195 | O63: Prasanth R | P63: 9159525210 | Q63: prasanthsatha@gmail.com | R63: 5.8yrs | S63: 5.8yrs | T63: Codenatives India Pvt Ltd | U63: 400000 | V63: 600000 | W63: 15 days | X63: N | Y63: N | Z63: N | AA63: TamilNadu | AB63: Bangalore
A64: 63 | B64: Dell FG | C64: 44559 | D64: 14885881 | E64: Vinay Nambiar | F64: 181547 | G64: Vendor Partner | H64: Growelsoftech pvt ltd | I64: UI/UX | J64: 5-8 yrs UX/UI Developer with HTML5,CSS3,Bootstrap,Javascript,Typescript | K64: Joined | L64: No Angular 6 exp | M64: Regular | N64: 431558 | O64: Sabareeswaran Palanisamy | P64: 9976108336 | Q64: sabaree.itle11@gmail.com | R64: 7yrs | S64: 7yrs | T64: Wisdomleaf Technologies | U64: 570000 | V64: 800000 | W64: jan31-lwd | X64: N | Y64: N | Z64: N | AA64: Hyderabad | AB64: Bangalore
A65: 64 | B65: Dell FG | C65: 44559 | D65: 64881514 | E65: Vinay Nambiar | F65: 181547 | G65: Vendor Partner | H65: Growelsoftech pvt ltd | I65: UI/UX | J65: 8-12y UI,UX, Front-end Web Developer,HTML5,CSS,Angular/ReactJS,Sketch/Invision/Photoshop | K65: Joined | L65: No Angular 6 exp | M65: Regular | N65: H28337978 | O65: SHATRUGHAN SAHANI | P65: 9973508305 | Q65: shatrughan.jsr@gmail.com | R65: 10years | S65: 10years | T65: TCS | U65: 750000 | V65: 1500000 | W65: LWD-Jan-25 | X65: N | Y65: N | Z65: N | AA65: Jamshedpu | AB65: Bangalore
A66: 65 | B66: Dell FG | C66: 44559 | D66: 96998230 | E66: Vinay Nambiar | F66: 181547 | G66: Vendor Partner | H66: Growelsoftech pvt ltd | I66: Server | J66: 8-12y Server Virtualization,VMware vSphere,Network Engineering,Software Defined Networking, Load Balancing,DNS Solutions,Kubernetes & Docker,Container Orchestration Infrastructure | K66: Joined | L66: No Angular 6 exp | M66: Regular | N66: 431904 | O66: VIVEK GANGANI | P66: 8102205777 | Q66: vivekgangani@gmail.com | R66: 11years | S66: 11years | T66: VIHAAN NETWORKS LTD | U66: 600000 | V66: 1000000 | W66: 15days | X66: N | Y66: N | Z66: N | AA66: Jamshedpu | AB66: Bangalore
A67: 66 | B67: Dell FG | C67: 44559 | D67: 14885881 | E67: Vinay Nambiar | F67: 181547 | G67: Vendor Partner | H67: Growelsoftech pvt ltd | I67: UI/UX | J67: 5-8y UX/UI Developer with HTML5,CSS3,Bootstrap,Javascript,Typescript | K67: Joined | L67: No Angular 6 exp | M67: Regular | N67: H8031428 | O67: Sivakumar.Y | P67: 9677776784 | Q67: sivakumarka08@gmail.com | R67: 6 years | S67: 6 Years | T67: Sisesoft it solutions | U67: 540000 | V67: 7500000 | W67: 15 Days | X67: N | Y67: N | Z67: N | AA67: Hosur | AB67: Bangalore
A68: 67 | B68: Dell FG | C68: 44559 | D68: 98587791 | E68: Vinay Nambiar | F68: 181547 | G68: Vendor Partner | H68: Growelsoftech pvt ltd | I68: python | J68: 5-8y Python Development | K68: Joined | L68: Requirement closed | M68: Regular | N68: 7392626 | O68: Vinay Kumar | P68: 7696118524 | Q68: vinaykumar.24@hotmail.com | R68: 5.7years | S68: 4.2years | T68: Gemini solution | U68: 1000000 | V68: 1550000 | W68: lwd-20jan | X68: N | Y68: N | Z68: N | AA68: BANGALORE | AB68: Bangalore
A69: 68 | B69: Dell FG | C69: 44559 | D69: 96445940 | E69: Vinay Nambiar | F69: 181547 | G69: Vendor Partner | H69: Mindsoft | I69: .NET CORE | J69: .NET CORE | K69: Offered | L69: Technical reject | M69: Regular | N69: 415962 | O69: Sureshbabu Padarthi | P69: 7981585429 | Q69: sureshbabup8888@gmail.com | R69: 13+YRS | S69: 13yrs | T69: Tech M | U69: 1600000 | V69: 2800000 | W69: LWD-JAN20TH | X69: N | Y69: N | Z69: N | AA69: Hyderabad | AB69: Hyderabad
A70: 69 | B70: Dell FG | C70: 44559 | D70: 94048049 | E70: Vinay Nambiar | F70: 181547 | G70: Vendor Partner | H70: Mindsoft | I70: .NET CORE | J70: .NET CORE | K70: Joined | L70: Other offer | M70: Regular | N70: 417158 | O70: Marripudi Balakrishna | P70: 8978768542 | Q70: marripudi.balakrishna@gmail.com | R70: 3.2yrs | S70: 3.2yrs | T70: Global logic | U70: 5500000 | V70: 1400000 | W70: LWD-DEC-28TH | X70: N | Y70: N | Z70: N | AA70: Hyderabad | AB70: Hyderabad
A71: 70 | B71: Dell FG | C71: 44559 | D71: 96445940 | E71: Vinay Nambiar | F71: 181547 | G71: Vendor Partner | H71: Mindsoft | I71: .NET CORE | J71: .NET CORE | K71: Joined | L71: Other offer | M71: Regular | N71: 417120 | O71: chandra shekar | P71: 6305283750 | Q71: csmansani@gmail.com | R71: 12yrs | S71: 12yrs | T71: Focus softnet | U71: 1660000 | V71: 2300000 | W71: LWD-JAN 17TH | X71: N | Y71: N | Z71: N | AA71: Hyderabad | AB71: Hyderabad
A72: 71 | B72: Dell FG | C72: 44559 | D72: 31824993 | E72: Vinay Nambiar | F72: 181547 | G72: Vendor Partner | H72: Mindsoft | I72: Power BI | J72: 1y Power BI (Tableau or similar data visualization tool),SQL | K72: Hold | L72: Position is on Hold | M72: Regular | N72: 438930 | O72: Amala Erthineni | P72: 9133047548 | Q72: elchuriamala@gmail.com | R72: 2.3 years | S72: 1.7 years in Power BI | T72: Quantyum Technology Solutions Pvt.Ltd | U72: 400000 | V72: 500000 | W72: 15 days official | X72: N | Y72: N | Z72: N | AA72: Hyderabad | AB72: Hyderabad
A73: 72 | B73: Dell FG | C73: 44559 | D73: 31824993 | E73: Vinay Nambiar | F73: 181547 | G73: Vendor Partner | H73: Mindsoft | I73: Power BI | J73: 1y Power BI (Tableau or similar data visualization tool),SQL | K73: Hold | L73: Position is on Hold | M73: Regular | N73: 439881 | O73: Kaukab Nazifa Shaikh | P73: 9182043712 | Q73: kaukabshaikh4@gmail.com | R73: 2.5 years | S73: 2.5 years in Power BI | T73: Pearl Stone Technology Pvt ltd | U73: 220000 | V73: 450000 | W73: 30 days but negotiable to 15 days | X73: N | Y73: N | Z73: N | AA73: Hyderabad | AB73: Hyderabad
A74: 73 | B74: Dell FG | C74: 44559 | D74: 31824993 | E74: Vinay Nambiar | F74: 181547 | G74: Vendor Partner | H74: Mindsoft | I74: Power BI | J74: 1y Power BI (Tableau or similar data visualization tool),SQL | K74: Hold | L74: Position is on Hold | M74: Regular | N74: 440068 | O74: Harish B | P74: 7842809161 | Q74: harishb2109@gmail.com | R74: 1 year | S74: 1 year in Power BI | T74: Techmahindra | U74: 180000 | V74: 450000 | W74: Immediate. Serving notice period. LWD is 15th Jan '22 | X74: N | Y74: N | Z74: N | AA74: Hyderabad | AB74: Hyderabad
A75: 74 | B75: Dell FG | C75: 44559 | D75: 31824993 | E75: Vinay Nambiar | F75: 181547 | G75: Vendor Partner | H75: Mindsoft | I75: Power BI | J75: 1y Power BI (Tableau or similar data visualization tool),SQL | K75: Hold | L75: Position is on Hold | M75: Regular | N75: 440827 | O75: Vellavalam Vishwanath | P75: 9398066805 | Q75: vvvishwanath06@gmail.com | R75: 4 years | S75: 3 years in Power BI | T75: Not working( Last worked with Kfin Technologies till October '21 ) | U75: 180000 | V75: 450000 | W75: Immediate | X75: N | Y75: N | Z75: N | AA75: Hyderabad | AB75: Hyderabad
A76: 75 | B76: Dell FG | C76: 44559 | D76: 31824993 | E76: Vinay Nambiar | F76: 181547 | G76: Vendor Partner | H76: Mindsoft | I76: Power BI | J76: 1y Power BI (Tableau or similar data visualization tool),SQL | K76: Hold | L76: Position is on Hold | M76: Regular | N76: 440883 | O76: Lova Prasad Chikkala | P76: 6304845656 | Q76: clovaprasad@gmail.com | R76: 2 years | S76: 1 year in Power BI | T76: Adcc Infocad Pvt Ltd | U76: 240000 | V76: 480000 | W76: Immediate. Serving notice period. LWD is 4th Jan '22 | X76: N | Y76: N | Z76: N | AA76: Hyderabad | AB76: Hyderabad
A77: 76 | B77: Dell FG | C77: 44560 | D77: 44879198 | E77: Rahul Kapoor | F77: U82721 | G77: Vendor Partner | H77: Nityo InfoTech | I77: .NET,SQL,WEB API | J77: DOTNET | K77: Tech1 Reject | M77: Regular | N77: 444379 | O77: Chandra Sekhar Swain | P77: 9337706028/9938316016 | Q77: csswain6@gmail.com | R77: 4 Years | S77: 3.10 Years | T77: infinite computer solutions | U77: 600000 | V77: 1000000 | W77: Immediate | X77: N | Y77: N | Z77: NA | AA77: Bangalore | AB77: Bangalore
A78: 77 | B78: Dell FG | C78: 44560 | D78: 44879198 | E78: Rahul Kapoor | F78: U82721 | G78: Vendor Partner | H78: Nityo InfoTech | I78: .NET,SQL,WEB API | J78: DOTNET | K78: Client Reject | M78: Regular | N78: 443349 | O78: Varun Dhawan | P78: 8727818110/9915550756 | Q78: varundhawan441@gmail.com | R78: 2.6 Years | S78: 2 Years | T78: InPracSys | U78: 324000 | V78: 950000 | W78: 30days(20days) | X78: N | Y78: N | Z78: NA | AA78: Amritsar | AB78: Bangalore
A79: 78 | B79: Dell FG | C79: 44560 | D79: 44879198 | E79: Rahul Kapoor | F79: U82721 | G79: Vendor Partner | H79: Nityo InfoTech | I79: .NET,SQL,WEB API | J79: DOTNET | K79: Tech1 Reject | M79: Regular | N79: 443334 | O79: Rabindra Kumar Gupta | P79: 8789522979/8052980343 | Q79: Rabindra19gupta@gmail.com | R79: 3.1 Years | S79: 3 Years | T79: Accenture India Pvt Ltd | U79: 500000 | V79: 900000 | W79: Immediate | X79: N | Y79: N | Z79: NA | AA79: Gurgaon | AB79: Bangalore
A80: 79 | B80: Dell FG | C80: 44560 | D80: 44879198 | E80: Rahul Kapoor | F80: U82721 | G80: Vendor Partner | H80: Nityo InfoTech | I80: .NET,SQL,WEB API | J80: DOTNET | K80: Tech2 IP | M80: Regular | N80: 444092 | O80: Shiva Kumar V | P80: 7406065250/7019125804 | Q80: rishigowda315@gmail.com | R80: 2 Years | S80: 2 Years | T80: ITC INFOTECH INDIA LTD | U80: 290000 | V80: 9500000 | W80: Immediate | X80: N | Y80: N | Z80: NA | AA80: Bangalore | AB80: Bangalore
A81: 80 | B81: Dell FG | C81: 44560 | D81: 50201569 | E81: Rahul Kapoor | F81: U82721 | G81: Vendor Partner | H81: Nityo InfoTech | I81: Mobility | J81: Mobility | K81: Client Reject | M81: Regular | N81: 443201 | O81: Mohammed Athar | P81: 8919936755 | Q81: mohammedatharf@gmail.com | R81: 5.6yrs | S81: 2.6yrs | T81: Raising Infotech | U81: 420000 | V81: 720000 | W81: 30 days official(Neg) | X81: N | Y81: N | Z81: N | AA81: Hyderabad | AB81: Hyderabad
A82: 81 | B82: Dell FG | C82: 44560 | D82: 50201569 | E82: Rahul Kapoor | F82: U82721 | G82: Vendor Partner | H82: Nityo InfoTech | I82: Mobility | J82: Mobility | K82: Client Reject | M82: Regular | N82: 443291 | O82: Amresh Kumar | P82: 6207414470 | Q82: singhamresh1993.kumar@gmail.com | R82: 5.8yrs | S82: 4yrs | T82: Quaser telecom | U82: 480000 | V82: 800000 | W82: 30 days | X82: N | Y82: N | Z82: N | AA82: Hyderabad | AB82: Hyderabad
A83: 82 | B83: Dell FG | C83: 44560 | D83: 39949317 | E83: Rahul Kapoor | F83: U82721 | G83: Vendor Partner | H83: Nityo InfoTech | I83: Java,Selenium,API | J83: SDET | K83: Client IP | L83: Waiting for client feedback | M83: Regular | N83: 446688 | O83: Agyarapu Srinivas | P83: 9542336206/8096984181 | Q83: srinivas.agyarapu@gmail.com | R83: 3.5 Years | S83: 3.3 Years | T83: PROMAESTRO TECHSOURCE PRIVATE LIMITED | U83: 480000 | V83: 850000 | W83: 15days | X83: N | Y83: N | Z83: NA | AA83: Hyderabad | AB83: Bangalore
A84: 83 | B84: Dell FG | C84: 44560 | D84: 39949317 | E84: Rahul Kapoor | F84: U82721 | G84: Vendor Partner | H84: Nityo InfoTech | I84: Java,Selenium,API | J84: SDET | K84: Client IP | L84: Waiting for client feedback | M84: Regular | N84: 445387 | O84: B.Ashok Reddy | P84: 918143754908/9502459279 | Q84: reddy.ashok1008@gmail.com | R84: 4.10 Years | S84: 3 Years | T84: skylives infotech pvt ltd | U84: 520000 | V84: 9500000 | W84: Immediate | X84: N | Y84: N | Z84: NA | AA84: Hyderabad | AB84: Bangalore
A85: 84 | B85: Dell FG | C85: 44560 | D85: 39949317 | E85: Rahul Kapoor | F85: U82721 | G85: Vendor Partner | H85: Nityo InfoTech | I85: Java,Selenium,API | J85: SDET | K85: Offered | L85: Waiting for client feedback | M85: Regular | N85: 446552 | O85: chandrasekhar ch | P85: 8105432661/9848074068 | Q85: chandrach311@gmail.com | R85: 3 Years | S85: 2 Years | T85: Accenture | U85: 480000 | V85: 850000 | W85: LWD:4/01/22 | X85: N | Y85: N | Z85: NA | AA85: Bangalore | AB85: Bangalore
A86: 85 | B86: Dell FG | C86: 44560 | D86: 39949317 | E86: Rahul Kapoor | F86: U82721 | G86: Vendor Partner | H86: Nityo InfoTech | I86: Java,Selenium,API | J86: SDET | K86: Client IP | L86: Waiting for client feedback | M86: Regular | N86: 446614 | O86: Pramod.L.Dhanave | P86: 7620686822/8806785100 | Q86: dhanavepl99@gmail.com | R86: 3.2 Years | S86: 2 Years | T86: Tibco india pvt ltd | U86: 450000 | V86: 800000 | W86: 15days | X86: N | Y86: N | Z86: NA | AA86: Pune | AB86: Bangalore
A87: 86 | B87: Dell FG | C87: 44560 | D87: 39949317 | E87: Rahul Kapoor | F87: U82721 | G87: Vendor Partner | H87: Nityo InfoTech | I87: Java,Selenium,API | J87: SDET | K87: Client IP | L87: Waiting for client feedback | M87: Regular | N87: 446640 | O87: Mohsin Phutankar | P87: 8329313263/9766735788 | Q87: phutankarmohsin@gmail.com | R87: 3.2 Years | S87: 3.2 Years | T87: PubMatic India Pvt Ltd | U87: 490000 | V87: 900000 | W87: 15days | X87: N | Y87: N | Z87: NA | AA87: Pune | AB87: Bangalore
A88: 87 | B88: Dell FG | C88: 44560 | D88: 50201569 | E88: Rahul Kapoor | F88: U82721 | G88: Vendor Partner | H88: Mindsoft | I88: Mobility | J88: Mobility | K88: Client IP | L88: Waiting for client feedback | M88: Regular | N88: 443201 | O88: Mohammed Athar | P88: 8919936755 | Q88: mohammedatharf@gmail.com | R88: 5.6yrs | S88: 5.6yrs | U88: 420000 | V88: 720000 | W88: 30 days official(Neg) | X88: N | Y88: N | Z88: N | AA88: Hyderabad | AB88: Hyderabad
A89: 88 | B89: Dell FG | C89: 44560 | D89: 50201569 | E89: Rahul Kapoor | F89: U82721 | G89: Vendor Partner | H89: Mindsoft | I89: Mobility | J89: Mobility | K89: Client IP | L89: Waiting for client feedback | M89: Regular | N89: 443291 | O89: Amresh Kumar | P89: 6207414470 | Q89: singhamresh1993.kumar@gmail.com | R89: 5.8yrs | S89: 5.8yrs | U89: 480000 | V89: 800000 | W89: 30 days | X89: N | Y89: N | Z89: N | AA89: Hyderabad | AB89: Hyderabad
A90: 89 | B90: Dell FG | C90: 44560 | D90: 76222649 | E90: Vinay Nambiar | F90: 181547 | G90: Vendor Partner | H90: Mindsoft | I90: PL SQL Dev | J90: Oracle,Informatica | K90: Joined | L90: No Show | M90: Regular | N90: 443413 | O90: Bindu Nanubala | P90: 7793997081 | Q90: bindunanubala.8@gmail.com | R90: 4.2yrs | S90: 4.2yrs | T90: Ness Technology | U90: 480000 | V90: 700000 | W90: Lwd Jan 12th | X90: N | Y90: N | Z90: N | AA90: Hyderabad | AB90: Hyderabad
A91: 90 | B91: Dell FG | C91: 44560 | D91: 76222649 | E91: Vinay Nambiar | F91: 181547 | G91: Vendor Partner | H91: Mindsoft | I91: PL SQL Dev | J91: Oracle,Informatica | K91: Joined | L91: No Show | M91: Regular | N91: 444799 | O91: Murali Krishna B | P91: 9908305965 | Q91: murali2db@gmail.com | R91: 3.5yrs | S91: 2.11yrs | T91: Mindtree | U91: 400000 | V91: 700000 | W91: 30 days(Neg) | X91: N | Y91: N | Z91: N | AA91: Hyderabad | AB91: Hyderabad
A92: 91 | B92: Dell FG | C92: 44560 | D92: 31824993 | E92: Vinay Nambiar | F92: 181547 | G92: Vendor Partner | H92: Mindsoft | I92: Power BI | J92: 1y Power BI (Tableau or similar data visualization tool),SQL | K92: Hold | L92: Position is on Hold | M92: Regular | N92: 444414 | O92: Mahesh Gundluru | P92: 9704828135 | Q92: maheshchintu432@gmail.com | R92: 3 years | S92: 3 years in Power BI | T92: Seed-flow Cyber Tech Pvt Ltd | U92: 170000 | V92: 450000 | W92: 30 days but negotiable to 15 days | X92: N | Y92: N | Z92: N | AA92: Hyderabad | AB92: Hyderabad
A93: 92 | B93: Dell FG | C93: 44560 | D93: 31824993 | E93: Vinay Nambiar | F93: 181547 | G93: Vendor Partner | H93: Mindsoft | I93: Power BI | J93: 1y Power BI (Tableau or similar data visualization tool),SQL | K93: Hold | L93: Position is on Hold | M93: Regular | N93: 444515 | O93: Rajasekhar Reddy K | P93: 8019844117 | Q93: Krajsekharreddkk@gmail.com | R93: 2.8 years | S93: 2 years in Power BI | T93: Stratycon Technologies | U93: 320000 | V93: 450000 | W93: 30 days but negotiable to 15 days. Currently on bench | X93: N | Y93: N | Z93: N | AA93: Bangalore | AB93: Hyderabad
A94: 93 | B94: Dell FG | C94: 44560 | D94: 53300677 | E94: Vinay Nambiar | F94: 181547 | G94: Vendor Partner | H94: Mindsoft | I94: SDET | J94: java selenium | K94: Joined | L94: Joined | M94: Regular | N94: 443497 | O94: Hemanth | P94: 7396642265 | Q94: dasarihemanth432@gmail.com | R94: 3.10yrs | S94: 2yrs | T94: Ericsson | U94: 400000 | V94: 800000 | W94: Immediate | X94: N | Y94: N | Z94: N | AA94: Hyderabad | AB94: Hyderabad
A95: 94 | B95: Dell FG | C95: 44560 | D95: 53300677 | E95: Vinay Nambiar | F95: 181547 | G95: Vendor Partner | H95: Mindsoft | I95: SDET | J95: java selenium | K95: Joined | L95: Joined | M95: Regular | N95: 444754 | O95: Kalyan | P95: 9182268829 | Q95: tkalyan816@gmail.com | R95: 3.2yrs | S95: 2yrs | T95: Mahendrada Softtech | U95: 620000 | V95: 850000 | W95: Immediate | X95: N | Y95: N | Z95: N | AA95: Hyderabad | AB95: Hyderabad
A96: 95 | B96: Dell FG | C96: 44560 | D96: 53300677 | E96: Vinay Nambiar | F96: 181547 | G96: Vendor Partner | H96: Mindsoft | I96: SDET | J96: java selenium | K96: Joined | L96: Joined | M96: Regular | N96: 445309 | O96: Pooja Rudrawar | P96: 8793228193 | Q96: rudrawarpooja81@gmail.com | R96: 3.5yrs | S96: 3.5yrs | T96: Bitwise Solutions | U96: 480000 | V96: 850000 | W96: 30days(nego 15days) | X96: N | Y96: N | Z96: N | AA96: Hyderabad | AB96: Hyderabad
A97: 96 | B97: Dell FG | C97: 44560 | D97: 53300677 | E97: Vinay Nambiar | F97: 181547 | G97: Vendor Partner | H97: Mindsoft | I97: SDET | J97: java selenium | K97: Joined | L97: Joined | M97: Regular | N97: 446449 | O97: PALLE SIVA RAMI REDDY | P97: 8500777534 | Q97: sivaramireddy75@gmail.com | R97: 2.8yrs | S97: 2yrs | T97: Cogbizant | U97: 485000 | V97: 1100000 | W97: lwd-jan 28th | X97: N | Y97: N | Z97: N | AA97: Hyderabad | AB97: Hyderabad
A98: 97 | B98: Dell FG | C98: 44561 | D98: 39949317 | E98: Rahul Kapoor | F98: U82721 | G98: Vendor Partner | H98: Nityo InfoTech | I98: Java,Selenium,API | J98: SDET | K98: Tech1 Reject | M98: Regular | N98: 449579 | O98: Bharat Dutt | P98: 918971936148/9560433176 | Q98: bharatdutt21@gmail.com | R98: 8 Years | S98: 4 Years | T98: Capgemini Technology Services India Limit | U98: 1000000 | V98: 1650000 | W98: Immediate | X98: N | Y98: N | Z98: NA | AA98: Pune | AB98: Bangalore
A99: 98 | B99: Dell FG | C99: 44561 | D99: 39949317 | E99: Rahul Kapoor | F99: U82721 | G99: Vendor Partner | H99: Nityo InfoTech | I99: Java,Selenium,API | J99: SDET | K99: Tech1 Reject | M99: Regular | N99: 450788 | O99: mamatha chinthareddy | P99: 9652911711/9959900011 | Q99: mamatha.chinthareddy1990@gmail.com | R99: 6.7 Years | S99: 3 Years | T99: IBM India Pvt. Limited | U99: 800000 | V99: 1450000 | W99: 30days(Neg 15days) | X99: N | Y99: N | Z99: NA | AA99: Hyderabad | AB99: Bangalore
A100: 99 | B100: Dell FG | C100: 44561 | D100: 39949317 | E100: Rahul Kapoor | F100: U82721 | G100: Vendor Partner | H100: Nityo InfoTech | I100: Java,Selenium,API | J100: SDET | K100: Tech1 Reject | M100: Regular | N100: 449697 | O100: Papun Kumar Sahoo | P100: 9348568166/9658229904 | Q100: papunk151@gmail.com | R100: 5.3 Years | S100: 4 Years | T100: Infosys(Payroll of Trigent Software) | U100: 531000 | V100: 1200000 | W100: 30days(Neg 20days) | X100: Y | Y100: N | Z100: NA | AA100: Bangalore | AB100: Bangalore
...

Sheet Questions
H6: 1): we have to show dashboard for
H7: 2): The candidates joined in different years
H8: 3): show top 5 skills hired in 2024
H9: 4): Top 3 locations from where we hired
H10: 5): Top 2 locations candidates preffered
H11: 6): Reqruiter performance: Joiner per reqruiter
H12: 7): Total offered, Total joined, offered to joining percentage
H13: 8): Total salary offered in one year
H14: 9): experience range 0-5, 5-10,10-15,15-20
H15: 10): data cleanup

Sheet  Q55
A3: Row Labels | B3: Count of Preferred Location
A4: Bangalore | B4: 569
A5: Hyderabad | B5: 147
A6: Grand Total | B6: 716

Sheet Q22
A3: Row Labels | B3: Count of Candidate Status
A4: 2021 | B4: 36
A5: 2022 | B5: 689
A6: Grand Total | B6: 725

Sheet Dashboard 2

Sheet Q33
A3: Row Labels | B3: Count of Mandatory Skill
A4: SDET | B4: 79
A5: Java | B5: 69
A6: Java Developer | B6: 42
A7: DOTNET | B7: 37
A8: UI Developer | B8: 23
A9: DW/EBI | B9: 23
A10: Grand Total | B10: 273

Sheet Q44
A3: Row Labels | B3: Count of Current Location
A4: Bangalore | B4: 331
A5: Hyderabad | B5: 185
A6: Pune | B6: 35
A7: Chennai | B7: 35
A8: Grand Total | B8: 586

Sheet Q66
A3: Row Labels | B3: Count of Candidate Status
A4: Divakara Rangaswamy | B4: 11
A5: Rahul Kapoor | B5: 72
A6: Dinesh Shiranpel | B6: 124
A7: Vinay Nambiar | B7: 176
A8: Febha John | B8: 342
A9: Grand Total | B9: 725

Sheet Q88
A3: Row Labels | B3: Sum of CTC
A4: 2021 | B4: 36575000
A5: 2022 | B5: 724796600
A6: Grand Total | B6: 761371600

Sheet Q99
A3: Row Labels | B3: Count of Year of Exp
A4: 1-5 | B4: 327
A5: 6-10 | B5: 343
A6: 11-15 | B6: 48
A7: 16-20 | B7: 4
A8: 26-30 | B8: 1
A9: 31-35 | B9: 2
A10: Grand Total | B10: 725

Sheet Candidate Data &Q7
A1: Sl.No | B1: Account | C1: Profile Submission Date | D1: SO Number | E1: Reqruiter Name | F1: Employee ID | G1: Source | H1: Sub Source | I1: Mandatory Skill | J1: Skill Combinations | K1: Candidate Status | L1: Detailed Status | M1: Hire Type | N1: Candidate ID | O1: Candidate Name | P1: Contact Number | Q1: Email id | R1: Total Yrs of Exp | S1: Current Company | T1: CTC | U1: Notice Period | V1: Ex-Employee(Y/N) | W1: Current Location | X1: Preferred Location | Y1: Month of Profile Submission | Z1: Year of Profile Submission | AA1: YO1 | AB1: YO2 | AC1: YO3 | AD1: YO4 | AE1: YO5 | AF1: YO6 | AG1: Year of Exp
A2: 1 | B2: Dell FG | C2: 44546 | D2: 38024355 | E2: Rahul Kapoor | F2: U82721 | G2: Vendor Partner | H2: Mindsoft | I2: Java Selenium | J2: JAVA SELENIUM | K2: Dropped | L2: Back up candidates | M2: Regular | N2: 484611 | O2: Jacob | P2: 9553801682 | Q2: jacobkoheer@gmail.com | R2: 3yrs | S2: Sun icon | T2: 600000 | U2: LWD-Dec 22nd-Immediate | V2: N | W2: Hyderabad | X2: Bangalore | Y2: =MONTH($C2) -> 12 | Z2: =YEAR($C2) -> 2021 | AA2: =LEFT(R2,2) -> 3y | AB2: =SUBSTITUTE(AA2,"y","") -> 3 | AC2: =SUBSTITUTE(AB2,".","") -> 3 | AD2: =SUBSTITUTE(AC2,"+","") -> 3 | AE2: =SUBSTITUTE(AD2,"Y","") -> 3 | AF2: =SUBSTITUTE(AE2,"e","") -> 3 | AG2: =SUBSTITUTE(AF2,",","")*1 -> 3
A3: 2 | B3: Dell FG | C3: 44550 | D3: 38024355 | E3: Rahul Kapoor | F3: U82721 | G3: Vendor Partner | H3: Mindsoft | I3: SDET | J3: JAVA SELENIUM | K3: Tech1 Reject | L3: Screening IP | M3: Regular | N3: 351671 | O3: T M NANDINI | P3: 9739829708 | Q3: nandini.m.t78@gmail.com | R3: 3.4yrs | S3: Mindtree | T3: 550000 | U3: LWD-JAN 25TH | V3: N | W3: Bangalore | X3: Bangalore | Y3: =MONTH($C3) -> 12 | Z3: =YEAR($C3) -> 2021 | AA3: =LEFT(R3,2) -> 3. | AB3: =SUBSTITUTE(AA3,"y","") -> 3. | AC3: =SUBSTITUTE(AB3,".","") -> 3 | AD3: =SUBSTITUTE(AC3,"+","") -> 3 | AE3: =SUBSTITUTE(AD3,"Y","") -> 3 | AF3: =SUBSTITUTE(AE3,"e","") -> 3 | AG3: =SUBSTITUTE(AF3,",","")*1 -> 3
A4: 3 | B4: Dell FG | C4: 44550 | D4: 94967553 | E4: Rahul Kapoor | F4: U82721 | G4: UST Global | H4: Mindsoft | I4: QA , Manual tester role | J4: SDET | K4: Dropped | L4: Rejected | M4: Regular | N4: 354205 | O4: Vaishali Dixit | P4: 9691520066 | Q4: dixit.vaishali08@gmail.com | R4: 3.5yrs | S4: Capgemini | T4: 450000 | U4: 30 days(LWD: 26th Jan) | V4: N | W4: Bangalore | X4: Bangalore | Y4: =MONTH($C4) -> 12 | Z4: =YEAR($C4) -> 2021 | AA4: =LEFT(R4,2) -> 3. | AB4: =SUBSTITUTE(AA4,"y","") -> 3. | AC4: =SUBSTITUTE(AB4,".","") -> 3 | AD4: =SUBSTITUTE(AC4,"+","") -> 3 | AE4: =SUBSTITUTE(AD4,"Y","") -> 3 | AF4: =SUBSTITUTE(AE4,"e","") -> 3 | AG4: =SUBSTITUTE(AF4,",","")*1 -> 3
A5: 4 | B5: Dell FG | C5: 44550 | D5: 31972088 | E5: Vinay Nambiar | F5: 181547 | G5: Vendor Partner | H5: SRS | I5: Java | J5: Java/J2EE,Spring Boot,Spring Core,Spring MVC, Spring Web Services, Spring boot, Spring Data, Spring Cloud,HTML/CSS/JS | K5: Joined | L5: Interview No show | M5: Regular | N5: 419101 | O5: Hema Latha | P5: 9948358570 | Q5: hemalatha.friends@gmail.com | R5: 14 yr | S5: Infosys | T5: 1450000 | U5: LWD : 4/1/2021 | V5: N | W5: Hyderabad | X5: Hyderabad | Y5: =MONTH($C5) -> 12 | Z5: =YEAR($C5) -> 2021 | AA5: =LEFT(R5,2) -> 14 | AB5: =SUBSTITUTE(AA5,"y","") -> 14 | AC5: =SUBSTITUTE(AB5,".","") -> 14 | AD5: =SUBSTITUTE(AC5,"+","") -> 14 | AE5: =SUBSTITUTE(AD5,"Y","") -> 14 | AF5: =SUBSTITUTE(AE5,"e","") -> 14 | AG5: =SUBSTITUTE(AF5,",","")*1 -> 14 | AI5: Total Joined | AJ5: =COUNTIF(K2:K3040,"Joined") -> 725
A6: 5 | B6: Dell FG | C6: 44551 | D6: 94967553 | E6: Rahul Kapoor | F6: U82721 | G6: UST Global | H6: Mindsoft | I6: QA , Manual tester role:- | J6: SDET | K6: Joined | L6: Rejected | M6: Regular | N6: 379458 | O6: Alekya | P6: 9441095144 | Q6: alekya.d1988@gmail.com | R6: 4.8yrs | S6: Nuance Transcription | T6: 500000 | U6: Immediate | V6: N | W6: Bangalore | X6: Bangalore | Y6: =MONTH($C6) -> 12 | Z6: =YEAR($C6) -> 2021 | AA6: =LEFT(R6,2) -> 4. | AB6: =SUBSTITUTE(AA6,"y","") -> 4. | AC6: =SUBSTITUTE(AB6,".","") -> 4 | AD6: =SUBSTITUTE(AC6,"+","") -> 4 | AE6: =SUBSTITUTE(AD6,"Y","") -> 4 | AF6: =SUBSTITUTE(AE6,"e","") -> 4 | AG6: =SUBSTITUTE(AF6,",","")*1 -> 4 | AI6: Total Declined | AJ6: =COUNTIF(K2:K3040,"Declined") -> 73
A7: 6 | B7: Dell FG | C7: 44551 | D7: 82866188 | E7: Rahul Kapoor | F7: U82721 | G7: UST Global | H7: Mindsoft | I7: UI/UX role | J7: UI | K7: Dropped | L7: Drop out | M7: Regular | N7: 355575 | O7: Rajesh Sah | P7: 9739607439 | Q7: codeuix@gmail.com | R7: 6 years | S7: Nubewell Networks Pvt Ltd | T7: 1500000 | U7: 11-Jan LWD | V7: N | W7: Bangalore | X7: Bangalore | Y7: =MONTH($C7) -> 12 | Z7: =YEAR($C7) -> 2021 | AA7: =LEFT(R7,2) -> 6 | AB7: =SUBSTITUTE(AA7,"y","") -> 6 | AC7: =SUBSTITUTE(AB7,".","") -> 6 | AD7: =SUBSTITUTE(AC7,"+","") -> 6 | AE7: =SUBSTITUTE(AD7,"Y","") -> 6 | AF7: =SUBSTITUTE(AE7,"e","") -> 6 | AG7: =SUBSTITUTE(AF7,",","")*1 -> 6 | AI7: Total Offered | AJ7: =$AJ$5+$AJ$6 -> 798
A8: 7 | B8: Dell FG | C8: 44551 | D8: 82866188 | E8: Rahul Kapoor | F8: U82721 | G8: UST Global | H8: Mindsoft | I8: UI/UX role | J8: UI | K8: Dropped | L8: Drop out | M8: Regular | N8: H8271088 | O8: Ankita Awasthi | P8: 9717348292 | Q8: ankitaawasthi05@gmail.com | R8: 7.6years | S8: Genpact | T8: 1000000 | U8: 29-Dec LWD | V8: N | W8: Bangalore | X8: Bangalore | Y8: =MONTH($C8) -> 12 | Z8: =YEAR($C8) -> 2021 | AA8: =LEFT(R8,2) -> 7. | AB8: =SUBSTITUTE(AA8,"y","") -> 7. | AC8: =SUBSTITUTE(AB8,".","") -> 7 | AD8: =SUBSTITUTE(AC8,"+","") -> 7 | AE8: =SUBSTITUTE(AD8,"Y","") -> 7 | AF8: =SUBSTITUTE(AE8,"e","") -> 7 | AG8: =SUBSTITUTE(AF8,",","")*1 -> 7 | AI8: Offered to Joined Percentage | AJ8: =($AJ$5/$AJ$7)*100 -> 90.85213
A9: 8 | B9: Dell FG | C9: 44551 | D9: 51907700 | E9: Vinay Nambiar | F9: 181547 | G9: Vendor Partner | H9: SRS | I9: Java | J9: Java/J2EE,Spring Boot,Spring Core,Spring MVC, Spring Web Services, Spring boot, Spring Data, Spring Cloud,HTML/CSS/JS | K9: Joined | L9: Not responding | M9: Regular | N9: H14387 | O9: Sreedhar Vinjamuri | P9: 7337067133 | Q9: sreedhar.vin12@gmail.com | R9: 13 yr | S9: Virinchi Technologies | T9: 1500000 | U9: IMMEDATE JOINNER | V9: N | W9: Hyderabad | X9: Hyderabad | Y9: =MONTH($C9) -> 12 | Z9: =YEAR($C9) -> 2021 | AA9: =LEFT(R9,2) -> 13 | AB9: =SUBSTITUTE(AA9,"y","") -> 13 | AC9: =SUBSTITUTE(AB9,".","") -> 13 | AD9: =SUBSTITUTE(AC9,"+","") -> 13 | AE9: =SUBSTITUTE(AD9,"Y","") -> 13 | AF9: =SUBSTITUTE(AE9,"e","") -> 13 | AG9: =SUBSTITUTE(AF9,",","")*1 -> 13
A10: 9 | B10: Dell FG | C10: 44551 | D10: 57335575 | E10: Vinay Nambiar | F10: 181547 | G10: Vendor Partner | H10: SRS | I10: Java | J10: Java/J2EE,Spring Boot,Spring Core,Spring MVC, Spring Web Services, Spring boot, Spring Data, Spring Cloud,HTML/CSS/JS | K10: Joined | L10: Interview No show | M10: Regular | N10: 419812 | O10: Pokuri Ramanjaneyulu | P10: 8106332319 | Q10: ram1980.p@gmail.com | R10: 14 yr | S10: HCL Technologies, | T10: 1450000 | U10: LWD: 28/1/2021 | V10: N | W10: Hyderabad | X10: Hyderabad | Y10: =MONTH($C10) -> 12 | Z10: =YEAR($C10) -> 2021 | AA10: =LEFT(R10,2) -> 14 | AB10: =SUBSTITUTE(AA10,"y","") -> 14 | AC10: =SUBSTITUTE(AB10,".","") -> 14 | AD10: =SUBSTITUTE(AC10,"+","") -> 14 | AE10: =SUBSTITUTE(AD10,"Y","") -> 14 | AF10: =SUBSTITUTE(AE10,"e","") -> 14 | AG10: =SUBSTITUTE(AF10,",","")*1 -> 14
A11: 10 | B11: Dell FG | C11: 44551 | D11: 94990037 | E11: Vinay Nambiar | F11: 181547 | G11: Vendor Partner | H11: SRS | I11: Java | J11: Java/J2EE,Spring Boot,Spring Core,Spring MVC, Spring Web Services, Spring boot, Spring Data, Spring Cloud,HTML/CSS/JS | K11: Joined | L11: Interview No show | M11: Regular | N11: 418251 | O11: Sailaja Malyala | P11: 9848623920 | Q11: sailajamalyal@gmail.com | R11: 14 yr | S11: IBM | T11: 1200000 | U11: ELWD : 26/01/22 | V11: N | W11: Hyderabad | X11: Hyderabad | Y11: =MONTH($C11) -> 12 | Z11: =YEAR($C11) -> 2021 | AA11: =LEFT(R11,2) -> 14 | AB11: =SUBSTITUTE(AA11,"y","") -> 14 | AC11: =SUBSTITUTE(AB11,".","") -> 14 | AD11: =SUBSTITUTE(AC11,"+","") -> 14 | AE11: =SUBSTITUTE(AD11,"Y","") -> 14 | AF11: =SUBSTITUTE(AE11,"e","") -> 14 | AG11: =SUBSTITUTE(AF11,",","")*1 -> 14
A12: 11 | B12: Dell FG | C12: 44552 | D12: 44173531 | E12: Vinay Nambiar | F12: 181547 | G12: Vendor Partner | H12: SRS | I12: Java | J12: Java/J2EE, Angularjs | K12: Dropped | L12: Not interested | M12: Regular | N12: 421816 | O12: G.Ramana Reddy | P12: 9390911344 | Q12: grreddy1729@gmail.com | R12: 5 Years | S12: L&T Infotech | T12: 900000 | U12: LWD 30-01-2022 | V12: N | W12: Hyderabad | X12: Hyderabad | Y12: =MONTH($C12) -> 12 | Z12: =YEAR($C12) -> 2021 | AA12: =LEFT(R12,2) -> 5 | AB12: =SUBSTITUTE(AA12,"y","") -> 5 | AC12: =SUBSTITUTE(AB12,".","") -> 5 | AD12: =SUBSTITUTE(AC12,"+","") -> 5 | AE12: =SUBSTITUTE(AD12,"Y","") -> 5 | AF12: =SUBSTITUTE(AE12,"e","") -> 5 | AG12: =SUBSTITUTE(AF12,",","")*1 -> 5
A13: 12 | B13: Dell FG | C13: 44552 | D13: 44173531 | E13: Vinay Nambiar | F13: 181547 | G13: Vendor Partner | H13: SRS | I13: Java | J13: Java/J2EE, Angularjs | K13: Screen Reject | L13: Not responding | M13: Regular | N13: 421822 | O13: Prem Kumar Jannu | P13: 7893092220 | Q13: prem.jannu182829@gamil.com | R13: 9 Years | S13: Infosys LTD | T13: 1200000 | U13: LWD 31-01-2022 | V13: N | W13: Hyderabad | X13: Hyderabad | Y13: =MONTH($C13) -> 12 | Z13: =YEAR($C13) -> 2021 | AA13: =LEFT(R13,2) -> 9 | AB13: =SUBSTITUTE(AA13,"y","") -> 9 | AC13: =SUBSTITUTE(AB13,".","") -> 9 | AD13: =SUBSTITUTE(AC13,"+","") -> 9 | AE13: =SUBSTITUTE(AD13,"Y","") -> 9 | AF13: =SUBSTITUTE(AE13,"e","") -> 9 | AG13: =SUBSTITUTE(AF13,",","")*1 -> 9
A14: 13 | B14: Dell FG | C14: 44552 | D14: 67489866 | E14: Vinay Nambiar | F14: 181547 | G14: Vendor Partner | H14: SRS | I14: DevOps | J14: 5-8y Devops with GIT,CICD (Gitlab),Powershell/Bash | K14: Dropped | L14: Requirement closed | M14: Regular | N14: 421830 | O14: Srinivas. Y | P14: 8247858588 | Q14: srinivasyara1257@gmail.com | R14: 5.3years | S14: Sciens Software Technologies | T14: 650000 | U14: 25days | V14: N | W14: Hyderabad | X14: Hyderabad | Y14: =MONTH($C14) -> 12 | Z14: =YEAR($C14) -> 2021 | AA14: =LEFT(R14,2) -> 5. | AB14: =SUBSTITUTE(AA14,"y","") -> 5. | AC14: =SUBSTITUTE(AB14,".","") -> 5 | AD14: =SUBSTITUTE(AC14,"+","") -> 5 | AE14: =SUBSTITUTE(AD14,"Y","") -> 5 | AF14: =SUBSTITUTE(AE14,"e","") -> 5 | AG14: =SUBSTITUTE(AF14,",","")*1 -> 5
A15: 14 | B15: Dell FG | C15: 44553 | D15: 94967553 | E15: Rahul Kapoor | F15: U82721 | G15: UST Global | H15: Mindsoft | I15: QA , Manual tester role | J15: SDET | K15: Dropped | L15: Pending | M15: Regular | N15: 389073 | O15: Vishnu kumar | P15: 9390839924 | Q15: m.vishnu225@gmail.com | R15: 3 yrs | S15: Brillquest technologies Pvt Ltd | T15: 300000 | U15: LWD-3rd Jan 22 | V15: N | W15: Bangalore | X15: Bangalore | Y15: =MONTH($C15) -> 12 | Z15: =YEAR($C15) -> 2021 | AA15: =LEFT(R15,2) -> 3 | AB15: =SUBSTITUTE(AA15,"y","") -> 3 | AC15: =SUBSTITUTE(AB15,".","") -> 3 | AD15: =SUBSTITUTE(AC15,"+","") -> 3 | AE15: =SUBSTITUTE(AD15,"Y","") -> 3 | AF15: =SUBSTITUTE(AE15,"e","") -> 3 | AG15: =SUBSTITUTE(AF15,",","")*1 -> 3
A16: 15 | B16: Dell FG | C16: 44553 | D16: 67489866 | E16: Vinay Nambiar | F16: 181547 | G16: Vendor Partner | H16: SRS | I16: DevOps | J16: 5-8y Devops with GIT,CICD (Gitlab),Powershell/Bash | K16: Dropped | L16: Requirement closed | M16: Regular | N16: 421842 | O16: Tejaswi Jonnalagadda | P16: 6302517658 | Q16: tejaswi.jonnalagadda91@gmail.com | R16: 7.2years | S16: Cognizant | T16: 510000 | U16: 30days | V16: N | W16: Hyderabad | X16: Hyderabad | Y16: =MONTH($C16) -> 12 | Z16: =YEAR($C16) -> 2021 | AA16: =LEFT(R16,2) -> 7. | AB16: =SUBSTITUTE(AA16,"y","") -> 7. | AC16: =SUBSTITUTE(AB16,".","") -> 7 | AD16: =SUBSTITUTE(AC16,"+","") -> 7 | AE16: =SUBSTITUTE(AD16,"Y","") -> 7 | AF16: =SUBSTITUTE(AE16,"e","") -> 7 | AG16: =SUBSTITUTE(AF16,",","")*1 -> 7
A17: 16 | B17: Dell FG | C17: 44553 | D17: 98936697 | E17: Vinay Nambiar | F17: 181547 | G17: Vendor Partner | H17: SRS | I17: Java | J17: Java/J2EE,Full Stack Developer,Spring Boot,Angular,Cloud Technologies | K17: Screen Reject | L17: Not responding | M17: Regular | N17: 422936 | O17: Raja Mohan Munjeti | P17: 9492543488 | Q17: mohan123.java@gmail.com | R17: 14 yr | S17: Birlasoft | T17: 1300000 | U17: LWD 20/1/2022 | V17: N | W17: Hyderabad | X17: Hyderabad | Y17: =MONTH($C17) -> 12 | Z17: =YEAR($C17) -> 2021 | AA17: =LEFT(R17,2) -> 14 | AB17: =SUBSTITUTE(AA17,"y","") -> 14 | AC17: =SUBSTITUTE(AB17,".","") -> 14 | AD17: =SUBSTITUTE(AC17,"+","") -> 14 | AE17: =SUBSTITUTE(AD17,"Y","") -> 14 | AF17: =SUBSTITUTE(AE17,"e","") -> 14 | AG17: =SUBSTITUTE(AF17,",","")*1 -> 14
A18: 17 | B18: Dell FG | C18: 44554 | D18: 34147670 | E18: Rahul Kapoor | F18: U82721 | G18: UST Global | H18: Mindsoft | I18: C#.NET,.NET Core, Web API, MVC,Angular,Jquery role . | J18: C#.NET | K18: Dropped | L18: High ctc expectation | M18: Regular | N18: H7835795 | O18: Venna Bhagyalakshmi | P18: 7022114311 | Q18: Bhagyalaxmi.venna@gmail.com | R18: 5.1 years | S18: Infosys, | T18: 730000 | U18: 10-Jan LWD | V18: N | W18: Bangalore | X18: Bangalore | Y18: =MONTH($C18) -> 12 | Z18: =YEAR($C18) -> 2021 | AA18: =LEFT(R18,2) -> 5. | AB18: =SUBSTITUTE(AA18,"y","") -> 5. | AC18: =SUBSTITUTE(AB18,".","") -> 5 | AD18: =SUBSTITUTE(AC18,"+","") -> 5 | AE18: =SUBSTITUTE(AD18,"Y","") -> 5 | AF18: =SUBSTITUTE(AE18,"e","") -> 5 | AG18: =SUBSTITUTE(AF18,",","")*1 -> 5
A19: 18 | B19: Dell FG | C19: 44554 | D19: 34147670 | E19: Rahul Kapoor | F19: U82721 | G19: UST Global | H19: Mindsoft | I19: C#.NET,.NET Core, Web API, MVC,Angular,Jquery role . | J19: C#.NET | K19: Joined | L19: Rejected | M19: Regular | N19: H6549840 | O19: Swagat Das Pattanaik | P19: 9090016506 | Q19: sdpswagat@gmail.com | R19: 8 years | S19: Infosys | T19: 1600000 | U19: 30 Days (in provision period till dec end) | V19: N | W19: Bhubaneswar | X19: Bangalore | Y19: =MONTH($C19) -> 12 | Z19: =YEAR($C19) -> 2021 | AA19: =LEFT(R19,2) -> 8 | AB19: =SUBSTITUTE(AA19,"y","") -> 8 | AC19: =SUBSTITUTE(AB19,".","") -> 8 | AD19: =SUBSTITUTE(AC19,"+","") -> 8 | AE19: =SUBSTITUTE(AD19,"Y","") -> 8 | AF19: =SUBSTITUTE(AE19,"e","") -> 8 | AG19: =SUBSTITUTE(AF19,",","")*1 -> 8
A20: 19 | B20: Dell FG | C20: 44554 | D20: 92843512 | E20: Rahul Kapoor | F20: U82721 | G20: UST Global | H20: Mindsoft | I20: C#.NET,.NET Core, Web API, MVC,Angular,Jquery | J20: C#.NET | K20: Dropped | L20: Drop out | M20: Regular | N20: 402046 | O20: Rajat Patel | P20: 8970264977 | Q20: rpatel062021@gmail.com | R20: 7.3yrs | S20: Wipro Limited | T20: 1300000 | U20: 30 days(LWD:27th Jan) | V20: N | W20: Bangalore | X20: Bangalore | Y20: =MONTH($C20) -> 12 | Z20: =YEAR($C20) -> 2021 | AA20: =LEFT(R20,2) -> 7. | AB20: =SUBSTITUTE(AA20,"y","") -> 7. | AC20: =SUBSTITUTE(AB20,".","") -> 7 | AD20: =SUBSTITUTE(AC20,"+","") -> 7 | AE20: =SUBSTITUTE(AD20,"Y","") -> 7 | AF20: =SUBSTITUTE(AE20,"e","") -> 7 | AG20: =SUBSTITUTE(AF20,",","")*1 -> 7
A21: 20 | B21: Dell FG | C21: 44554 | D21: 68506880 | E21: Rahul Kapoor | F21: U82721 | G21: UST Global | H21: Mindsoft | I21: C#.NET,.NET Core, Web API, MVC,Angular,Jquery | J21: C#.NET | K21: Dropped | L21: High ctc rejected | M21: Regular | N21: 401907 | O21: Pramod K | P21: 9538686070 | Q21: Pramodk41@gmail.com | R21: 11yrs | S21: Wells Fargo EGS India Pvt. Ltd | T21: 1600000 | U21: 20 days(LWD:14th Jan) | V21: Y | W21: Bangalore | X21: Bangalore | Y21: =MONTH($C21) -> 12 | Z21: =YEAR($C21) -> 2021 | AA21: =LEFT(R21,2) -> 11 | AB21: =SUBSTITUTE(AA21,"y","") -> 11 | AC21: =SUBSTITUTE(AB21,".","") -> 11 | AD21: =SUBSTITUTE(AC21,"+","") -> 11 | AE21: =SUBSTITUTE(AD21,"Y","") -> 11 | AF21: =SUBSTITUTE(AE21,"e","") -> 11 | AG21: =SUBSTITUTE(AF21,",","")*1 -> 11
A22: 21 | B22: Dell FG | C22: 44554 | D22: 68506880 | E22: Rahul Kapoor | F22: U82721 | G22: UST Global | H22: Mindsoft | I22: C#.NET,.NET Core, Web API, MVC,Angular,Jquery | J22: C#.NET | K22: Dropped | L22: Duplicate | M22: Regular | N22: 402000 | O22: Ramachandra Reddy E | P22: 9739527778 | Q22: ercreddy4@gmail.com | R22: 14.5yrs | S22: Not working | T22: 1900000 | U22: Immediate | V22: N | W22: Bangalore | X22: Bangalore | Y22: =MONTH($C22) -> 12 | Z22: =YEAR($C22) -> 2021 | AA22: =LEFT(R22,2) -> 14 | AB22: =SUBSTITUTE(AA22,"y","") -> 14 | AC22: =SUBSTITUTE(AB22,".","") -> 14 | AD22: =SUBSTITUTE(AC22,"+","") -> 14 | AE22: =SUBSTITUTE(AD22,"Y","") -> 14 | AF22: =SUBSTITUTE(AE22,"e","") -> 14 | AG22: =SUBSTITUTE(AF22,",","")*1 -> 14
A23: 22 | B23: Dell FG | C23: 44554 | D23: 98936697 | E23: Vinay Nambiar | F23: 181547 | G23: Vendor Partner | H23: SRS | I23: Java | J23: Java/J2EE,Full Stack Developer,Spring Boot,Angular,Cloud Technologies | K23: Screen Reject | L23: Not responding | M23: Regular | N23: H8110634 | O23: Jinka Mohan | P23: 9963120609 | Q23: jinkamohan@yahoo.com | R23: 15 YR | S23: Hyderabad | T23: 1500000 | U23: IMMEDAITE JOINNER | V23: N | W23: Hyderabad | X23: Hyderabad | Y23: =MONTH($C23) -> 12 | Z23: =YEAR($C23) -> 2021 | AA23: =LEFT(R23,2) -> 15 | AB23: =SUBSTITUTE(AA23,"y","") -> 15 | AC23: =SUBSTITUTE(AB23,".","") -> 15 | AD23: =SUBSTITUTE(AC23,"+","") -> 15 | AE23: =SUBSTITUTE(AD23,"Y","") -> 15 | AF23: =SUBSTITUTE(AE23,"e","") -> 15 | AG23: =SUBSTITUTE(AF23,",","")*1 -> 15
A24: 23 | B24: Dell FG | C24: 44554 | D24: 77765032 | E24: Vinay Nambiar | F24: 181547 | G24: Vendor Partner | H24: SRS | I24: Java | J24: Java/J2EE,Spring,PostgreSQL,ReactJS,PCF,Cloud Microservices,TFS,GitLab,Dev Ops CICD | K24: Screen Reject | L24: Not responding | M24: Regular | N24: 422946 | O24: C. Phani Kishore | P24: 9502329926 | Q24: phanikishorechavvakula@gmail.com | R24: 4.10 years | S24: Zenith Technology Services | T24: 1000000 | U24: LWD: 17/01/2022 | V24: N | W24: Hyderabad | X24: Hyderabad | Y24: =MONTH($C24) -> 12 | Z24: =YEAR($C24) -> 2021 | AA24: =LEFT(R24,2) -> 4. | AB24: =SUBSTITUTE(AA24,"y","") -> 4. | AC24: =SUBSTITUTE(AB24,".","") -> 4 | AD24: =SUBSTITUTE(AC24,"+","") -> 4 | AE24: =SUBSTITUTE(AD24,"Y","") -> 4 | AF24: =SUBSTITUTE(AE24,"e","") -> 4 | AG24: =SUBSTITUTE(AF24,",","")*1 -> 4
A25: 24 | B25: Dell FG | C25: 44554 | D25: 58270892 | E25: Rahul Kapoor | F25: U82721 | G25: Vendor Partner | H25: Nityo InfoTech | I25: PLSQL Developer, Informatica and Control – M | J25: PLSQL Developer | K25: Dropped | L25: Back up candidates | M25: Regular | N25: 431922 | O25: Tanguturi Jayapal | P25: 8217012668/7899098018 | Q25: jayapalinfo232@gmail.com | R25: 3.8 Years | S25: Tata Consultancy Services Ltd. | T25: 520000 | U25: LWD:30/12/21 | V25: N | W25: Bangalore | X25: Bangalore | Y25: =MONTH($C25) -> 12 | Z25: =YEAR($C25) -> 2021 | AA25: =LEFT(R25,2) -> 3. | AB25: =SUBSTITUTE(AA25,"y","") -> 3. | AC25: =SUBSTITUTE(AB25,".","") -> 3 | AD25: =SUBSTITUTE(AC25,"+","") -> 3 | AE25: =SUBSTITUTE(AD25,"Y","") -> 3 | AF25: =SUBSTITUTE(AE25,"e","") -> 3 | AG25: =SUBSTITUTE(AF25,",","")*1 -> 3
A26: 25 | B26: Dell FG | C26: 44557 | D26: 58270892 | E26: Rahul Kapoor | F26: U82721 | G26: Vendor Partner | H26: Nityo InfoTech | I26: PLSQL Developer, Informatica and Control – M | J26: PLSQL Developer | K26: Dropped | L26: Back up candidates | M26: Regular | N26: 430273 | O26: Ashok Kumar Nahak | P26: 7550154965 | Q26: ashoktech1008@gmail.com | R26: 3.5 Years | S26: PLEXUS SOFTWARE SECURITY SYSTEMS PRIVATE LIMITED | T26: 850000 | U26: Immediate | V26: N | W26: Chennai | X26: Bangalore | Y26: =MONTH($C26) -> 12 | Z26: =YEAR($C26) -> 2021 | AA26: =LEFT(R26,2) -> 3. | AB26: =SUBSTITUTE(AA26,"y","") -> 3. | AC26: =SUBSTITUTE(AB26,".","") -> 3 | AD26: =SUBSTITUTE(AC26,"+","") -> 3 | AE26: =SUBSTITUTE(AD26,"Y","") -> 3 | AF26: =SUBSTITUTE(AE26,"e","") -> 3 | AG26: =SUBSTITUTE(AF26,",","")*1 -> 3
A27: 26 | B27: Dell FG | C27: 44557 | D27: 58270892 | E27: Rahul Kapoor | F27: U82721 | G27: Vendor Partner | H27: Nityo InfoTech | I27: PLSQL Develop, Informatica and Control – M | J27: PLSQL Developer | K27: Dropped | L27: Back up candidates | M27: Regular | N27: 430286 | O27: M Murali krishna | P27: 8217455947/7008255417 | Q27: medmuralikrishna@gmail.com | R27: 3.6 Years | S27: Cognizant Technologies | T27: 850000 | U27: 30days(15days) | V27: N | W27: Bangalore | X27: Bangalore | Y27: =MONTH($C27) -> 12 | Z27: =YEAR($C27) -> 2021 | AA27: =LEFT(R27,2) -> 3. | AB27: =SUBSTITUTE(AA27,"y","") -> 3. | AC27: =SUBSTITUTE(AB27,".","") -> 3 | AD27: =SUBSTITUTE(AC27,"+","") -> 3 | AE27: =SUBSTITUTE(AD27,"Y","") -> 3 | AF27: =SUBSTITUTE(AE27,"e","") -> 3 | AG27: =SUBSTITUTE(AF27,",","")*1 -> 3
A28: 27 | B28: Dell FG | C28: 44557 | D28: 58270892 | E28: Rahul Kapoor | F28: U82721 | G28: Vendor Partner | H28: Nityo InfoTech | I28: PLSQL Develop, Informatica and Control – M | J28: PLSQL Developer | K28: Dropped | L28: Back up candidates | M28: Regular | N28: 430617 | O28: Eswar Sai S | P28: 7675099160 | Q28: eswarsai.etldb@gmail.com | R28: 3.5 Years | S28: Deltra Soft Technologies Pvt Ltd | T28: 360000 | U28: 30days(15days) | V28: N | W28: Hyderabad | X28: Bangalore | Y28: =MONTH($C28) -> 12 | Z28: =YEAR($C28) -> 2021 | AA28: =LEFT(R28,2) -> 3. | AB28: =SUBSTITUTE(AA28,"y","") -> 3. | AC28: =SUBSTITUTE(AB28,".","") -> 3 | AD28: =SUBSTITUTE(AC28,"+","") -> 3 | AE28: =SUBSTITUTE(AD28,"Y","") -> 3 | AF28: =SUBSTITUTE(AE28,"e","") -> 3 | AG28: =SUBSTITUTE(AF28,",","")*1 -> 3
A29: 28 | B29: Dell FG | C29: 44557 | D29: 34147670 | E29: Rahul Kapoor | F29: U82721 | G29: UST Global | H29: Mindsoft | I29: C#.NET,.NET Core, Web API, MVC,Angular,Jquery role | J29: C#.NET | K29: Dropped | L29: Drop out | M29: Regular | N29: L376418 | O29: Manikandan K | P29: 7829098574 | Q29: maniksfwr@gmail.com | R29: 7.2 yrs | S29: Not working | T29: 950000 | U29: Immediate | V29: N | W29: Bangalore | X29: Bangalore | Y29: =MONTH($C29) -> 12 | Z29: =YEAR($C29) -> 2021 | AA29: =LEFT(R29,2) -> 7. | AB29: =SUBSTITUTE(AA29,"y","") -> 7. | AC29: =SUBSTITUTE(AB29,".","") -> 7 | AD29: =SUBSTITUTE(AC29,"+","") -> 7 | AE29: =SUBSTITUTE(AD29,"Y","") -> 7 | AF29: =SUBSTITUTE(AE29,"e","") -> 7 | AG29: =SUBSTITUTE(AF29,",","")*1 -> 7
A30: 29 | B30: Dell FG | C30: 44557 | D30: 58270892 | E30: Rahul Kapoor | F30: U82721 | G30: Vendor Partner | H30: Nityo InfoTech | I30: PLSQL Develop, Informatica and Control – M | J30: PLSQL Developer | K30: Dropped | L30: Back up candidates | M30: Regular | N30: 431752 | O30: Naga Malleswara Rao Mannem | P30: 7659935955 | Q30: nagamallesh519@gmail.com | R30: 4.6 Years | S30: Tata Consultancy Services Ltd. | T30: 600000 | U30: 30days(15days) | V30: N | W30: Bangalore | X30: Bangalore | Y30: =MONTH($C30) -> 12 | Z30: =YEAR($C30) -> 2021 | AA30: =LEFT(R30,2) -> 4. | AB30: =SUBSTITUTE(AA30,"y","") -> 4. | AC30: =SUBSTITUTE(AB30,".","") -> 4 | AD30: =SUBSTITUTE(AC30,"+","") -> 4 | AE30: =SUBSTITUTE(AD30,"Y","") -> 4 | AF30: =SUBSTITUTE(AE30,"e","") -> 4 | AG30: =SUBSTITUTE(AF30,",","")*1 -> 4
A31: 30 | B31: Dell FG | C31: 44558 | D31: 67489866 | E31: Vinay Nambiar | F31: 181547 | G31: Vendor Partner | H31: SRS | I31: DevOps | J31: 5-8y Devops with GIT,CICD (Gitlab),Powershell/Bash | K31: Dropped | L31: Requirement closed | M31: Regular | N31: H7890084 | O31: Prashanth Reddy | P31: 7816087160 | Q31: prashanth.anakapally@gmail.com | R31: 5years | S31: Future Nine Information Technologies Pvt. Ltd | T31: 700000 | U31: 25days | V31: N | W31: Hyderabad | X31: Hyderabad | Y31: =MONTH($C31) -> 12 | Z31: =YEAR($C31) -> 2021 | AA31: =LEFT(R31,2) -> 5y | AB31: =SUBSTITUTE(AA31,"y","") -> 5 | AC31: =SUBSTITUTE(AB31,".","") -> 5 | AD31: =SUBSTITUTE(AC31,"+","") -> 5 | AE31: =SUBSTITUTE(AD31,"Y","") -> 5 | AF31: =SUBSTITUTE(AE31,"e","") -> 5 | AG31: =SUBSTITUTE(AF31,",","")*1 -> 5
A32: 31 | B32: Dell FG | C32: 44558 | D32: 67489866 | E32: Vinay Nambiar | F32: 181547 | G32: Vendor Partner | H32: SRS | I32: DevOps | J32: 5-8y Devops with GIT,CICD (Gitlab),Powershell/Bash | K32: Dropped | L32: Requirement closed | M32: Regular | N32: 431002 | O32: Vamsi reddy Peddinti | P32: 9381863414 | Q32: vamsipeddinti28@gmail.com | R32: 5.5years | S32: Nivass IT Solutions Pvt Ltd | T32: 550000 | U32: 30days | V32: N | W32: Hyderabad | X32: Hyderabad | Y32: =MONTH($C32) -> 12 | Z32: =YEAR($C32) -> 2021 | AA32: =LEFT(R32,2) -> 5. | AB32: =SUBSTITUTE(AA32,"y","") -> 5. | AC32: =SUBSTITUTE(AB32,".","") -> 5 | AD32: =SUBSTITUTE(AC32,"+","") -> 5 | AE32: =SUBSTITUTE(AD32,"Y","") -> 5 | AF32: =SUBSTITUTE(AE32,"e","") -> 5 | AG32: =SUBSTITUTE(AF32,",","")*1 -> 5
A33: 32 | B33: Dell FG | C33: 44558 | D33: ​98936697 | E33: Vinay Nambiar | F33: 181547 | G33: Vendor Partner | H33: SRS | I33: Java | J33: Java/J2EE,Full Stack Developer,Spring Boot,Angular,Cloud Technologies | K33: Joined | L33: Joined because of high CTC | M33: Regular | N33: 351658 | O33: Yashwanth Vyamasani | P33: 9949073900 | Q33: yashwanth.vyam@gmail.com | R33: 13 yr | S33: IBM | T33: 1230000 | U33: ELWD : 21/01/22 | V33: N | W33: Hyderabad | X33: Hyderabad | Y33: =MONTH($C33) -> 12 | Z33: =YEAR($C33) -> 2021 | AA33: =LEFT(R33,2) -> 13 | AB33: =SUBSTITUTE(AA33,"y","") -> 13 | AC33: =SUBSTITUTE(AB33,".","") -> 13 | AD33: =SUBSTITUTE(AC33,"+","") -> 13 | AE33: =SUBSTITUTE(AD33,"Y","") -> 13 | AF33: =SUBSTITUTE(AE33,"e","") -> 13 | AG33: =SUBSTITUTE(AF33,",","")*1 -> 13
A34: 33 | B34: Dell FG | C34: 44558 | D34: ​98936697 | E34: Vinay Nambiar | F34: 181547 | G34: Vendor Partner | H34: SRS | I34: Java | J34: Java/J2EE,Full Stack Developer,Spring Boot,Angular,Cloud Technologies | K34: Feedback pending from client | L34: Processed yet to get feedback from client | M34: Regular | N34: 432232 | O34: Chiranjeevi Madasu | P34: 9848869290 | Q34: chiranjeevi.madasu@gmail.com | R34: 15 yr | S34: Infosys | T34: 1600000 | U34: Immediate joiner | V34: N | W34: Hyderabad | X34: Hyderabad | Y34: =MONTH($C34) -> 12 | Z34: =YEAR($C34) -> 2021 | AA34: =LEFT(R34,2) -> 15 | AB34: =SUBSTITUTE(AA34,"y","") -> 15 | AC34: =SUBSTITUTE(AB34,".","") -> 15 | AD34: =SUBSTITUTE(AC34,"+","") -> 15 | AE34: =SUBSTITUTE(AD34,"Y","") -> 15 | AF34: =SUBSTITUTE(AE34,"e","") -> 15 | AG34: =SUBSTITUTE(AF34,",","")*1 -> 15
A35: 34 | B35: Dell FG | C35: 44558 | D35: 95801483 | E35: Vinay Nambiar | F35: 181547 | G35: Vendor Partner | H35: SRS | I35: Java | J35: JAVA/J2EE SPRING, ANGULAR | K35: Joined | L35: Not responding | M35: Regular | N35: H7777151 | O35: M Anil Kumar | P35: 9538824541 | Q35: anelkumar.m159@gmail.com | R35: 6 yr | S35: Tech Mahindra | T35: 750000 | U35: ELWD : 29/01/22 | V35: N | W35: Bangalore | X35: Bangalore | Y35: =MONTH($C35) -> 12 | Z35: =YEAR($C35) -> 2021 | AA35: =LEFT(R35,2) -> 6 | AB35: =SUBSTITUTE(AA35,"y","") -> 6 | AC35: =SUBSTITUTE(AB35,".","") -> 6 | AD35: =SUBSTITUTE(AC35,"+","") -> 6 | AE35: =SUBSTITUTE(AD35,"Y","") -> 6 | AF35: =SUBSTITUTE(AE35,"e","") -> 6 | AG35: =SUBSTITUTE(AF35,",","")*1 -> 6
A36: 35 | B36: Dell FG | C36: 44558 | D36: 95801483 | E36: Vinay Nambiar | F36: 181547 | G36: Vendor Partner | H36: SRS | I36: Java | J36: JAVA/J2EE SPRING ANGULAR | K36: Joined | L36: Not responding | M36: Regular | N36: 328950 | O36: Ravikanth Sharma | P36: 8639575493 | Q36: vrksharma1981@gmail.com | R36: 8yr | S36: DXC Technology | T36: 1000000 | U36: ELWD : 21/01/22 | V36: N | W36: Bangalore | X36: Bangalore | Y36: =MONTH($C36) -> 12 | Z36: =YEAR($C36) -> 2021 | AA36: =LEFT(R36,2) -> 8y | AB36: =SUBSTITUTE(AA36,"y","") -> 8 | AC36: =SUBSTITUTE(AB36,".","") -> 8 | AD36: =SUBSTITUTE(AC36,"+","") -> 8 | AE36: =SUBSTITUTE(AD36,"Y","") -> 8 | AF36: =SUBSTITUTE(AE36,"e","") -> 8 | AG36: =SUBSTITUTE(AF36,",","")*1 -> 8
A37: 36 | B37: Dell FG | C37: 44558 | D37: 95801483 | E37: Vinay Nambiar | F37: 181547 | G37: Vendor Partner | H37: SRS | I37: Java | J37: JAVA/J2EE SPRING ANGULAR | K37: Joined | L37: Not responding | M37: Regular | N37: L757477 | O37: Tarun Barik | P37: 7828724103 | Q37: tarunbarik.csit@gmail.com | R37: 6 yr | S37: Slk Software Services | T37: 790000 | U37: ELWD : 25/01/22 | V37: N | W37: Bangalore | X37: Bangalore | Y37: =MONTH($C37) -> 12 | Z37: =YEAR($C37) -> 2021 | AA37: =LEFT(R37,2) -> 6 | AB37: =SUBSTITUTE(AA37,"y","") -> 6 | AC37: =SUBSTITUTE(AB37,".","") -> 6 | AD37: =SUBSTITUTE(AC37,"+","") -> 6 | AE37: =SUBSTITUTE(AD37,"Y","") -> 6 | AF37: =SUBSTITUTE(AE37,"e","") -> 6 | AG37: =SUBSTITUTE(AF37,",","")*1 -> 6
A38: 37 | B38: Dell FG | C38: 44558 | D38: 95801483 | E38: Vinay Nambiar | F38: 181547 | G38: Vendor Partner | H38: SRS | I38: Java | J38: Java/J2EE, Angularjs,Spring Boot | K38: Joined | L38: Not responding | M38: Regular | N38: 432194 | O38: Selva Kumar G | P38: 9500552392 | Q38: selva.kak@gmail.com | R38: 5.5 Years | S38: Smartpoint Technologies | T38: 890000 | U38: LWD 04-02-2022 | V38: N | W38: Chennai | X38: Bangalore | Y38: =MONTH($C38) -> 12 | Z38: =YEAR($C38) -> 2021 | AA38: =LEFT(R38,2) -> 5. | AB38: =SUBSTITUTE(AA38,"y","") -> 5. | AC38: =SUBSTITUTE(AB38,".","") -> 5 | AD38: =SUBSTITUTE(AC38,"+","") -> 5 | AE38: =SUBSTITUTE(AD38,"Y","") -> 5 | AF38: =SUBSTITUTE(AE38,"e","") -> 5 | AG38: =SUBSTITUTE(AF38,",","")*1 -> 5
A39: 38 | B39: Dell FG | C39: 44558 | D39: 98927307 | E39: Vinay Nambiar | F39: 181547 | G39: Vendor Partner | H39: SRS | I39: Java | J39: 3-6y Java/J2EE,Springboot,Cloud Native Concepts,RESTful,web services,Microservice Architecture,Spring Framework | K39: Joined | L39: No show | M39: Regular | N39: 433908 | O39: Manoj kumar | P39: 8143524153 | Q39: manojkumar.yerukondu@gmail.com | R39: 3.2 years | S39: Infosys | T39: 660000 | U39: LWD: 31/12/2021 | V39: N | W39: Hyderabad | X39: Bangalore | Y39: =MONTH($C39) -> 12 | Z39: =YEAR($C39) -> 2021 | AA39: =LEFT(R39,2) -> 3. | AB39: =SUBSTITUTE(AA39,"y","") -> 3. | AC39: =SUBSTITUTE(AB39,".","") -> 3 | AD39: =SUBSTITUTE(AC39,"+","") -> 3 | AE39: =SUBSTITUTE(AD39,"Y","") -> 3 | AF39: =SUBSTITUTE(AE39,"e","") -> 3 | AG39: =SUBSTITUTE(AF39,",","")*1 -> 3
A40: 39 | B40: Dell FG | C40: 44558 | D40: 98927307 | E40: Vinay Nambiar | F40: 181547 | G40: Vendor Partner | H40: SRS | I40: Java | J40: 3-6y Java/J2EE,Springboot,Cloud Native Concepts,RESTful,web services,Microservice Architecture,Spring Framework | K40: Dropped | L40: Candidate has other offer not processed | M40: Regular | N40: 433941 | O40: G. Ganesh | P40: 7893030070 | Q40: gampalaganesh05@gmail.com | R40: 2.4 years | S40: Sun Icon systems Pvt. Ltd | T40: 480000 | U40: 30 days | V40: N | W40: Hyderabad | X40: Hyderabad | Y40: =MONTH($C40) -> 12 | Z40: =YEAR($C40) -> 2021 | AA40: =LEFT(R40,2) -> 2. | AB40: =SUBSTITUTE(AA40,"y","") -> 2. | AC40: =SUBSTITUTE(AB40,".","") -> 2 | AD40: =SUBSTITUTE(AC40,"+","") -> 2 | AE40: =SUBSTITUTE(AD40,"Y","") -> 2 | AF40: =SUBSTITUTE(AE40,"e","") -> 2 | AG40: =SUBSTITUTE(AF40,",","")*1 -> 2
A41: 40 | B41: Dell FG | C41: 44558 | D41: 31972088 | E41: Vinay Nambiar | F41: 181547 | G41: Vendor Partner | H41: Mindsoft | I41: Java | J41: Java/J2EE,Spring Boot,Spring Core,Spring MVC, Spring Web Services, Spring boot, Spring Data, Spring Cloud,HTML/CSS/JS | K41: Joined | L41: Other offer | M41: Regular | N41: 430788 | O41: K.V.S Chandra Sekhar | P41: 9347977897 | Q41: chandu.process@gmail.com | R41: 14.5 years | S41: Not working( Last worked with Ivy Comptech till August '21 | T41: 2300000 | U41: Immediate | V41: N | W41: Hyderabad | X41: Hyderabad | Y41: =MONTH($C41) -> 12 | Z41: =YEAR($C41) -> 2021 | AA41: =LEFT(R41,2) -> 14 | AB41: =SUBSTITUTE(AA41,"y","") -> 14 | AC41: =SUBSTITUTE(AB41,".","") -> 14 | AD41: =SUBSTITUTE(AC41,"+","") -> 14 | AE41: =SUBSTITUTE(AD41,"Y","") -> 14 | AF41: =SUBSTITUTE(AE41,"e","") -> 14 | AG41: =SUBSTITUTE(AF41,",","")*1 -> 14
A42: 41 | B42: Dell FG | C42: 44558 | D42: 31972088 | E42: Vinay Nambiar | F42: 181547 | G42: Vendor Partner | H42: Mindsoft | I42: Java | J42: Java/J2EE,Spring Boot,Spring Core,Spring MVC, Spring Web Services, Spring boot, Spring Data, Spring Cloud,HTML/CSS/JS | K42: Dropped | L42: Candidate not responding the calls | M42: Regular | N42: 436834 | O42: Sreelekha Jakka | P42: 9000950687 | Q42: jsreelekhareddy@gmail.com | R42: 12 years | S42: Not working( Last worked with Vsoft Technologies till December '21 ) | T42: 1100000 | U42: Immediate | V42: N | W42: Hyderabad | X42: Hyderabad | Y42: =MONTH($C42) -> 12 | Z42: =YEAR($C42) -> 2021 | AA42: =LEFT(R42,2) -> 12 | AB42: =SUBSTITUTE(AA42,"y","") -> 12 | AC42: =SUBSTITUTE(AB42,".","") -> 12 | AD42: =SUBSTITUTE(AC42,"+","") -> 12 | AE42: =SUBSTITUTE(AD42,"Y","") -> 12 | AF42: =SUBSTITUTE(AE42,"e","") -> 12 | AG42: =SUBSTITUTE(AF42,",","")*1 -> 12
A43: 42 | B43: Dell FG | C43: 44558 | D43: 36862234 | E43: Rahul Kapoor | F43: U82721 | G43: Vendor Partner | H43: Nityo InfoTech | I43: Mobility | J43: 4G/5G RAN L2 | K43: Client Reject | L43: Back up candidates | M43: Regular | N43: 429695 | O43: AMITKUMAR P SHIROL | P43: 9535291492 | Q43: amitshirolbgm@gmail.com | R43: 6.5YRS | S43: coforge | T43: 1000000 | U43: Immediate-LWD/30TH NOV | V43: N | W43: Bangalore | X43: Bangalore | Y43: =MONTH($C43) -> 12 | Z43: =YEAR($C43) -> 2021 | AA43: =LEFT(R43,2) -> 6. | AB43: =SUBSTITUTE(AA43,"y","") -> 6. | AC43: =SUBSTITUTE(AB43,".","") -> 6 | AD43: =SUBSTITUTE(AC43,"+","") -> 6 | AE43: =SUBSTITUTE(AD43,"Y","") -> 6 | AF43: =SUBSTITUTE(AE43,"e","") -> 6 | AG43: =SUBSTITUTE(AF43,",","")*1 -> 6
A44: 43 | B44: Dell FG | C44: 44558 | D44: 73030060 | E44: Rahul Kapoor | F44: U82721 | G44: Vendor Partner | H44: Nityo InfoTech | I44: Mobility | J44: 4G/5G RAN L2 | K44: Client Reject | L44: Back up candidates | M44: Regular | N44: 429683 | O44: Prathap kumar | P44: 9618484841 | Q44: prathapambothula@outlook.com | R44: 8yrs | S44: Radisys | T44: 2100000 | U44: Immediate-LWD/31ST DEC | V44: N | W44: Hyderabad | X44: Bangalore | Y44: =MONTH($C44) -> 12 | Z44: =YEAR($C44) -> 2021 | AA44: =LEFT(R44,2) -> 8y | AB44: =SUBSTITUTE(AA44,"y","") -> 8 | AC44: =SUBSTITUTE(AB44,".","") -> 8 | AD44: =SUBSTITUTE(AC44,"+","") -> 8 | AE44: =SUBSTITUTE(AD44,"Y","") -> 8 | AF44: =SUBSTITUTE(AE44,"e","") -> 8 | AG44: =SUBSTITUTE(AF44,",","")*1 -> 8
A45: 44 | B45: Dell FG | C45: 44558 | D45: 75600044 | E45: Rahul Kapoor | F45: U82721 | G45: Vendor Partner | H45: Nityo InfoTech | I45: Mobility | J45: 4G/5G RAN L2 | K45: Client Reject | L45: Back up candidates | M45: Regular | N45: 431908 | O45: Vikrant Namdev | P45: 8817724704 | Q45: vikrant.namdev@gmail.com | R45: 10yrs | S45: ultimateinfo soft | T45: 980000 | U45: 30days(nego 15days) | V45: N | W45: Indore | X45: Bangalore | Y45: =MONTH($C45) -> 12 | Z45: =YEAR($C45) -> 2021 | AA45: =LEFT(R45,2) -> 10 | AB45: =SUBSTITUTE(AA45,"y","") -> 10 | AC45: =SUBSTITUTE(AB45,".","") -> 10 | AD45: =SUBSTITUTE(AC45,"+","") -> 10 | AE45: =SUBSTITUTE(AD45,"Y","") -> 10 | AF45: =SUBSTITUTE(AE45,"e","") -> 10 | AG45: =SUBSTITUTE(AF45,",","")*1 -> 10
A46: 45 | B46: Dell FG | C46: 44558 | D46: 50201569 | E46: Rahul Kapoor | F46: U82721 | G46: Vendor Partner | H46: Nityo InfoTech | I46: Mobility | J46: 4G/5G RAN L2 | K46: Client Reject | L46: Back up candidates | M46: Regular | N46: 429246 | O46: Pinki Singh | P46: 7987723612 | Q46: singhpinkirajput@gmail.com | R46: 6yrs | S46: Mastec Quadgen Wireless | T46: 813000 | U46: Lwd Jan 17th | V46: N | W46: Bangalore | X46: Bangalore | Y46: =MONTH($C46) -> 12 | Z46: =YEAR($C46) -> 2021 | AA46: =LEFT(R46,2) -> 6y | AB46: =SUBSTITUTE(AA46,"y","") -> 6 | AC46: =SUBSTITUTE(AB46,".","") -> 6 | AD46: =SUBSTITUTE(AC46,"+","") -> 6 | AE46: =SUBSTITUTE(AD46,"Y","") -> 6 | AF46: =SUBSTITUTE(AE46,"e","") -> 6 | AG46: =SUBSTITUTE(AF46,",","")*1 -> 6
A47: 46 | B47: Dell FG | C47: 44558 | D47: 50201569 | E47: Rahul Kapoor | F47: U82721 | G47: Vendor Partner | H47: Nityo InfoTech | I47: Mobility | J47: 4G/5G RAN L2 | K47: Client Reject | L47: Back up candidates | M47: Regular | N47: 429324 | O47: Erfan Muhammed | P47: 9539025426 | Q47: mohderfan0991@gmail.com | R47: 6yrs | S47: Ericsson Global | T47: 700000 | U47: 30 days official(Neg) | V47: N | W47: Bangalore | X47: Bangalore | Y47: =MONTH($C47) -> 12 | Z47: =YEAR($C47) -> 2021 | AA47: =LEFT(R47,2) -> 6y | AB47: =SUBSTITUTE(AA47,"y","") -> 6 | AC47: =SUBSTITUTE(AB47,".","") -> 6 | AD47: =SUBSTITUTE(AC47,"+","") -> 6 | AE47: =SUBSTITUTE(AD47,"Y","") -> 6 | AF47: =SUBSTITUTE(AE47,"e","") -> 6 | AG47: =SUBSTITUTE(AF47,",","")*1 -> 6
A48: 47 | B48: Dell FG | C48: 44558 | D48: 73030060 | E48: Rahul Kapoor | F48: U82721 | G48: Vendor Partner | H48: Nityo InfoTech | I48: Mobility | J48: 4G/5G RAN L2 | K48: Client Reject | L48: Back up candidates | M48: Regular | N48: 428259 | O48: Md Zafar | P48: 7717761848 | Q48: mdzafar008@gmail.com | R48: 7.6yrs | S48: Telemania Services | T48: 560000 | U48: 30 days official(Neg) | V48: N | W48: Hyderabad | X48: Bangalore | Y48: =MONTH($C48) -> 12 | Z48: =YEAR($C48) -> 2021 | AA48: =LEFT(R48,2) -> 7. | AB48: =SUBSTITUTE(AA48,"y","") -> 7. | AC48: =SUBSTITUTE(AB48,".","") -> 7 | AD48: =SUBSTITUTE(AC48,"+","") -> 7 | AE48: =SUBSTITUTE(AD48,"Y","") -> 7 | AF48: =SUBSTITUTE(AE48,"e","") -> 7 | AG48: =SUBSTITUTE(AF48,",","")*1 -> 7
A49: 48 | B49: Dell FG | C49: 44559 | D49: 44879198 | E49: Rahul Kapoor | F49: U82721 | G49: Vendor Partner | H49: Nityo InfoTech | I49: .NET,SQL,WEB API | J49: DOTNET | K49: Declined | L49: Back up candidates | M49: Regular | N49: 436862 | O49: AMIT JANGIR | P49: 8058860500/8078679705 | Q49: amit5010jangir@gmail.com | R49: 2.5 Years | S49: Anuin Techlogix | T49: 315000 | U49: LWD:20/01/22 | V49: N | W49: Pune | X49: Bangalore | Y49: =MONTH($C49) -> 12 | Z49: =YEAR($C49) -> 2021 | AA49: =LEFT(R49,2) -> 2. | AB49: =SUBSTITUTE(AA49,"y","") -> 2. | AC49: =SUBSTITUTE(AB49,".","") -> 2 | AD49: =SUBSTITUTE(AC49,"+","") -> 2 | AE49: =SUBSTITUTE(AD49,"Y","") -> 2 | AF49: =SUBSTITUTE(AE49,"e","") -> 2 | AG49: =SUBSTITUTE(AF49,",","")*1 -> 2
A50: 49 | B50: Dell FG | C50: 44559 | D50: 44879198 | E50: Rahul Kapoor | F50: U82721 | G50: Vendor Partner | H50: Nityo InfoTech | I50: .NET,SQL,WEB API | J50: DOTNET | K50: Declined | L50: Back up candidates | M50: Regular | N50: 436855 | O50: Praveen kumar.R | P50: 7659022717/7411026147 | Q50: praveenreddi.in@gmail.com | R50: 2.2 Years | S50: Temenos | T50: 510000 | U50: LWD:2/01/22 | V50: N | W50: Bangalore | X50: Bangalore | Y50: =MONTH($C50) -> 12 | Z50: =YEAR($C50) -> 2021 | AA50: =LEFT(R50,2) -> 2. | AB50: =SUBSTITUTE(AA50,"y","") -> 2. | AC50: =SUBSTITUTE(AB50,".","") -> 2 | AD50: =SUBSTITUTE(AC50,"+","") -> 2 | AE50: =SUBSTITUTE(AD50,"Y","") -> 2 | AF50: =SUBSTITUTE(AE50,"e","") -> 2 | AG50: =SUBSTITUTE(AF50,",","")*1 -> 2
A51: 50 | B51: Dell FG | C51: 44559 | D51: 44879198 | E51: Rahul Kapoor | F51: U82721 | G51: Vendor Partner | H51: Nityo InfoTech | I51: .NET,SQL,WEB API | J51: DOTNET | K51: Declined | L51: Back up candidates | M51: Regular | N51: 437985 | O51: SATISH UDA | P51: 9515500554/8639576943 | Q51: satishgoud313@gmail.com | R51: 2 Years | S51: Ecofil Technologies India Pvt Ltd | T51: 420000 | U51: Immediate | V51: N | W51: Chennai | X51: Bangalore | Y51: =MONTH($C51) -> 12 | Z51: =YEAR($C51) -> 2021 | AA51: =LEFT(R51,2) -> 2 | AB51: =SUBSTITUTE(AA51,"y","") -> 2 | AC51: =SUBSTITUTE(AB51,".","") -> 2 | AD51: =SUBSTITUTE(AC51,"+","") -> 2 | AE51: =SUBSTITUTE(AD51,"Y","") -> 2 | AF51: =SUBSTITUTE(AE51,"e","") -> 2 | AG51: =SUBSTITUTE(AF51,",","")*1 -> 2
A52: 51 | B52: Dell FG | C52: 44559 | D52: 44879198 | E52: Rahul Kapoor | F52: U82721 | G52: Vendor Partner | H52: Nityo InfoTech | I52: .NET,SQL,WEB API | J52: DOTNET | K52: Declined | L52: Back up candidates | M52: Regular | N52: 436649 | O52: Srinivas T | P52: 9398575490/9642633714 | Q52: tsrinivas714@gmail.com | R52: 2.7 Years | S52: Resilience Info Tech | T52: 350000 | U52: Immediate | V52: N | W52: Bangalore | X52: Bangalore | Y52: =MONTH($C52) -> 12 | Z52: =YEAR($C52) -> 2021 | AA52: =LEFT(R52,2) -> 2. | AB52: =SUBSTITUTE(AA52,"y","") -> 2. | AC52: =SUBSTITUTE(AB52,".","") -> 2 | AD52: =SUBSTITUTE(AC52,"+","") -> 2 | AE52: =SUBSTITUTE(AD52,"Y","") -> 2 | AF52: =SUBSTITUTE(AE52,"e","") -> 2 | AG52: =SUBSTITUTE(AF52,",","")*1 -> 2
A53: 52 | B53: Dell FG | C53: 44559 | D53: 73030060 | E53: Rahul Kapoor | F53: U82721 | G53: Vendor Partner | H53: Nityo InfoTech | I53: Mobility | J53: 4G/5G RAN L2 | K53: Client Reject | L53: Back up candidates | M53: Regular | N53: 436426 | O53: Sachin Kakkadath | P53: 9947099962 | Q53: snk.360@gmail.com | R53: 12yrs | S53: Vodafone Idea Ltd | T53: 710000 | U53: 30 days | V53: N | W53: Cochin | X53: Bangalore | Y53: =MONTH($C53) -> 12 | Z53: =YEAR($C53) -> 2021 | AA53: =LEFT(R53,2) -> 12 | AB53: =SUBSTITUTE(AA53,"y","") -> 12 | AC53: =SUBSTITUTE(AB53,".","") -> 12 | AD53: =SUBSTITUTE(AC53,"+","") -> 12 | AE53: =SUBSTITUTE(AD53,"Y","") -> 12 | AF53: =SUBSTITUTE(AE53,"e","") -> 12 | AG53: =SUBSTITUTE(AF53,",","")*1 -> 12
A54: 53 | B54: Dell FG | C54: 44559 | D54: 73030060 | E54: Rahul Kapoor | F54: U82721 | G54: Vendor Partner | H54: Nityo InfoTech | I54: Mobility | J54: 4G/5G RAN L2 | K54: Client Reject | L54: Back up candidates | M54: Regular | N54: 429479 | O54: Midhun P K | P54: 9446861022 | Q54: pk.midhun01@gmail.com | R54: 8yrs | S54: IKYA Human Capital | T54: 1200000 | U54: Immediate | V54: N | W54: Bangalore | X54: Bangalore | Y54: =MONTH($C54) -> 12 | Z54: =YEAR($C54) -> 2021 | AA54: =LEFT(R54,2) -> 8y | AB54: =SUBSTITUTE(AA54,"y","") -> 8 | AC54: =SUBSTITUTE(AB54,".","") -> 8 | AD54: =SUBSTITUTE(AC54,"+","") -> 8 | AE54: =SUBSTITUTE(AD54,"Y","") -> 8 | AF54: =SUBSTITUTE(AE54,"e","") -> 8 | AG54: =SUBSTITUTE(AF54,",","")*1 -> 8
A55: 54 | B55: Dell FG | C55: 44559 | D55: 73030060 | E55: Rahul Kapoor | F55: U82721 | G55: Vendor Partner | H55: Mindsoft | I55: Mobility | J55: Mobility | K55: Client Reject | L55: Waiting for client feedback | M55: Regular | N55: 431520 | O55: Ajit Singh | P55: 7462826329 | Q55: ajitsinghcsmt@gmail.com | R55: 10yrs | S55: Tata Communication | T55: 720000 | U55: Immediate | V55: N | W55: Bangalore | X55: Bangalore | Y55: =MONTH($C55) -> 12 | Z55: =YEAR($C55) -> 2021 | AA55: =LEFT(R55,2) -> 10 | AB55: =SUBSTITUTE(AA55,"y","") -> 10 | AC55: =SUBSTITUTE(AB55,".","") -> 10 | AD55: =SUBSTITUTE(AC55,"+","") -> 10 | AE55: =SUBSTITUTE(AD55,"Y","") -> 10 | AF55: =SUBSTITUTE(AE55,"e","") -> 10 | AG55: =SUBSTITUTE(AF55,",","")*1 -> 10
A56: 55 | B56: Dell FG | C56: 44559 | D56: 12527642 | E56: Vinay Nambiar | F56: 181547 | G56: Vendor Partner | H56: Growelsoftech pvt ltd | I56: Project Manager | J56: 5-8y Project Manager with Agile,SCRUM | K56: Joined | L56: Back up candidates | M56: Regular | N56: 2903254 | O56: Sunil S Shettigar | P56: 8105956342/7892257756 | Q56: sunil.shettigar615@gmail.com | R56: 6years | S56: IXAR Pvt ltd | T56: 600000 | U56: 15 days 30 days officially ( negotiablr) | V56: N | W56: MUMBAI | X56: Bangalore | Y56: =MONTH($C56) -> 12 | Z56: =YEAR($C56) -> 2021 | AA56: =LEFT(R56,2) -> 6y | AB56: =SUBSTITUTE(AA56,"y","") -> 6 | AC56: =SUBSTITUTE(AB56,".","") -> 6 | AD56: =SUBSTITUTE(AC56,"+","") -> 6 | AE56: =SUBSTITUTE(AD56,"Y","") -> 6 | AF56: =SUBSTITUTE(AE56,"e","") -> 6 | AG56: =SUBSTITUTE(AF56,",","")*1 -> 6
A57: 56 | B57: Dell FG | C57: 44559 | D57: 12527642 | E57: Vinay Nambiar | F57: 181547 | G57: Vendor Partner | H57: Growelsoftech pvt ltd | I57: Project Manager | J57: 5-8y Project Manager with Agile,SCRUM | K57: Joined | L57: Back up candidates | M57: Regular | N57: 297406 | O57: PRERNA RANI | P57: 9911941521 | Q57: prernarani18@gmail.com | R57: 7+YEARS | S57: Pragmatic Play India Pvt Ltd | T57: 550000 | U57: LWD-15 SEP ( IMMEDIATE JOINER) | V57: N | W57: Bangalore | X57: Bangalore | Y57: =MONTH($C57) -> 12 | Z57: =YEAR($C57) -> 2021 | AA57: =LEFT(R57,2) -> 7+ | AB57: =SUBSTITUTE(AA57,"y","") -> 7+ | AC57: =SUBSTITUTE(AB57,".","") -> 7+ | AD57: =SUBSTITUTE(AC57,"+","") -> 7 | AE57: =SUBSTITUTE(AD57,"Y","") -> 7 | AF57: =SUBSTITUTE(AE57,"e","") -> 7 | AG57: =SUBSTITUTE(AF57,",","")*1 -> 7
A58: 57 | B58: Dell FG | C58: 44559 | D58: 12527642 | E58: Vinay Nambiar | F58: 181547 | G58: Vendor Partner | H58: Growelsoftech pvt ltd | I58: Project Manager | J58: 5-8y Project Manager with Agile,SCRUM | K58: Joined | L58: Back up candidates | M58: Regular | N58: 429859 | O58: Jyoti Khetal | P58: 9871494074 | Q58: khetaljyoti@gmail.com | R58: 7years | S58: Brute Corp | T58: 750000 | U58: LWD-Dec-31 | V58: N | W58: Gaziabad | X58: Bangalore | Y58: =MONTH($C58) -> 12 | Z58: =YEAR($C58) -> 2021 | AA58: =LEFT(R58,2) -> 7y | AB58: =SUBSTITUTE(AA58,"y","") -> 7 | AC58: =SUBSTITUTE(AB58,".","") -> 7 | AD58: =SUBSTITUTE(AC58,"+","") -> 7 | AE58: =SUBSTITUTE(AD58,"Y","") -> 7 | AF58: =SUBSTITUTE(AE58,"e","") -> 7 | AG58: =SUBSTITUTE(AF58,",","")*1 -> 7
A59: 58 | B59: Dell FG | C59: 44559 | D59: 12527642 | E59: Vinay Nambiar | F59: 181547 | G59: Vendor Partner | H59: Growelsoftech pvt ltd | I59: Project Manager | J59: 5-8y Project Manager with Agile,SCRUM | K59: Joined | L59: Back up candidates | M59: Regular | N59: 431485 | O59: Sathiya K | P59: 6380481442 | Q59: sathiyakannadasann@gmail.com | R59: 5yrs | S59: Maximos Global Solutions | T59: 300000 | U59: lwd-30 Dec | V59: N | W59: Chennai | X59: Bangalore | Y59: =MONTH($C59) -> 12 | Z59: =YEAR($C59) -> 2021 | AA59: =LEFT(R59,2) -> 5y | AB59: =SUBSTITUTE(AA59,"y","") -> 5 | AC59: =SUBSTITUTE(AB59,".","") -> 5 | AD59: =SUBSTITUTE(AC59,"+","") -> 5 | AE59: =SUBSTITUTE(AD59,"Y","") -> 5 | AF59: =SUBSTITUTE(AE59,"e","") -> 5 | AG59: =SUBSTITUTE(AF59,",","")*1 -> 5
A60: 59 | B60: Dell FG | C60: 44559 | D60: 12527642 | E60: Vinay Nambiar | F60: 181547 | G60: Vendor Partner | H60: Growelsoftech pvt ltd | I60: Project Manager | J60: 5-8y Project Manager with Agile,SCRUM | K60: Joined | L60: Back up candidates | M60: Regular | N60: 430746 | O60: Madhukar Ch | P60: 9949387693 | Q60: madhukarch90@gmail.com | R60: 5years | S60: Optum - UHG | T60: 850000 | U60: immediate | V60: N | W60: Hyderabad | X60: Bangalore | Y60: =MONTH($C60) -> 12 | Z60: =YEAR($C60) -> 2021 | AA60: =LEFT(R60,2) -> 5y | AB60: =SUBSTITUTE(AA60,"y","") -> 5 | AC60: =SUBSTITUTE(AB60,".","") -> 5 | AD60: =SUBSTITUTE(AC60,"+","") -> 5 | AE60: =SUBSTITUTE(AD60,"Y","") -> 5 | AF60: =SUBSTITUTE(AE60,"e","") -> 5 | AG60: =SUBSTITUTE(AF60,",","")*1 -> 5
A61: 60 | B61: Dell FG | C61: 44559 | D61: 12527642 | E61: Vinay Nambiar | F61: 181547 | G61: Vendor Partner | H61: Growelsoftech pvt ltd | I61: Project Manager | J61: 5-8y Project Manager with Agile,SCRUM | K61: Joined | L61: Back up candidates | M61: Regular | N61: 430767 | O61: Muna Hannan | P61: 9449150744 | Q61: munahannan@gmail.com | R61: 8.5 Years | S61: Shreeon Computers Pvt Ltd | T61: 900000 | U61: Immediate joiner LWD:24.12.2021 | V61: N | W61: Bangalore | X61: Bangalore | Y61: =MONTH($C61) -> 12 | Z61: =YEAR($C61) -> 2021 | AA61: =LEFT(R61,2) -> 8. | AB61: =SUBSTITUTE(AA61,"y","") -> 8. | AC61: =SUBSTITUTE(AB61,".","") -> 8 | AD61: =SUBSTITUTE(AC61,"+","") -> 8 | AE61: =SUBSTITUTE(AD61,"Y","") -> 8 | AF61: =SUBSTITUTE(AE61,"e","") -> 8 | AG61: =SUBSTITUTE(AF61,",","")*1 -> 8
A62: 61 | B62: Dell FG | C62: 44559 | D62: 14885881 | E62: Vinay Nambiar | F62: 181547 | G62: Vendor Partner | H62: Growelsoftech pvt ltd | I62: UI/UX | J62: 5-8 yrs UX/UI Developer with HTML5,CSS3,Bootstrap,Javascript,Typescript | K62: Joined | L62: No Angular 6 exp | M62: Regular | N62: 430071 | O62: Shashi Prakash Singh | P62: 8800470750 | Q62: shashi.s22@yahoo.com | R62: 8years | S62: American Express | T62: 770000 | U62: LWD-Dec-31 | V62: N | W62: Gurgaon | X62: Bangalore | Y62: =MONTH($C62) -> 12 | Z62: =YEAR($C62) -> 2021 | AA62: =LEFT(R62,2) -> 8y | AB62: =SUBSTITUTE(AA62,"y","") -> 8 | AC62: =SUBSTITUTE(AB62,".","") -> 8 | AD62: =SUBSTITUTE(AC62,"+","") -> 8 | AE62: =SUBSTITUTE(AD62,"Y","") -> 8 | AF62: =SUBSTITUTE(AE62,"e","") -> 8 | AG62: =SUBSTITUTE(AF62,",","")*1 -> 8
A63: 62 | B63: Dell FG | C63: 44559 | D63: 14885881 | E63: Vinay Nambiar | F63: 181547 | G63: Vendor Partner | H63: Growelsoftech pvt ltd | I63: UI/UX | J63: 5-8 yrs UX/UI Developer with HTML5,CSS3,Bootstrap,Javascript,Typescript | K63: Joined | L63: No Angular 6 exp | M63: Regular | N63: 355195 | O63: Prasanth R | P63: 9159525210 | Q63: prasanthsatha@gmail.com | R63: 5.8yrs | S63: Codenatives India Pvt Ltd | T63: 400000 | U63: 15 days | V63: N | W63: TamilNadu | X63: Bangalore | Y63: =MONTH($C63) -> 12 | Z63: =YEAR($C63) -> 2021 | AA63: =LEFT(R63,2) -> 5. | AB63: =SUBSTITUTE(AA63,"y","") -> 5. | AC63: =SUBSTITUTE(AB63,".","") -> 5 | AD63: =SUBSTITUTE(AC63,"+","") -> 5 | AE63: =SUBSTITUTE(AD63,"Y","") -> 5 | AF63: =SUBSTITUTE(AE63,"e","") -> 5 | AG63: =SUBSTITUTE(AF63,",","")*1 -> 5
A64: 63 | B64: Dell FG | C64: 44559 | D64: 14885881 | E64: Vinay Nambiar | F64: 181547 | G64: Vendor Partner | H64: Growelsoftech pvt ltd | I64: UI/UX | J64: 5-8 yrs UX/UI Developer with HTML5,CSS3,Bootstrap,Javascript,Typescript | K64: Joined | L64: No Angular 6 exp | M64: Regular | N64: 431558 | O64: Sabareeswaran Palanisamy | P64: 9976108336 | Q64: sabaree.itle11@gmail.com | R64: 7yrs | S64: Wisdomleaf Technologies | T64: 570000 | U64: jan31-lwd | V64: N | W64: Hyderabad | X64: Bangalore | Y64: =MONTH($C64) -> 12 | Z64: =YEAR($C64) -> 2021 | AA64: =LEFT(R64,2) -> 7y | AB64: =SUBSTITUTE(AA64,"y","") -> 7 | AC64: =SUBSTITUTE(AB64,".","") -> 7 | AD64: =SUBSTITUTE(AC64,"+","") -> 7 | AE64: =SUBSTITUTE(AD64,"Y","") -> 7 | AF64: =SUBSTITUTE(AE64,"e","") -> 7 | AG64: =SUBSTITUTE(AF64,",","")*1 -> 7
A65: 64 | B65: Dell FG | C65: 44559 | D65: 64881514 | E65: Vinay Nambiar | F65: 181547 | G65: Vendor Partner | H65: Growelsoftech pvt ltd | I65: UI/UX | J65: 8-12y UI,UX, Front-end Web Developer,HTML5,CSS,Angular/ReactJS,Sketch/Invision/Photoshop | K65: Joined | L65: No Angular 6 exp | M65: Regular | N65: H28337978 | O65: SHATRUGHAN SAHANI | P65: 9973508305 | Q65: shatrughan.jsr@gmail.com | R65: 10years | S65: TCS | T65: 750000 | U65: LWD-Jan-25 | V65: N | W65: Jamshedpur | X65: Bangalore | Y65: =MONTH($C65) -> 12 | Z65: =YEAR($C65) -> 2021 | AA65: =LEFT(R65,2) -> 10 | AB65: =SUBSTITUTE(AA65,"y","") -> 10 | AC65: =SUBSTITUTE(AB65,".","") -> 10 | AD65: =SUBSTITUTE(AC65,"+","") -> 10 | AE65: =SUBSTITUTE(AD65,"Y","") -> 10 | AF65: =SUBSTITUTE(AE65,"e","") -> 10 | AG65: =SUBSTITUTE(AF65,",","")*1 -> 10
A66: 65 | B66: Dell FG | C66: 44559 | D66: 96998230 | E66: Vinay Nambiar | F66: 181547 | G66: Vendor Partner | H66: Growelsoftech pvt ltd | I66: Server | J66: 8-12y Server Virtualization,VMware vSphere,Network Engineering,Software Defined Networking, Load Balancing,DNS Solutions,Kubernetes & Docker,Container Orchestration Infrastructure | K66: Joined | L66: No Angular 6 exp | M66: Regular | N66: 431904 | O66: VIVEK GANGANI | P66: 8102205777 | Q66: vivekgangani@gmail.com | R66: 11years | S66: VIHAAN NETWORKS LTD | T66: 600000 | U66: 15days | V66: N | W66: Jamshedpur | X66: Bangalore | Y66: =MONTH($C66) -> 12 | Z66: =YEAR($C66) -> 2021 | AA66: =LEFT(R66,2) -> 11 | AB66: =SUBSTITUTE(AA66,"y","") -> 11 | AC66: =SUBSTITUTE(AB66,".","") -> 11 | AD66: =SUBSTITUTE(AC66,"+","") -> 11 | AE66: =SUBSTITUTE(AD66,"Y","") -> 11 | AF66: =SUBSTITUTE(AE66,"e","") -> 11 | AG66: =SUBSTITUTE(AF66,",","")*1 -> 11
A67: 66 | B67: Dell FG | C67: 44559 | D67: 14885881 | E67: Vinay Nambiar | F67: 181547 | G67: Vendor Partner | H67: Growelsoftech pvt ltd | I67: UI/UX | J67: 5-8y UX/UI Developer with HTML5,CSS3,Bootstrap,Javascript,Typescript | K67: Joined | L67: No Angular 6 exp | M67: Regular | N67: H8031428 | O67: Sivakumar.Y | P67: 9677776784 | Q67: sivakumarka08@gmail.com | R67: 6 years | S67: Sisesoft it solutions | T67: 540000 | U67: 15 Days | V67: N | W67: Hosur | X67: Bangalore | Y67: =MONTH($C67) -> 12 | Z67: =YEAR($C67) -> 2021 | AA67: =LEFT(R67,2) -> 6 | AB67: =SUBSTITUTE(AA67,"y","") -> 6 | AC67: =SUBSTITUTE(AB67,".","") -> 6 | AD67: =SUBSTITUTE(AC67,"+","") -> 6 | AE67: =SUBSTITUTE(AD67,"Y","") -> 6 | AF67: =SUBSTITUTE(AE67,"e","") -> 6 | AG67: =SUBSTITUTE(AF67,",","")*1 -> 6
A68: 67 | B68: Dell FG | C68: 44559 | D68: 98587791 | E68: Vinay Nambiar | F68: 181547 | G68: Vendor Partner | H68: Growelsoftech pvt ltd | I68: python | J68: 5-8y Python Development | K68: Joined | L68: Requirement closed | M68: Regular | N68: 7392626 | O68: Vinay Kumar | P68: 7696118524 | Q68: vinaykumar.24@hotmail.com | R68: 5.7years | S68: Gemini solution | T68: 1000000 | U68: lwd-20jan | V68: N | W68: Bangalore | X68: Bangalore | Y68: =MONTH($C68) -> 12 | Z68: =YEAR($C68) -> 2021 | AA68: =LEFT(R68,2) -> 5. | AB68: =SUBSTITUTE(AA68,"y","") -> 5. | AC68: =SUBSTITUTE(AB68,".","") -> 5 | AD68: =SUBSTITUTE(AC68,"+","") -> 5 | AE68: =SUBSTITUTE(AD68,"Y","") -> 5 | AF68: =SUBSTITUTE(AE68,"e","") -> 5 | AG68: =SUBSTITUTE(AF68,",","")*1 -> 5
A69: 68 | B69: Dell FG | C69: 44559 | D69: 96445940 | E69: Vinay Nambiar | F69: 181547 | G69: Vendor Partner | H69: Mindsoft | I69: .NET CORE | J69: .NET CORE | K69: Declined | L69: Technical reject | M69: Regular | N69: 415962 | O69: Sureshbabu Padarthi | P69: 7981585429 | Q69: sureshbabup8888@gmail.com | R69: 13+YRS | S69: Tech M | T69: 1600000 | U69: LWD-JAN20TH | V69: N | W69: Hyderabad | X69: Hyderabad | Y69: =MONTH($C69) -> 12 | Z69: =YEAR($C69) -> 2021 | AA69: =LEFT(R69,2) -> 13 | AB69: =SUBSTITUTE(AA69,"y","") -> 13 | AC69: =SUBSTITUTE(AB69,".","") -> 13 | AD69: =SUBSTITUTE(AC69,"+","") -> 13 | AE69: =SUBSTITUTE(AD69,"Y","") -> 13 | AF69: =SUBSTITUTE(AE69,"e","") -> 13 | AG69: =SUBSTITUTE(AF69,",","")*1 -> 13
A70: 69 | B70: Dell FG | C70: 44559 | D70: 94048049 | E70: Vinay Nambiar | F70: 181547 | G70: Vendor Partner | H70: Mindsoft | I70: .NET CORE | J70: .NET CORE | K70: Joined | L70: Other offer | M70: Regular | N70: 417158 | O70: Marripudi Balakrishna | P70: 8978768542 | Q70: marripudi.balakrishna@gmail.com | R70: 3.2yrs | S70: Global logic | T70: 5500000 | U70: LWD-DEC-28TH | V70: N | W70: Hyderabad | X70: Hyderabad | Y70: =MONTH($C70) -> 12 | Z70: =YEAR($C70) -> 2021 | AA70: =LEFT(R70,2) -> 3. | AB70: =SUBSTITUTE(AA70,"y","") -> 3. | AC70: =SUBSTITUTE(AB70,".","") -> 3 | AD70: =SUBSTITUTE(AC70,"+","") -> 3 | AE70: =SUBSTITUTE(AD70,"Y","") -> 3 | AF70: =SUBSTITUTE(AE70,"e","") -> 3 | AG70: =SUBSTITUTE(AF70,",","")*1 -> 3
A71: 70 | B71: Dell FG | C71: 44559 | D71: 96445940 | E71: Vinay Nambiar | F71: 181547 | G71: Vendor Partner | H71: Mindsoft | I71: .NET CORE | J71: .NET CORE | K71: Joined | L71: Other offer | M71: Regular | N71: 417120 | O71: chandra shekar | P71: 6305283750 | Q71: csmansani@gmail.com | R71: 12yrs | S71: Focus softnet | T71: 1660000 | U71: LWD-JAN 17TH | V71: N | W71: Hyderabad | X71: Hyderabad | Y71: =MONTH($C71) -> 12 | Z71: =YEAR($C71) -> 2021 | AA71: =LEFT(R71,2) -> 12 | AB71: =SUBSTITUTE(AA71,"y","") -> 12 | AC71: =SUBSTITUTE(AB71,".","") -> 12 | AD71: =SUBSTITUTE(AC71,"+","") -> 12 | AE71: =SUBSTITUTE(AD71,"Y","") -> 12 | AF71: =SUBSTITUTE(AE71,"e","") -> 12 | AG71: =SUBSTITUTE(AF71,",","")*1 -> 12
A72: 71 | B72: Dell FG | C72: 44559 | D72: 31824993 | E72: Vinay Nambiar | F72: 181547 | G72: Vendor Partner | H72: Mindsoft | I72: Power BI | J72: 1y Power BI (Tableau or similar data visualization tool),SQL | K72: Hold | L72: Position is on Hold | M72: Regular | N72: 438930 | O72: Amala Erthineni | P72: 9133047548 | Q72: elchuriamala@gmail.com | R72: 2.3 years | S72: Quantyum Technology Solutions Pvt.Ltd | T72: 400000 | U72: 15 days official | V72: N | W72: Hyderabad | X72: Hyderabad | Y72: =MONTH($C72) -> 12 | Z72: =YEAR($C72) -> 2021 | AA72: =LEFT(R72,2) -> 2. | AB72: =SUBSTITUTE(AA72,"y","") -> 2. | AC72: =SUBSTITUTE(AB72,".","") -> 2 | AD72: =SUBSTITUTE(AC72,"+","") -> 2 | AE72: =SUBSTITUTE(AD72,"Y","") -> 2 | AF72: =SUBSTITUTE(AE72,"e","") -> 2 | AG72: =SUBSTITUTE(AF72,",","")*1 -> 2
A73: 72 | B73: Dell FG | C73: 44559 | D73: 31824993 | E73: Vinay Nambiar | F73: 181547 | G73: Vendor Partner | H73: Mindsoft | I73: Power BI | J73: 1y Power BI (Tableau or similar data visualization tool),SQL | K73: Hold | L73: Position is on Hold | M73: Regular | N73: 439881 | O73: Kaukab Nazifa Shaikh | P73: 9182043712 | Q73: kaukabshaikh4@gmail.com | R73: 2.5 years | S73: Pearl Stone Technology Pvt ltd | T73: 220000 | U73: 30 days but negotiable to 15 days | V73: N | W73: Hyderabad | X73: Hyderabad | Y73: =MONTH($C73) -> 12 | Z73: =YEAR($C73) -> 2021 | AA73: =LEFT(R73,2) -> 2. | AB73: =SUBSTITUTE(AA73,"y","") -> 2. | AC73: =SUBSTITUTE(AB73,".","") -> 2 | AD73: =SUBSTITUTE(AC73,"+","") -> 2 | AE73: =SUBSTITUTE(AD73,"Y","") -> 2 | AF73: =SUBSTITUTE(AE73,"e","") -> 2 | AG73: =SUBSTITUTE(AF73,",","")*1 -> 2
A74: 73 | B74: Dell FG | C74: 44559 | D74: 31824993 | E74: Vinay Nambiar | F74: 181547 | G74: Vendor Partner | H74: Mindsoft | I74: Power BI | J74: 1y Power BI (Tableau or similar data visualization tool),SQL | K74: Hold | L74: Position is on Hold | M74: Regular | N74: 440068 | O74: Harish B | P74: 7842809161 | Q74: harishb2109@gmail.com | R74: 1 year | S74: Techmahindra | T74: 180000 | U74: Immediate. Serving notice period. LWD is 15th Jan '22 | V74: N | W74: Hyderabad | X74: Hyderabad | Y74: =MONTH($C74) -> 12 | Z74: =YEAR($C74) -> 2021 | AA74: =LEFT(R74,2) -> 1 | AB74: =SUBSTITUTE(AA74,"y","") -> 1 | AC74: =SUBSTITUTE(AB74,".","") -> 1 | AD74: =SUBSTITUTE(AC74,"+","") -> 1 | AE74: =SUBSTITUTE(AD74,"Y","") -> 1 | AF74: =SUBSTITUTE(AE74,"e","") -> 1 | AG74: =SUBSTITUTE(AF74,",","")*1 -> 1
A75: 74 | B75: Dell FG | C75: 44559 | D75: 31824993 | E75: Vinay Nambiar | F75: 181547 | G75: Vendor Partner | H75: Mindsoft | I75: Power BI | J75: 1y Power BI (Tableau or similar data visualization tool),SQL | K75: Hold | L75: Position is on Hold | M75: Regular | N75: 440827 | O75: Vellavalam Vishwanath | P75: 9398066805 | Q75: vvvishwanath06@gmail.com | R75: 4 years | S75: Not working( Last worked with Kfin Technologies till October '21 ) | T75: 180000 | U75: Immediate | V75: N | W75: Hyderabad | X75: Hyderabad | Y75: =MONTH($C75) -> 12 | Z75: =YEAR($C75) -> 2021 | AA75: =LEFT(R75,2) -> 4 | AB75: =SUBSTITUTE(AA75,"y","") -> 4 | AC75: =SUBSTITUTE(AB75,".","") -> 4 | AD75: =SUBSTITUTE(AC75,"+","") -> 4 | AE75: =SUBSTITUTE(AD75,"Y","") -> 4 | AF75: =SUBSTITUTE(AE75,"e","") -> 4 | AG75: =SUBSTITUTE(AF75,",","")*1 -> 4
A76: 75 | B76: Dell FG | C76: 44559 | D76: 31824993 | E76: Vinay Nambiar | F76: 181547 | G76: Vendor Partner | H76: Mindsoft | I76: Power BI | J76: 1y Power BI (Tableau or similar data visualization tool),SQL | K76: Hold | L76: Position is on Hold | M76: Regular | N76: 440883 | O76: Lova Prasad Chikkala | P76: 6304845656 | Q76: clovaprasad@gmail.com | R76: 2 years | S76: Adcc Infocad Pvt Ltd | T76: 240000 | U76: Immediate. Serving notice period. LWD is 4th Jan '22 | V76: N | W76: Hyderabad | X76: Hyderabad | Y76: =MONTH($C76) -> 12 | Z76: =YEAR($C76) -> 2021 | AA76: =LEFT(R76,2) -> 2 | AB76: =SUBSTITUTE(AA76,"y","") -> 2 | AC76: =SUBSTITUTE(AB76,".","") -> 2 | AD76: =SUBSTITUTE(AC76,"+","") -> 2 | AE76: =SUBSTITUTE(AD76,"Y","") -> 2 | AF76: =SUBSTITUTE(AE76,"e","") -> 2 | AG76: =SUBSTITUTE(AF76,",","")*1 -> 2
A77: 76 | B77: Dell FG | C77: 44560 | D77: 44879198 | E77: Rahul Kapoor | F77: U82721 | G77: Vendor Partner | H77: Nityo InfoTech | I77: .NET,SQL,WEB API | J77: DOTNET | K77: Tech1 Reject | L77: Back up candidates | M77: Regular | N77: 444379 | O77: Chandra Sekhar Swain | P77: 9337706028/9938316016 | Q77: csswain6@gmail.com | R77: 4 Years | S77: infinite computer solutions | T77: 600000 | U77: Immediate | V77: N | W77: Bangalore | X77: Bangalore | Y77: =MONTH($C77) -> 12 | Z77: =YEAR($C77) -> 2021 | AA77: =LEFT(R77,2) -> 4 | AB77: =SUBSTITUTE(AA77,"y","") -> 4 | AC77: =SUBSTITUTE(AB77,".","") -> 4 | AD77: =SUBSTITUTE(AC77,"+","") -> 4 | AE77: =SUBSTITUTE(AD77,"Y","") -> 4 | AF77: =SUBSTITUTE(AE77,"e","") -> 4 | AG77: =SUBSTITUTE(AF77,",","")*1 -> 4
A78: 77 | B78: Dell FG | C78: 44560 | D78: 44879198 | E78: Rahul Kapoor | F78: U82721 | G78: Vendor Partner | H78: Nityo InfoTech | I78: .NET,SQL,WEB API | J78: DOTNET | K78: Client Reject | L78: Back up candidates | M78: Regular | N78: 443349 | O78: Varun Dhawan | P78: 8727818110/9915550756 | Q78: varundhawan441@gmail.com | R78: 2.6 Years | S78: InPracSys | T78: 324000 | U78: 30days(20days) | V78: N | W78: Amritsar | X78: Bangalore | Y78: =MONTH($C78) -> 12 | Z78: =YEAR($C78) -> 2021 | AA78: =LEFT(R78,2) -> 2. | AB78: =SUBSTITUTE(AA78,"y","") -> 2. | AC78: =SUBSTITUTE(AB78,".","") -> 2 | AD78: =SUBSTITUTE(AC78,"+","") -> 2 | AE78: =SUBSTITUTE(AD78,"Y","") -> 2 | AF78: =SUBSTITUTE(AE78,"e","") -> 2 | AG78: =SUBSTITUTE(AF78,",","")*1 -> 2
A79: 78 | B79: Dell FG | C79: 44560 | D79: 44879198 | E79: Rahul Kapoor | F79: U82721 | G79: Vendor Partner | H79: Nityo InfoTech | I79: .NET,SQL,WEB API | J79: DOTNET | K79: Tech1 Reject | L79: Back up candidates | M79: Regular | N79: 443334 | O79: Rabindra Kumar Gupta | P79: 8789522979/8052980343 | Q79: Rabindra19gupta@gmail.com | R79: 3.1 Years | S79: Accenture India Pvt Ltd | T79: 500000 | U79: Immediate | V79: N | W79: Gurgaon | X79: Bangalore | Y79: =MONTH($C79) -> 12 | Z79: =YEAR($C79) -> 2021 | AA79: =LEFT(R79,2) -> 3. | AB79: =SUBSTITUTE(AA79,"y","") -> 3. | AC79: =SUBSTITUTE(AB79,".","") -> 3 | AD79: =SUBSTITUTE(AC79,"+","") -> 3 | AE79: =SUBSTITUTE(AD79,"Y","") -> 3 | AF79: =SUBSTITUTE(AE79,"e","") -> 3 | AG79: =SUBSTITUTE(AF79,",","")*1 -> 3
A80: 79 | B80: Dell FG | C80: 44560 | D80: 44879198 | E80: Rahul Kapoor | F80: U82721 | G80: Vendor Partner | H80: Nityo InfoTech | I80: .NET,SQL,WEB API | J80: DOTNET | K80: Tech2 IP | L80: Back up candidates | M80: Regular | N80: 444092 | O80: Shiva Kumar V | P80: 7406065250/7019125804 | Q80: rishigowda315@gmail.com | R80: 2 Years | S80: ITC INFOTECH INDIA LTD | T80: 290000 | U80: Immediate | V80: N | W80: Bangalore | X80: Bangalore | Y80: =MONTH($C80) -> 12 | Z80: =YEAR($C80) -> 2021 | AA80: =LEFT(R80,2) -> 2 | AB80: =SUBSTITUTE(AA80,"y","") -> 2 | AC80: =SUBSTITUTE(AB80,".","") -> 2 | AD80: =SUBSTITUTE(AC80,"+","") -> 2 | AE80: =SUBSTITUTE(AD80,"Y","") -> 2 | AF80: =SUBSTITUTE(AE80,"e","") -> 2 | AG80: =SUBSTITUTE(AF80,",","")*1 -> 2
A81: 80 | B81: Dell FG | C81: 44560 | D81: 50201569 | E81: Rahul Kapoor | F81: U82721 | G81: Vendor Partner | H81: Nityo InfoTech | I81: Mobility | J81: Mobility | K81: Client Reject | L81: Back up candidates | M81: Regular | N81: 443201 | O81: Mohammed Athar | P81: 8919936755 | Q81: mohammedatharf@gmail.com | R81: 5.6yrs | S81: Raising Infotech | T81: 420000 | U81: 30 days official(Neg) | V81: N | W81: Hyderabad | X81: Hyderabad | Y81: =MONTH($C81) -> 12 | Z81: =YEAR($C81) -> 2021 | AA81: =LEFT(R81,2) -> 5. | AB81: =SUBSTITUTE(AA81,"y","") -> 5. | AC81: =SUBSTITUTE(AB81,".","") -> 5 | AD81: =SUBSTITUTE(AC81,"+","") -> 5 | AE81: =SUBSTITUTE(AD81,"Y","") -> 5 | AF81: =SUBSTITUTE(AE81,"e","") -> 5 | AG81: =SUBSTITUTE(AF81,",","")*1 -> 5
A82: 81 | B82: Dell FG | C82: 44560 | D82: 50201569 | E82: Rahul Kapoor | F82: U82721 | G82: Vendor Partner | H82: Nityo InfoTech | I82: Mobility | J82: Mobility | K82: Client Reject | L82: Back up candidates | M82: Regular | N82: 443291 | O82: Amresh Kumar | P82: 6207414470 | Q82: singhamresh1993.kumar@gmail.com | R82: 5.8yrs | S82: Quaser telecom | T82: 480000 | U82: 30 days | V82: N | W82: Hyderabad | X82: Hyderabad | Y82: =MONTH($C82) -> 12 | Z82: =YEAR($C82) -> 2021 | AA82: =LEFT(R82,2) -> 5. | AB82: =SUBSTITUTE(AA82,"y","") -> 5. | AC82: =SUBSTITUTE(AB82,".","") -> 5 | AD82: =SUBSTITUTE(AC82,"+","") -> 5 | AE82: =SUBSTITUTE(AD82,"Y","") -> 5 | AF82: =SUBSTITUTE(AE82,"e","") -> 5 | AG82: =SUBSTITUTE(AF82,",","")*1 -> 5
A83: 82 | B83: Dell FG | C83: 44560 | D83: 39949317 | E83: Rahul Kapoor | F83: U82721 | G83: Vendor Partner | H83: Nityo InfoTech | I83: Java,Selenium,API | J83: SDET | K83: Client IP | L83: Waiting for client feedback | M83: Regular | N83: 446688 | O83: Agyarapu Srinivas | P83: 9542336206/8096984181 | Q83: srinivas.agyarapu@gmail.com | R83: 3.5 Years | S83: PROMAESTRO TECHSOURCE PRIVATE LIMITED | T83: 480000 | U83: 15days | V83: N | W83: Hyderabad | X83: Bangalore | Y83: =MONTH($C83) -> 12 | Z83: =YEAR($C83) -> 2021 | AA83: =LEFT(R83,2) -> 3. | AB83: =SUBSTITUTE(AA83,"y","") -> 3. | AC83: =SUBSTITUTE(AB83,".","") -> 3 | AD83: =SUBSTITUTE(AC83,"+","") -> 3 | AE83: =SUBSTITUTE(AD83,"Y","") -> 3 | AF83: =SUBSTITUTE(AE83,"e","") -> 3 | AG83: =SUBSTITUTE(AF83,",","")*1 -> 3
A84: 83 | B84: Dell FG | C84: 44560 | D84: 39949317 | E84: Rahul Kapoor | F84: U82721 | G84: Vendor Partner | H84: Nityo InfoTech | I84: Java,Selenium,API | J84: SDET | K84: Client IP | L84: Waiting for client feedback | M84: Regular | N84: 445387 | O84: B.Ashok Reddy | P84: 918143754908/9502459279 | Q84: reddy.ashok1008@gmail.com | R84: 4.10 Years | S84: skylives infotech pvt ltd | T84: 520000 | U84: Immediate | V84: N | W84: Hyderabad | X84: Bangalore | Y84: =MONTH($C84) -> 12 | Z84: =YEAR($C84) -> 2021 | AA84: =LEFT(R84,2) -> 4. | AB84: =SUBSTITUTE(AA84,"y","") -> 4. | AC84: =SUBSTITUTE(AB84,".","") -> 4 | AD84: =SUBSTITUTE(AC84,"+","") -> 4 | AE84: =SUBSTITUTE(AD84,"Y","") -> 4 | AF84: =SUBSTITUTE(AE84,"e","") -> 4 | AG84: =SUBSTITUTE(AF84,",","")*1 -> 4
A85: 84 | B85: Dell FG | C85: 44560 | D85: 39949317 | E85: Rahul Kapoor | F85: U82721 | G85: Vendor Partner | H85: Nityo InfoTech | I85: Java,Selenium,API | J85: SDET | K85: Declined | L85: Waiting for client feedback | M85: Regular | N85: 446552 | O85: chandrasekhar ch | P85: 8105432661/9848074068 | Q85: chandrach311@gmail.com | R85: 3 Years | S85: Accenture | T85: 480000 | U85: LWD:4/01/22 | V85: N | W85: Bangalore | X85: Bangalore | Y85: =MONTH($C85) -> 12 | Z85: =YEAR($C85) -> 2021 | AA85: =LEFT(R85,2) -> 3 | AB85: =SUBSTITUTE(AA85,"y","") -> 3 | AC85: =SUBSTITUTE(AB85,".","") -> 3 | AD85: =SUBSTITUTE(AC85,"+","") -> 3 | AE85: =SUBSTITUTE(AD85,"Y","") -> 3 | AF85: =SUBSTITUTE(AE85,"e","") -> 3 | AG85: =SUBSTITUTE(AF85,",","")*1 -> 3
A86: 85 | B86: Dell FG | C86: 44560 | D86: 39949317 | E86: Rahul Kapoor | F86: U82721 | G86: Vendor Partner | H86: Nityo InfoTech | I86: Java,Selenium,API | J86: SDET | K86: Client IP | L86: Waiting for client feedback | M86: Regular | N86: 446614 | O86: Pramod.L.Dhanave | P86: 7620686822/8806785100 | Q86: dhanavepl99@gmail.com | R86: 3.2 Years | S86: Tibco india pvt ltd | T86: 450000 | U86: 15days | V86: N | W86: Pune | X86: Bangalore | Y86: =MONTH($C86) -> 12 | Z86: =YEAR($C86) -> 2021 | AA86: =LEFT(R86,2) -> 3. | AB86: =SUBSTITUTE(AA86,"y","") -> 3. | AC86: =SUBSTITUTE(AB86,".","") -> 3 | AD86: =SUBSTITUTE(AC86,"+","") -> 3 | AE86: =SUBSTITUTE(AD86,"Y","") -> 3 | AF86: =SUBSTITUTE(AE86,"e","") -> 3 | AG86: =SUBSTITUTE(AF86,",","")*1 -> 3
A87: 86 | B87: Dell FG | C87: 44560 | D87: 39949317 | E87: Rahul Kapoor | F87: U82721 | G87: Vendor Partner | H87: Nityo InfoTech | I87: Java,Selenium,API | J87: SDET | K87: Client IP | L87: Waiting for client feedback | M87: Regular | N87: 446640 | O87: Mohsin Phutankar | P87: 8329313263/9766735788 | Q87: phutankarmohsin@gmail.com | R87: 3.2 Years | S87: PubMatic India Pvt Ltd | T87: 490000 | U87: 15days | V87: N | W87: Pune | X87: Bangalore | Y87: =MONTH($C87) -> 12 | Z87: =YEAR($C87) -> 2021 | AA87: =LEFT(R87,2) -> 3. | AB87: =SUBSTITUTE(AA87,"y","") -> 3. | AC87: =SUBSTITUTE(AB87,".","") -> 3 | AD87: =SUBSTITUTE(AC87,"+","") -> 3 | AE87: =SUBSTITUTE(AD87,"Y","") -> 3 | AF87: =SUBSTITUTE(AE87,"e","") -> 3 | AG87: =SUBSTITUTE(AF87,",","")*1 -> 3
A88: 87 | B88: Dell FG | C88: 44560 | D88: 50201569 | E88: Rahul Kapoor | F88: U82721 | G88: Vendor Partner | H88: Mindsoft | I88: Mobility | J88: Mobility | K88: Client IP | L88: Waiting for client feedback | M88: Regular | N88: 443201 | O88: Mohammed Athar | P88: 8919936755 | Q88: mohammedatharf@gmail.com | R88: 5.6yrs | S88: Accenture | T88: 420000 | U88: 30 days official(Neg) | V88: N | W88: Hyderabad | X88: Hyderabad | Y88: =MONTH($C88) -> 12 | Z88: =YEAR($C88) -> 2021 | AA88: =LEFT(R88,2) -> 5. | AB88: =SUBSTITUTE(AA88,"y","") -> 5. | AC88: =SUBSTITUTE(AB88,".","") -> 5 | AD88: =SUBSTITUTE(AC88,"+","") -> 5 | AE88: =SUBSTITUTE(AD88,"Y","") -> 5 | AF88: =SUBSTITUTE(AE88,"e","") -> 5 | AG88: =SUBSTITUTE(AF88,",","")*1 -> 5
A89: 88 | B89: Dell FG | C89: 44560 | D89: 50201569 | E89: Rahul Kapoor | F89: U82721 | G89: Vendor Partner | H89: Mindsoft | I89: Mobility | J89: Mobility | K89: Client IP | L89: Waiting for client feedback | M89: Regular | N89: 443291 | O89: Amresh Kumar | P89: 6207414470 | Q89: singhamresh1993.kumar@gmail.com | R89: 5.8yrs | S89: Accenture | T89: 480000 | U89: 30 days | V89: N | W89: Hyderabad | X89: Hyderabad | Y89: =MONTH($C89) -> 12 | Z89: =YEAR($C89) -> 2021 | AA89: =LEFT(R89,2) -> 5. | AB89: =SUBSTITUTE(AA89,"y","") -> 5. | AC89: =SUBSTITUTE(AB89,".","") -> 5 | AD89: =SUBSTITUTE(AC89,"+","") -> 5 | AE89: =SUBSTITUTE(AD89,"Y","") -> 5 | AF89: =SUBSTITUTE(AE89,"e","") -> 5 | AG89: =SUBSTITUTE(AF89,",","")*1 -> 5
A90: 89 | B90: Dell FG | C90: 44560 | D90: 76222649 | E90: Vinay Nambiar | F90: 181547 | G90: Vendor Partner | H90: Mindsoft | I90: PL SQL Dev | J90: Oracle,Informatica | K90: Joined | L90: No Show | M90: Regular | N90: 443413 | O90: Bindu Nanubala | P90: 7793997081 | Q90: bindunanubala.8@gmail.com | R90: 4.2yrs | S90: Ness Technology | T90: 480000 | U90: Lwd Jan 12th | V90: N | W90: Hyderabad | X90: Hyderabad | Y90: =MONTH($C90) -> 12 | Z90: =YEAR($C90) -> 2021 | AA90: =LEFT(R90,2) -> 4. | AB90: =SUBSTITUTE(AA90,"y","") -> 4. | AC90: =SUBSTITUTE(AB90,".","") -> 4 | AD90: =SUBSTITUTE(AC90,"+","") -> 4 | AE90: =SUBSTITUTE(AD90,"Y","") -> 4 | AF90: =SUBSTITUTE(AE90,"e","") -> 4 | AG90: =SUBSTITUTE(AF90,",","")*1 -> 4
A91: 90 | B91: Dell FG | C91: 44560 | D91: 76222649 | E91: Vinay Nambiar | F91: 181547 | G91: Vendor Partner | H91: Mindsoft | I91: PL SQL Dev | J91: Oracle,Informatica | K91: Joined | L91: No Show | M91: Regular | N91: 444799 | O91: Murali Krishna B | P91: 9908305965 | Q91: murali2db@gmail.com | R91: 3.5yrs | S91: Mindtree | T91: 400000 | U91: 30 days(Neg) | V91: N | W91: Hyderabad | X91: Hyderabad | Y91: =MONTH($C91) -> 12 | Z91: =YEAR($C91) -> 2021 | AA91: =LEFT(R91,2) -> 3. | AB91: =SUBSTITUTE(AA91,"y","") -> 3. | AC91: =SUBSTITUTE(AB91,".","") -> 3 | AD91: =SUBSTITUTE(AC91,"+","") -> 3 | AE91: =SUBSTITUTE(AD91,"Y","") -> 3 | AF91: =SUBSTITUTE(AE91,"e","") -> 3 | AG91: =SUBSTITUTE(AF91,",","")*1 -> 3
A92: 91 | B92: Dell FG | C92: 44560 | D92: 31824993 | E92: Vinay Nambiar | F92: 181547 | G92: Vendor Partner | H92: Mindsoft | I92: Power BI | J92: 1y Power BI (Tableau or similar data visualization tool),SQL | K92: Hold | L92: Position is on Hold | M92: Regular | N92: 444414 | O92: Mahesh Gundluru | P92: 9704828135 | Q92: maheshchintu432@gmail.com | R92: 3 years | S92: Seed-flow Cyber Tech Pvt Ltd | T92: 170000 | U92: 30 days but negotiable to 15 days | V92: N | W92: Hyderabad | X92: Hyderabad | Y92: =MONTH($C92) -> 12 | Z92: =YEAR($C92) -> 2021 | AA92: =LEFT(R92,2) -> 3 | AB92: =SUBSTITUTE(AA92,"y","") -> 3 | AC92: =SUBSTITUTE(AB92,".","") -> 3 | AD92: =SUBSTITUTE(AC92,"+","") -> 3 | AE92: =SUBSTITUTE(AD92,"Y","") -> 3 | AF92: =SUBSTITUTE(AE92,"e","") -> 3 | AG92: =SUBSTITUTE(AF92,",","")*1 -> 3
A93: 92 | B93: Dell FG | C93: 44560 | D93: 31824993 | E93: Vinay Nambiar | F93: 181547 | G93: Vendor Partner | H93: Mindsoft | I93: Power BI | J93: 1y Power BI (Tableau or similar data visualization tool),SQL | K93: Hold | L93: Position is on Hold | M93: Regular | N93: 444515 | O93: Rajasekhar Reddy K | P93: 8019844117 | Q93: Krajsekharreddkk@gmail.com | R93: 2.8 years | S93: Stratycon Technologies | T93: 320000 | U93: 30 days but negotiable to 15 days. Currently on bench | V93: N | W93: Bangalore | X93: Hyderabad | Y93: =MONTH($C93) -> 12 | Z93: =YEAR($C93) -> 2021 | AA93: =LEFT(R93,2) -> 2. | AB93: =SUBSTITUTE(AA93,"y","") -> 2. | AC93: =SUBSTITUTE(AB93,".","") -> 2 | AD93: =SUBSTITUTE(AC93,"+","") -> 2 | AE93: =SUBSTITUTE(AD93,"Y","") -> 2 | AF93: =SUBSTITUTE(AE93,"e","") -> 2 | AG93: =SUBSTITUTE(AF93,",","")*1 -> 2
A94: 93 | B94: Dell FG | C94: 44560 | D94: 53300677 | E94: Vinay Nambiar | F94: 181547 | G94: Vendor Partner | H94: Mindsoft | I94: SDET | J94: java selenium | K94: Joined | L94: Joined | M94: Regular | N94: 443497 | O94: Hemanth | P94: 7396642265 | Q94: dasarihemanth432@gmail.com | R94: 3.10yrs | S94: Ericsson | T94: 400000 | U94: Immediate | V94: N | W94: Hyderabad | X94: Hyderabad | Y94: =MONTH($C94) -> 12 | Z94: =YEAR($C94) -> 2021 | AA94: =LEFT(R94,2) -> 3. | AB94: =SUBSTITUTE(AA94,"y","") -> 3. | AC94: =SUBSTITUTE(AB94,".","") -> 3 | AD94: =SUBSTITUTE(AC94,"+","") -> 3 | AE94: =SUBSTITUTE(AD94,"Y","") -> 3 | AF94: =SUBSTITUTE(AE94,"e","") -> 3 | AG94: =SUBSTITUTE(AF94,",","")*1 -> 3
A95: 94 | B95: Dell FG | C95: 44560 | D95: 53300677 | E95: Vinay Nambiar | F95: 181547 | G95: Vendor Partner | H95: Mindsoft | I95: SDET | J95: java selenium | K95: Joined | L95: Joined | M95: Regular | N95: 444754 | O95: Kalyan | P95: 9182268829 | Q95: tkalyan816@gmail.com | R95: 3.2yrs | S95: Mahendrada Softtech | T95: 620000 | U95: Immediate | V95: N | W95: Hyderabad | X95: Hyderabad | Y95: =MONTH($C95) -> 12 | Z95: =YEAR($C95) -> 2021 | AA95: =LEFT(R95,2) -> 3. | AB95: =SUBSTITUTE(AA95,"y","") -> 3. | AC95: =SUBSTITUTE(AB95,".","") -> 3 | AD95: =SUBSTITUTE(AC95,"+","") -> 3 | AE95: =SUBSTITUTE(AD95,"Y","") -> 3 | AF95: =SUBSTITUTE(AE95,"e","") -> 3 | AG95: =SUBSTITUTE(AF95,",","")*1 -> 3
A96: 9 | B96: Dell FG | C96: 44560 | D96: 53300677 | E96: Vinay Nambiar | F96: 181547 | G96: Vendor Partner | H96: Mindsoft | I96: SDET | J96: java selenium | K96: Joined | L96: Joined | M96: Regular | N96: 445309 | O96: Pooja Rudrawar | P96: 8793228193 | Q96: rudrawarpooja81@gmail.com | R96: 3.5yrs | S96: Bitwise Solutions | T96: 480000 | U96: 30days(nego 15days) | V96: N | W96: Hyderabad | X96: Hyderabad | Y96: =MONTH($C96) -> 12 | Z96: =YEAR($C96) -> 2021 | AA96: =LEFT(R96,2) -> 3. | AB96: =SUBSTITUTE(AA96,"y","") -> 3. | AC96: =SUBSTITUTE(AB96,".","") -> 3 | AD96: =SUBSTITUTE(AC96,"+","") -> 3 | AE96: =SUBSTITUTE(AD96,"Y","") -> 3 | AF96: =SUBSTITUTE(AE96,"e","") -> 3 | AG96: =SUBSTITUTE(AF96,",","")*1 -> 3
A97: 96 | B97: Dell FG | C97: 44560 | D97: 53300677 | E97: Vinay Nambiar | F97: 181547 | G97: Vendor Partner | H97: Mindsoft | I97: SDET | J97: java selenium | K97: Joined | L97: Joined | M97: Regular | N97: 446449 | O97: PALLE SIVA RAMI REDDY | P97: 8500777534 | Q97: sivaramireddy75@gmail.com | R97: 2.8yrs | S97: Cogbizant | T97: 485000 | U97: lwd-jan 28th | V97: N | W97: Hyderabad | X97: Hyderabad | Y97: =MONTH($C97) -> 12 | Z97: =YEAR($C97) -> 2021 | AA97: =LEFT(R97,2) -> 2. | AB97: =SUBSTITUTE(AA97,"y","") -> 2. | AC97: =SUBSTITUTE(AB97,".","") -> 2 | AD97: =SUBSTITUTE(AC97,"+","") -> 2 | AE97: =SUBSTITUTE(AD97,"Y","") -> 2 | AF97: =SUBSTITUTE(AE97,"e","") -> 2 | AG97: =SUBSTITUTE(AF97,",","")*1 -> 2
A98: 97 | B98: Dell FG | C98: 44561 | D98: 39949317 | E98: Rahul Kapoor | F98: U82721 | G98: Vendor Partner | H98: Nityo InfoTech | I98: Java,Selenium,API | J98: SDET | K98: Tech1 Reject | L98: Back up candidates | M98: Regular | N98: 449579 | O98: Bharat Dutt | P98: 918971936148/9560433176 | Q98: bharatdutt21@gmail.com | R98: 8 Years | S98: Capgemini Technology Services India Limit | T98: 1000000 | U98: Immediate | V98: N | W98: Pune | X98: Bangalore | Y98: =MONTH($C98) -> 12 | Z98: =YEAR($C98) -> 2021 | AA98: =LEFT(R98,2) -> 8 | AB98: =SUBSTITUTE(AA98,"y","") -> 8 | AC98: =SUBSTITUTE(AB98,".","") -> 8 | AD98: =SUBSTITUTE(AC98,"+","") -> 8 | AE98: =SUBSTITUTE(AD98,"Y","") -> 8 | AF98: =SUBSTITUTE(AE98,"e","") -> 8 | AG98: =SUBSTITUTE(AF98,",","")*1 -> 8
A99: 98 | B99: Dell FG | C99: 44561 | D99: 39949317 | E99: Rahul Kapoor | F99: U82721 | G99: Vendor Partner | H99: Nityo InfoTech | I99: Java,Selenium,API | J99: SDET | K99: Tech1 Reject | L99: Back up candidates | M99: Regular | N99: 450788 | O99: mamatha chinthareddy | P99: 9652911711/9959900011 | Q99: mamatha.chinthareddy1990@gmail.com | R99: 6.7 Years | S99: IBM India Pvt. Limited | T99: 800000 | U99: 30days(Neg 15days) | V99: N | W99: Hyderabad | X99: Bangalore | Y99: =MONTH($C99) -> 12 | Z99: =YEAR($C99) -> 2021 | AA99: =LEFT(R99,2) -> 6. | AB99: =SUBSTITUTE(AA99,"y","") -> 6. | AC99: =SUBSTITUTE(AB99,".","") -> 6 | AD99: =SUBSTITUTE(AC99,"+","") -> 6 | AE99: =SUBSTITUTE(AD99,"Y","") -> 6 | AF99: =SUBSTITUTE(AE99,"e","") -> 6 | AG99: =SUBSTITUTE(AF99,",","")*1 -> 6
A100: 99 | B100: Dell FG | C100: 44561 | D100: 39949317 | E100: Rahul Kapoor | F100: U82721 | G100: Vendor Partner | H100: Nityo InfoTech | I100: Java,Selenium,API | J100: SDET | K100: Tech1 Reject | L100: Back up candidates | M100: Regular | N100: 449697 | O100: Papun Kumar Sahoo | P100: 9348568166/9658229904 | Q100: papunk151@gmail.com | R100: 5.3 Years | S100: Infosys(Payroll of Trigent Software) | T100: 531000 | U100: 30days(Neg 20days) | V100: N | W100: Bangalore | X100: Bangalore | Y100: =MONTH($C100) -> 12 | Z100: =YEAR($C100) -> 2021 | AA100: =LEFT(R100,2) -> 5. | AB100: =SUBSTITUTE(AA100,"y","") -> 5. | AC100: =SUBSTITUTE(AB100,".","") -> 5 | AD100: =SUBSTITUTE(AC100,"+","") -> 5 | AE100: =SUBSTITUTE(AD100,"Y","") -> 5 | AF100: =SUBSTITUTE(AE100,"e","") -> 5 | AG100: =SUBSTITUTE(AF100,",","")*1 -> 5
...

Sheet Offer Approval Format
B2: To be Filled | D2: To be Filled
A3: Candidate id | B3: H8051680 | C3: Business Approval(Y/N) | D3: Yes
A4: RMG POC | B4: ABZ | C4: TA Head Approval(Y/N) | D4: Yes
A5: Hiring Manager/Account Manager Name | B5: TYU | C5: Move to HR(Y/N) | D5: Yes
A6: Hiring Manager/Account Manager Band | B6: b2 | C6: Shared to Offer Team On(Date)
A12: SO# | B12: Candidate id | C12: Candidate Name | D12: Skill | E12: Experience | F12: Current Organization | G12: Account Name | H12: Total CTC Offered in LPA/Monthly Rate card | I12: CTC Proposed(Fixed) | J12: Variable Amount | K12: Variable % | L12: Current CTC | M12: Joining Bonus If Any | N12: Band Offered | O12: Designation Offered | P12: Max salary approved for the Band | Q12: Delta to be approved | R12: Reason for Exception (other than max. of salary band) | S12: Expected Joining Date | T12: Employment Type | U12: Source | V12: Recruiter Name | W12: RMG POC | X12: Work Location (City and State) | Y12: To be filled by the Business | Z12: Hiring Manager/Account Manager Name | AA12: Hiring Manager/Account Manager Band | AB12: Project Type | AC12: Client Rate/hr | AD12: GPM % | AE12: Status | AF12: Business Approval(Y/N) | AG12: TA Head Approval(Y/N) | AH12: Move to HR(Y/N) | AI12: Shared to Offer Team On(Date)
A13: =IF(B3="","",_xlfn.XLOOKUP(B3,'Candidate Basedata'!N:N,'Candidate Basedata'!D:D)) -> 69374586 | B13: =IF(B3="","",B3) -> H8051680 | C13: =IF(B3="","",_xlfn.XLOOKUP(B3,'Candidate Basedata'!N:N,'Candidate Basedata'!O:O)) -> Chandra Vamsi Aradhyula | D13: =IF(B3="","",_xlfn.XLOOKUP(B3,'Candidate Basedata'!N:N,'Candidate Basedata'!I:I)) -> SDET | E13: =IF(B3="","",_xlfn.XLOOKUP(B3,'Candidate Basedata'!N:N,'Candidate Basedata'!R:R)) -> 7.9yrs | F13: =IF(B3="","",_xlfn.XLOOKUP(B3,'Candidate Basedata'!N:N,'Candidate Basedata'!T:T)) -> Jarus Technologies | G13: =IF(B3="","",_xlfn.XLOOKUP(B3,'Candidate Basedata'!N:N,'Candidate Basedata'!B:B)) -> Dell FG | H13: =IF(B3="","",_xlfn.XLOOKUP(B3,'Candidate Basedata'!N:N,'Candidate Basedata'!#REF!)) -> #REF! | I13: =IF(B3="","",_xlfn.XLOOKUP(B3,'Candidate Basedata'!N:N,'Candidate Basedata'!#REF!)) -> #REF! | J13: =IF(B3="","",_xlfn.XLOOKUP(B3,'Candidate Basedata'!N:N,'Candidate Basedata'!#REF!)) -> #REF! | K13: =IF(B3="","",_xlfn.XLOOKUP(B3,'Candidate Basedata'!N:N,'Candidate Basedata'!#REF!)) -> #REF! | L13: =IF(B3="","",_xlfn.XLOOKUP(B3,'Candidate Basedata'!N:N,'Candidate Basedata'!U:U)) -> 793000 | M13: =IF(B3="","",_xlfn.XLOOKUP(B3,'Candidate Basedata'!N:N,'Candidate Basedata'!#REF!)) -> #REF! | N13: =IF(B3="","",_xlfn.XLOOKUP(B3,'Candidate Basedata'!N:N,'Candidate Basedata'!#REF!)) -> #REF! | O13: =IF(B3="","",_xlfn.XLOOKUP(B3,'Candidate Basedata'!N:N,'Candidate Basedata'!#REF!)) -> #REF! | P13: =IF(B3="","",_xlfn.XLOOKUP(B3,'Candidate Basedata'!N:N,'Candidate Basedata'!#REF!)) -> #REF! | Q13: =IF(B3="","",_xlfn.XLOOKUP(B3,'Candidate Basedata'!N:N,'Candidate Basedata'!#REF!)) -> #REF! | R13: =IF(B3="","",_xlfn.XLOOKUP(B3,'Candidate Basedata'!N:N,'Candidate Basedata'!#REF!)) -> #REF! | S13: =IF(B3="","",_xlfn.XLOOKUP(B3,'Candidate Basedata'!N:N,'Candidate Basedata'!#REF!)) -> #REF! | T13: =IF(B3="","",_xlfn.XLOOKUP(B3,'Candidate Basedata'!N:N,'Candidate Basedata'!#REF!)) -> #REF! | U13: =IF(B3="","",_xlfn.XLOOKUP(B3,'Candidate Basedata'!N:N,'Candidate Basedata'!G:G)) -> Vendor Partner | V13: =IF(B3="","",_xlfn.XLOOKUP(B3,'Candidate Basedata'!N:N,'Candidate Basedata'!E:E)) -> Dinesh Shiranpel | W13: =IF(B4="","",B4) -> ABZ | X13: =IF(B3="","",_xlfn.XLOOKUP(B3,'Candidate Basedata'!N:N,'Candidate Basedata'!#REF!)) -> #REF! | Z13: =IF(B5="","",B5) -> TYU | AA13: =IF(B6="","",B6) -> b2 | AB13: =IF(B3="","",_xlfn.XLOOKUP(B3,'Candidate Basedata'!N:N,'Candidate Basedata'!#REF!)) -> #REF! | AC13: =IF(B3="","",_xlfn.XLOOKUP(B3,'Candidate Basedata'!N:N,'Candidate Basedata'!#REF!)) -> #REF! | AD13: =IF(B3="","",_xlfn.XLOOKUP(B3,'Candidate Basedata'!N:N,'Candidate Basedata'!#REF!)) -> #REF! | AE13: =IF(B3="","",_xlfn.XLOOKUP(B3,'Candidate Basedata'!N:N,'Candidate Basedata'!#REF!)) -> #REF! | AF13: =IF(D3="","",D3) -> Yes | AG13: =IF(D4="","",D4) -> Yes | AH13: =IF(D5="","",D5) -> Yes | AI13: =IF(D6="","",D6)
A16: SO# | B16: Candidate id | C16: Candidate Name | D16: Skill | E16: Experience | F16: Current Organization | G16: Account Name | H16: Total CTC Offered in LPA | I16: CTC Proposed(Fixed) | J16: Variable Amount | K16: Variable % | L16: Current CTC | M16: Joining Bonus If Any | N16: Band Offered | O16: Designation Offered | P16: Max salary approved for the Band | Q16: Delta to be approved | R16: Reason for Exception (other than max. of salary band) | S16: Expected Joining Date | T16: Employment Type | U16: Source | V16: Recruiter Name | W16: RMG POC | X16: Work Location (City and State) | Y16: To be filled by the Business | Z16: Hiring Manager/Account Manager Name | AA16: Hiring Manager/Account Manager Band | AB16: Project Type | AC16: Client Rate/hr | AD16: GPM % | AE16: Status | AF16: Business Approval(Y/N) | AG16: TA Head Approval(Y/N) | AH16: Move to HR(Y/N) | AI16: Shared to Offer Team On(Date)
A17: 38024355 | B17: 351671 | C17: T M NANDINI | D17: SDET | E17: 3.4yrs | F17: Mindtree | G17: DELL FG | H17: 0 | I17: 0 | J17: 0 | K17: 0 | L17: 550000 | M17: 0 | N17: 0 | O17: 0 | P17: 0 | Q17: 0 | R17: 0 | S17: 0 | T17: Fulltime | U17: Vendor | V17: Pratik Yamawar | W17: ABZ | X17: 0 | Z17: TYU | AA17: b2 | AB17: 0 | AC17: 0 | AD17: 0 | AE17: Client Reject | AF17: Yes | AG17: Yes | AH17: Yes
A18: 31972088 | B18: 419101 | C18: Hema Latha | D18: Java | E18: 14 yr | F18: Infosys | G18: DELL FG | H18: 0 | I18: 0 | J18: 0 | K18: 0 | L18: 1450000 | M18: 0 | N18: 0 | O18: 0 | P18: 0 | Q18: 0 | R18: 0 | S18: 0 | T18: Fulltime | U18: Vendor | V18: Vinay Nambiar | W18: ABZ | X18: 0

Sheet TAC Tracker
A1: Recruiter UID | B1: Recruiter Name | C1: Technology | D1: SO ID | E1: Candidate Phone No | F1: Candidate Name | G1: Candidate ID | H1: Hiring Manager UID | I1: Interview Reward Amount | J1: Candidate Onboard | K1: UID of Employee | L1: Q HR Score | M1: Interviewer Panel UID | N1: Panel Full Name | O1: Panel Contact No | P1: Interview Type | Q1: Weekday Slot | R1: Panel Account | S1: Interview Held Date | T1: Candidate Source | U1: Candidate Status
A2: ='Candidate Basedata'!F2 -> U82721 | B2: ='Candidate Basedata'!E2 -> Rahul Kapoor | C2: ='Candidate Basedata'!I2 -> Java Selenium | D2: ='Candidate Basedata'!D2 -> 38024355 | E2: ='Candidate Basedata'!P2 -> 9553801682 | F2: ='Candidate Basedata'!O2 -> Jacob | G2: ='Candidate Basedata'!N2 -> 484611 | M2: ='Candidate Basedata'!#REF! -> #REF! | N2: ='Candidate Basedata'!#REF! -> #REF! | O2: ='Candidate Basedata'!#REF! -> #REF! | P2: On Account | T2: ='Candidate Basedata'!G2 -> Vendor Partner | U2: ='Candidate Basedata'!L2
A3: ='Candidate Basedata'!F3 -> U82721 | B3: ='Candidate Basedata'!E3 -> Rahul Kapoor | C3: ='Candidate Basedata'!I3 -> SDET | D3: ='Candidate Basedata'!D3 -> 38024355 | E3: ='Candidate Basedata'!P3 -> 9739829708 | F3: ='Candidate Basedata'!O3 -> T M NANDINI | G3: ='Candidate Basedata'!N3 -> 351671 | M3: ='Candidate Basedata'!#REF! -> #REF! | N3: ='Candidate Basedata'!#REF! -> #REF! | O3: ='Candidate Basedata'!#REF! -> #REF! | P3: On Account | T3: ='Candidate Basedata'!G3 -> Vendor Partner | U3: ='Candidate Basedata'!L3 -> Screening IP
A4: ='Candidate Basedata'!F4 -> U82721 | B4: ='Candidate Basedata'!E4 -> Rahul Kapoor | C4: ='Candidate Basedata'!I4 -> QA , Manual tester role | D4: ='Candidate Basedata'!D4 -> 94967553 | E4: ='Candidate Basedata'!P4 -> 9691520066 | F4: ='Candidate Basedata'!O4 -> Vaishali Dixit | G4: ='Candidate Basedata'!N4 -> 354205 | M4: ='Candidate Basedata'!#REF! -> #REF! | N4: ='Candidate Basedata'!#REF! -> #REF! | O4: ='Candidate Basedata'!#REF! -> #REF! | P4: On Account | T4: ='Candidate Basedata'!G4 -> UST Global | U4: ='Candidate Basedata'!L4 -> Rejected
A5: ='Candidate Basedata'!F5 -> 181547 | B5: ='Candidate Basedata'!E5 -> Vinay Nambiar | C5: ='Candidate Basedata'!I5 -> Java | D5: ='Candidate Basedata'!D5 -> 31972088 | E5: ='Candidate Basedata'!P5 -> 9948358570 | F5: ='Candidate Basedata'!O5 -> Hema Latha | G5: ='Candidate Basedata'!N5 -> 419101 | M5: ='Candidate Basedata'!#REF! -> #REF! | N5: ='Candidate Basedata'!#REF! -> #REF! | O5: ='Candidate Basedata'!#REF! -> #REF! | P5: On Account | T5: ='Candidate Basedata'!G5 -> Vendor Partner | U5: ='Candidate Basedata'!L5 -> Interview No show
A6: ='Candidate Basedata'!F6 -> U82721 | B6: ='Candidate Basedata'!E6 -> Rahul Kapoor | C6: ='Candidate Basedata'!I6 -> QA , Manual tester role:- | D6: ='Candidate Basedata'!D6 -> 94967553 | E6: ='Candidate Basedata'!P6 -> 9441095144 | F6: ='Candidate Basedata'!O6 -> Alekya | G6: ='Candidate Basedata'!N6 -> 379458 | M6: ='Candidate Basedata'!#REF! -> #REF! | N6: ='Candidate Basedata'!#REF! -> #REF! | O6: ='Candidate Basedata'!#REF! -> #REF! | P6: On Account | T6: ='Candidate Basedata'!G6 -> UST Global | U6: ='Candidate Basedata'!L6 -> Rejected
A7: ='Candidate Basedata'!F7 -> U82721 | B7: ='Candidate Basedata'!E7 -> Rahul Kapoor | C7: ='Candidate Basedata'!I7 -> UI/UX role | D7: ='Candidate Basedata'!D7 -> 82866188 | E7: ='Candidate Basedata'!P7 -> 9739607439 | F7: ='Candidate Basedata'!O7 -> Rajesh Sah | G7: ='Candidate Basedata'!N7 -> 355575 | M7: ='Candidate Basedata'!#REF! -> #REF! | N7: ='Candidate Basedata'!#REF! -> #REF! | O7: ='Candidate Basedata'!#REF! -> #REF! | P7: On Account | T7: ='Candidate Basedata'!G7 -> UST Global | U7: ='Candidate Basedata'!L7 -> Drop out
A8: ='Candidate Basedata'!F8 -> U82721 | B8: ='Candidate Basedata'!E8 -> Rahul Kapoor | C8: ='Candidate Basedata'!I8 -> UI/UX role | D8: ='Candidate Basedata'!D8 -> 82866188 | E8: ='Candidate Basedata'!P8 -> 9717348292 | F8: ='Candidate Basedata'!O8 -> Ankita Awasthi | G8: ='Candidate Basedata'!N8 -> H8271088 | M8: ='Candidate Basedata'!#REF! -> #REF! | N8: ='Candidate Basedata'!#REF! -> #REF! | O8: ='Candidate Basedata'!#REF! -> #REF! | P8: On Account | T8: ='Candidate Basedata'!G8 -> UST Global | U8: ='Candidate Basedata'!L8 -> Drop out
A9: ='Candidate Basedata'!F9 -> 181547 | B9: ='Candidate Basedata'!E9 -> Vinay Nambiar | C9: ='Candidate Basedata'!I9 -> Java | D9: ='Candidate Basedata'!D9 -> 51907700 | E9: ='Candidate Basedata'!P9 -> 7337067133 | F9: ='Candidate Basedata'!O9 -> Sreedhar Vinjamuri | G9: ='Candidate Basedata'!N9 -> H14387 | M9: ='Candidate Basedata'!#REF! -> #REF! | N9: ='Candidate Basedata'!#REF! -> #REF! | O9: ='Candidate Basedata'!#REF! -> #REF! | P9: On Account | T9: ='Candidate Basedata'!G9 -> Vendor Partner | U9: ='Candidate Basedata'!L9 -> Not responding
A10: ='Candidate Basedata'!F10 -> 181547 | B10: ='Candidate Basedata'!E10 -> Vinay Nambiar | C10: ='Candidate Basedata'!I10 -> Java | D10: ='Candidate Basedata'!D10 -> 57335575 | E10: ='Candidate Basedata'!P10 -> 8106332319 | F10: ='Candidate Basedata'!O10 -> Pokuri Ramanjaneyulu | G10: ='Candidate Basedata'!N10 -> 419812 | M10: ='Candidate Basedata'!#REF! -> #REF! | N10: ='Candidate Basedata'!#REF! -> #REF! | O10: ='Candidate Basedata'!#REF! -> #REF! | P10: On Account | T10: ='Candidate Basedata'!G10 -> Vendor Partner | U10: ='Candidate Basedata'!L10 -> Interview No show
A11: ='Candidate Basedata'!F11 -> 181547 | B11: ='Candidate Basedata'!E11 -> Vinay Nambiar | C11: ='Candidate Basedata'!I11 -> Java | D11: ='Candidate Basedata'!D11 -> 94990037 | E11: ='Candidate Basedata'!P11 -> 9848623920 | F11: ='Candidate Basedata'!O11 -> Sailaja Malyala | G11: ='Candidate Basedata'!N11 -> 418251 | M11: ='Candidate Basedata'!#REF! -> #REF! | N11: ='Candidate Basedata'!#REF! -> #REF! | O11: ='Candidate Basedata'!#REF! -> #REF! | P11: On Account | T11: ='Candidate Basedata'!G11 -> Vendor Partner | U11: ='Candidate Basedata'!L11 -> Interview No show
A12: ='Candidate Basedata'!F12 -> 181547 | B12: ='Candidate Basedata'!E12 -> Vinay Nambiar | C12: ='Candidate Basedata'!I12 -> Java | D12: ='Candidate Basedata'!D12 -> 44173531 | E12: ='Candidate Basedata'!P12 -> 9390911344 | F12: ='Candidate Basedata'!O12 -> G.Ramana Reddy | G12: ='Candidate Basedata'!N12 -> 421816 | M12: ='Candidate Basedata'!#REF! -> #REF! | N12: ='Candidate Basedata'!#REF! -> #REF! | O12: ='Candidate Basedata'!#REF! -> #REF! | P12: On Account | T12: ='Candidate Basedata'!G12 -> Vendor Partner | U12: ='Candidate Basedata'!L12 -> Not interested
A13: ='Candidate Basedata'!F13 -> 181547 | B13: ='Candidate Basedata'!E13 -> Vinay Nambiar | C13: ='Candidate Basedata'!I13 -> Java | D13: ='Candidate Basedata'!D13 -> 44173531 | E13: ='Candidate Basedata'!P13 -> 7893092220 | F13: ='Candidate Basedata'!O13 -> Prem Kumar Jannu | G13: ='Candidate Basedata'!N13 -> 421822 | M13: ='Candidate Basedata'!#REF! -> #REF! | N13: ='Candidate Basedata'!#REF! -> #REF! | O13: ='Candidate Basedata'!#REF! -> #REF! | P13: On Account | T13: ='Candidate Basedata'!G13 -> Vendor Partner | U13: ='Candidate Basedata'!L13 -> Not responding
... A51: ='Candidate Basedata'!F51 -> U82721 | B51: ='Candidate Basedata'!E51 -> Rahul Kapoor | C51: ='Candidate Basedata'!I51 -> .NET,SQL,WEB API | D51: ='Candidate Basedata'!D51 -> 44879198 | E51: ='Candidate Basedata'!P51 -> 9515500554/8639576943 | F51: ='Candidate Basedata'!O51 -> SATISH UDA | G51: ='Candidate Basedata'!N51 -> 437985 | M51: ='Candidate Basedata'!#REF! -> #REF! | N51: ='Candidate Basedata'!#REF! -> #REF! | O51: ='Candidate Basedata'!#REF! -> #REF! | P51: On Account | T51: ='Candidate Basedata'!G51 -> Vendor Partner | U51: ='Candidate Basedata'!L51

Sheet Sheet3
A1: Anjali Dwivedi | C1: External
A2: Reema | C2: Internal
A3: Sivanesh
A4: Ashna

Sheet Sheet2
A1: vendor | D1: Staff Aug positions | G1: US | I1: low Priority
A2: Talent Scout | D2: Managed Services | G2: UK | I2: High priority
A3: Linkedin | G3: INDIA-APAC | I3: Slow moving
A4: Job boards
A5: Employee referral
A6: Vendor - contract
